Workbook
Name \A: #REF!
Name \A: #REF!
Name \A: #REF!
Name \A: #REF!
Name \A: #REF!
Name \A: #REF!
Name \A: #REF!
Name \A: #REF!
Name \A: #REF!
Name \A: #REF!
Name \b: '[1]Water Demand'!#REF!
Name \b: '[1]Water Demand'!#REF!
Name \b: '[1]Water Demand'!#REF!
Name \b: '[1]Water Demand'!#REF!
Name \b: '[1]Water Demand'!#REF!
Name \b: '[1]Water Demand'!#REF!
Name \b: '[1]Water Demand'!#REF!
Name \b: '[1]Water Demand'!#REF!
Name \b: '[1]Water Demand'!#REF!
Name \b: '[1]Water Demand'!#REF!
Name \berr: '[1]Water Demand'!#REF!
Name \berr: '[1]Water Demand'!#REF!
Name \berr: '[1]Water Demand'!#REF!
Name \berr: '[1]Water Demand'!#REF!
Name \berr: '[1]Water Demand'!#REF!
Name \berr: '[1]Water Demand'!#REF!
Name \berr: '[1]Water Demand'!#REF!
Name \berr: '[1]Water Demand'!#REF!
Name \berr: '[1]Water Demand'!#REF!
Name \berr: '[1]Water Demand'!#REF!
Name \c: '[1]Water Demand'!#REF!
Name \c: '[1]Water Demand'!#REF!
Name \c: '[1]Water Demand'!#REF!
Name \c: '[1]Water Demand'!#REF!
Name \c: '[1]Water Demand'!#REF!
Name \c: '[1]Water Demand'!#REF!
Name \c: '[1]Water Demand'!#REF!
Name \c: '[1]Water Demand'!#REF!
Name \c: '[1]Water Demand'!#REF!
Name \c: '[1]Water Demand'!#REF!
Name \cerr: '[1]Water Demand'!#REF!
Name \cerr: '[1]Water Demand'!#REF!
Name \cerr: '[1]Water Demand'!#REF!
Name \cerr: '[1]Water Demand'!#REF!
Name \cerr: '[1]Water Demand'!#REF!
Name \cerr: '[1]Water Demand'!#REF!
Name \cerr: '[1]Water Demand'!#REF!
Name \cerr: '[1]Water Demand'!#REF!
Name \cerr: '[1]Water Demand'!#REF!
Name \cerr: '[1]Water Demand'!#REF!
Name \e: #REF!
Name \e: #REF!
Name \e: #REF!
Name \e: #REF!
Name \e: #REF!
Name \e: #REF!
Name \e: #REF!
Name \e: #REF!
Name \e: #REF!
Name \e: #REF!

Sheet SUMMARY
A1: Nepal Government
A2: Ministry of Physical Planning and Work
A3: Department of Water Supply and Sewerage
A4: Drinking Water Quality Improvement Project
A6: Summary of Cost
A7: Project: …………………... Water Quality Improvement Project
A8: Q = | B8: 8.0 LPS
A10: S.N. | B10: Description of Works | C10: No. | D10: Quantity | F10: Total Amount
F11: (NRs.)
A12: 1 | B12: Land Acquisition | C12: 1 | D12: Ropani | E12: 100000 | F12: =E12*C12 -> 100000
A13: 2 | B13: Site Development | C13: 1 | D13: job | E13: =COST_ALL!$G$213 -> 493305.6 | F13: =E13*C13 -> 493305.6
A14: 3 | B14: Intake Maintenance | C14: 1 | D14: No. | E14: …………. | F14: …………….
A15: 4 | B15: Plain Sedimentation Tank | C15: 1 | D15: No. | E15: =COST_ALL!G45 -> 2384849.5 | F15: =E15*C15 -> 2384849.5
A16: 5 | B16: Horizontal Roughing Filter | C16: 1 | D16: No. | E16: =COST_ALL!G97 -> 3462456.4 | F16: =E16*C16 -> 3462456.4
A17: 6 | B17: Slow Sand Filter | C17: 1 | D17: No. | E17: =COST_ALL!G160 -> 10288656 | F17: =E17*C17 -> 10288656
A18: 7 | B18: Disinfection Chamber | C18: 1 | D18: No. | E18: =COST_ALL!G179 -> 24637.46 | F18: =E18*C18 -> 24637.46
A19: 8 | B19: Sand Wash Platform | C19: 1 | D19: No. | E19: =COST_ALL!G196 -> 80287.86 | F19: =E19*C19 -> 80287.86
A20: 9 | B20: Pipes and Fittings Procurement | C20: 1 | D20: job | E20: =COST_ALL!G426 -> 3775975.6 | F20: =E20*C20 -> 3775975.6
A21: 10 | B21: Pipe Line Relaying and Jointing | C21: 1 | D21: job | E21: 27334 | F21: =E21*C21 -> 27334
A22: 8 | B22: Chlorine Dosing Unit with accessories and Fitting | C22: 1 | D22: No. | E22: 70000 | F22: =E22*C22 -> 70000
A23: 11 | B23: Compound Wall with Barbed Wire Fencing
B24: and Gate | C24: 1 | D24: job | E24: =COST_ALL!G233 -> 3067323 | F24: =E24*C24 -> 3067323
A25: 13 | B25: Chaukidar Quarters | C25: 1 | D25: No. | E25: =COST_ALL!G297 -> 1251857.9 | F25: =E25*C25 -> 1251857.9
A26: 12 | B26: Reservoir Maintenance | C26: 1 | D26: No. | E26: 500000 | F26: …………….
A27: 13 | B27: Protection Works | C27: 1 | D27: job | E27: =COST_ALL!G357 -> 4519468.6 | F27: =E27*C27 -> 4519468.6
A28: 14 | B28: Training and Orientation / Water Quality Campaigns | C28: 1 | D28: package | E28: 94350 | F28: =E28*C28 -> 94350
B29: Sub Total | F29: =ROUND(SUM(F12:F28),2) -> 29640502
B30: 2.5 % Contingencies | F30: =ROUND((F29*0.025),2) -> 741012.55
B31: Grand Total | F31: =ROUND(SUM(F29:F30),2) -> 30381515

Sheet Salient feature
A1: Salient Features ( Schemewise ) of Project
B3: District: Kathmandu
A4: 1 | B4: Name of Project | C4: ='Entry for Rates'!F4 -> 0
A5: 2 | B5: Name of District | D5: Kathmandu | E5: Kathmandu
A6: 3 | B6: Name of Municipality | D6: Shankharapur | E6: Shankharapur
A7: 4 | B7: Wards Covered | D7: 3 | E7: 4
A8: 5 | B8: Number of Schemes | D8: 1 | E8: 1
A9: Sn | B9: Parameters | C9: Unit | D9: ='sum cost_All'!D3:F3 -> Fedi (Sc-1) | E9: Damai Kholsi (Sc-2)
A10: A. | B10: General Parameter
A11: 1 | B11: Households(Survey year:2017) | C11: No. | D11: 133 | E11: 134
A12: 2 | B12: Population(Survey year:2017) | C12: No. | D12: 857 | E12: 763
A13: 3 | B13: Households(Base year:2019) | C13: No. | D13: =D11*(1+1.31/100)^2 -> 136.50742 | E13: =E11*(1+1.31/100)^2 -> 137.5338
A14: 4 | B14: Population(Base year:2019) | C14: No. | D14: 898 | E14: 788
A15: 5 | B15: Households(Design year:2039) | C15: No. | D15: =D11*(1+1.31/100)^22 -> 177.09348 | E15: =E11*(1+1.31/100)^22 -> 178.42501
A16: 6 | B16: Population(Design year:2039) | C16: No. | D16: 1155 | E16: 1023
A17: 1 | B17: Design Period | C17: Yrs. | D17: 20 | E17: 20
A18: 2 | B18: Annual growth rate | C18: % | D18: 3.5 | E18: 3.5
A19: B. | B19: Source Information
A20: 1 | B20: Source Name | D20: Fedi | E20: Damai Kholsi
A21: =A20+1 -> 2 | B21: Source Type & Number | C21: Type/No. | D21: Spring | E21: Spring
A22: =A21+1 -> 3 | B22: Tapped Discharge source - | C22: Lps | D22: 20 | E22: 12
A23: =A22+1 -> 4 | B23: Approximate Distance from Project Site | C23: km | D23: 1 | E23: 1.02
A24: 4 | B24: Water Quality of Source | D24: Fair | E24: Fair
A25: C. | B25: Water provision & Demand
A26: 1 | B26: Provision for Domestic use | C26: lpcd | D26: 69300 | E26: 61380
A27: 3 | B27: Provision for Institutional use | C27: lpcd | D27: 4320 | E27: 2000
A28: 4 | B28: Provision for Live Stock | C28: Yes/No | D28: No | E28: No
A29: 5 | B29: Total Water Demand (Design Year) | C29: Lpd | D29: =D26+D27 -> 73620 | E29: =E26+E27 -> 63380
A30: C. | B30: Project Components
A31: 1 | B31: Actual Length of Transmission Main | C31: km | D31: ='pip-line'!F18/1000 -> 0.11 | E31: ='pip-line'!F19/1000 -> 0
A32: 2 | B32: Actual Length of Distribution Pipe Line | C32: km | D32: ='pip-line'!F42/1000 -> 0 | E32: ='pip-line'!F41/1000 -> 2.175
A33: 3 | B33: Institutional connections | C33: No. | D33: 2 | E33: 1
A34: 4 | B34: Number of Private Connection Provided | C34: No. | D34: =D33+D13 -> 138.50742 | E34: =E33+E13 -> 138.5338
A35: 5 | B35: Reservoir Number/ Capacity | C35: m³/no | D35: 20,4 | E35: 20,2
A36: 6 | B36: Total Number of CC, DC, IC, VC & AVC | C36: No. | D36: =SUM('sum cost_All'!E34:E36) -> 12 | E36: =SUM('sum cost_All'!H34:H36) -> 6
A37: 7 | B37: Crossing | C37: No. | D37: No | E37: No
A38: 8 | B38: Institutional latrine | C38: No. | D38: No | E38: No
A39: E. | B39: Project Cost Data
A40: 1 | B40: Total Estimated Cost(without physical & price adjustment contingencies | C40: NRs. | D40: ='sum cost_All'!F54 -> 39436766 | E40: ='sum cost_All'!I54 -> 20106828
A41: =A40+1 -> 2 | B41: Average Per Capita Cost at Base Year | C41: NRs. | D41: =D40/D14 -> 43916.221 | E41: =E40/E14 -> 25516.279
A42: =A41+1 -> 3 | B42: Average Per Capita Cost at Design Year | C42: NRs. | D42: =D40/D16 -> 34144.387 | E42: =E40/E16 -> 19654.768
A43: 2 | B43: Community Contribution Amount as per Estimate | C43: NRs. | D43: =D40*10% -> 3943676.6 | E43: 4011500.3
A44: 3 | B44: Community Contribution as per % of Estimate | C44: % | D44: 0.1 | E44: 10.5
A45: =A44+1 -> 4 | B45: Number of WUSC Members/VMW | C45: No.

Sheet sum cost_All
A1: Summary of Cost ( With Schemewise Cost )
B2: Name of Scheme: Sankhu Drinking Water Supply Project
A3: Sn | B3: Items | C3: Unit | D3: Fedi (Sc-1) | G3: Damai Kholsi (Sc-2) | J3: Total
D4: Unit Rate | E4: Qty | F4: Amount | G4: Unit Rate | H4: Qty | I4: Amount | J4: Qty | K4: Amount
A5: A | B5: Community Education Awareness
B6: Program
A7: 1 | B7: Pre-construction Training | C7: no | J7: 1 | K7: 25000
A8: 2 | B8: Appraisal & Comm. Preparation | C8: no | J8: 1 | K8: 14000
A9: 3 | B9: VMWs Training | C9: no | J9: 1 | K9: 15000
A10: 4 | B10: Pre-handover Training | C10: no | J10: 1 | K10: 15000
A11: 5 | B11: Motivators/Volunteers Training | C11: no | J11: 1 | K11: 10000
B12: Total A | K12: =SUM(K7:K11) -> 79000
A13: B | B13: Water Supply & Sanitation
A14: B1 | B14: Civil Works
A15: 1 | B15: Detailed Survey & Design Work | C15: % | D15: 150000 | E15: 0 | F15: =D15*E15 -> 0 | G15: ='[59]sum cost_All'!D16 -> 150000 | H15: 0 | I15: =H15*G15 -> 0 | J15: =E15+H15 -> 0 | K15: =F15+I15 -> 0
A16: =A15+1 -> 2 | B16: Stream intake(without VC) | C16: no | D16: =Cost_In_1!F30 -> 1665211.5 | E16: =FittingsSummary!P6 -> 1 | F16: =E16*D16 -> 1665211.5 | G16: =int!J64 -> 264382.25 | H16: 1 | I16: =H16*G16 -> 264382.25 | J16: =E16+H16 -> 2 | K16: =F16+I16 -> 1929593.8
A17: 3 | B17: Collection Chamber | C17: no | D17: ='CC-DC'!J52 -> 237257.56 | E17: 1 | F17: =D17*E17 -> 237257.56 | G17: ='[59]sum cost_All'!D18 -> 155943.49 | H17: 1 | I17: =H17*G17 -> 155943.49 | J17: =E17+H17 -> 2 | K17: =F17+I17 -> 393201.05
A18: 4 | B18: Plain Sedimentation Tank | C18: no | F18: Existing | G18: =COST_ALL!G45 -> 2384849.5 | H18: 1 | I18: =H18*G18 -> 2384849.5 | J18: =E18+H18 -> 1 | K18: =I18 -> 2384849.5
A19: 5 | B19: Horizontal Roughing Filter | C19: no | F19: Existing | G19: =COST_ALL!G97 -> 3462456.4 | H19: 1 | I19: =H19*G19 -> 3462456.4 | J19: =E19+H19 -> 1 | K19: =I19 -> 3462456.4
A20: 6 | B20: Slow Sand Filter | C20: no | F20: Existing | G20: =COST_ALL!G160 -> 10288656 | H20: 1 | I20: =H20*G20 -> 10288656 | J20: =E20+H20 -> 1 | K20: =I20 -> 10288656
A21: 7 | B21: Disinfection Chamber | C21: no | F21: Existing | G21: =COST_ALL!G179 -> 24637.46 | H21: 1 | I21: =H21*G21 -> 24637.46 | J21: =E21+H21 -> 1 | K21: =I21 -> 24637.46
A22: 8 | B22: Sand Wash Platform | C22: no | G22: =COST_ALL!G196 -> 80287.86 | H22: 1 | I22: =H22*G22 -> 80287.86 | J22: =E22+H22 -> 1 | K22: =F22+I22 -> 80287.86
A23: 9 | B23: 400 cum Reservoir at Fedi and Damai Kholsi | C23: no | D23: ='Cost RVT-400'!F42 -> 7691591.2 | E23: 1 | F23: =D23*E23 -> 7691591.2 | G23: ='Cost RVT-400'!F42 -> 7691591.2 | H23: 1 | I23: =H23*G23 -> 7691591.2 | K23: =F23+I23 -> 15383182
A24: 9 | B24: Pipes and Fittings Procurement | C24: no | J24: 1 | K24: =COST_ALL!G426 -> 3775975.6
A25: 10 | B25: Pipe Line Relaying and Jointing | C25: no | G25: =COST_ALL!G340 -> 174399.24 | H25: 1 | I25: =H25*G25 -> 174399.24 | J25: =E25+H25 -> 1 | K25: =F25+I25 -> 174399.24
A26: 12 | B26: Chlorine Dosing Unit with accessories and Fitting | C26: no
A27: 13 | B27: Compound Wall with Barbed Wire Fencing and Gate | C27: no | G27: =COST_ALL!G233 -> 3067323 | H27: 1 | I27: =H27*G27 -> 3067323 | J27: =E27+H27 -> 1 | K27: =F27+I27 -> 3067323
A28: 14 | B28: Retaining wall | C28: no | D28: =COST_ALL!$G$310 -> 26921.87 | E28: 100 | F28: =D28*E28 -> 2692187 | G28: =COST_ALL!$G$310 -> 26921.87 | H28: 50 | I28: =G28*H28 -> 1346093.5 | J28: =E28+H28 -> 150 | K28: =F28+I28 -> 4038280.5
A29: 15 | B29: PCC pitching in river | C29: m | E29: 50 | F29: =Cost_In_1!F49 -> 231671.29 | K29: =F29+I29 -> 231671.29
A30: 15 | B30: Chaukidar Quarters | C30: no | D30: =COST_ALL!G297 -> 1251857.9 | E30: 1 | F30: =D30*E30 -> 1251857.9 | G30: =COST_ALL!G297 -> 1251857.9 | H30: 1 | I30: =G30*H30 -> 1251857.9 | K30: =F30+I30 -> 2503715.8
A31: 16 | B31: WTP Maintenance including plaster in RVT | C31: no | D31: 500000 | E31: 1 | F31: =D31*E31 -> 500000 | J31: =E31+H31 -> 1 | K31: =F31+I31 -> 500000
A32: 17 | B32: Protection Works | C32: no | G32: =COST_ALL!G354+COST_ALL!G355+COST_ALL!G356 -> 481188.08 | H32: 1 | I32: =G32*H32 -> 481188.08 | J32: =E32+H32 -> 1 | K32: =F32+I32 -> 481188.08
A33: =A32+1 -> 18 | B33: Private Connection (including institution) | C33: no | D33: =Private_Con!J25 -> 13011.509 | E33: 0 | F33: =D33*E33 -> 0 | G33: ='[59]sum cost_All'!D24 -> 9723.79 | H33: ='[59]sum cost_All'!E24 -> 139 | I33: =G33*H33 -> 1351606.8 | J33: =E33+H33 -> 139 | K33: =F33+I33 -> 1351606.8
A34: 18 | B34: Distribution Chamber (Two chamber) | C34: no | D34: ='CC-DC'!J103 -> 115359.08 | E34: =FittingsSummary!J6 -> 1 | F34: =D34*E34 -> 115359.08 | G34: ='[59]sum cost_All'!D25 -> 79374.31 | H34: 1 | I34: =G34*H34 -> 79374.31 | J34: =E34+H34 -> 2 | K34: =F34+I34 -> 194733.39
A35: 19 | B35: Air Valve Chamber at Junction | C35: no | D35: ='vc-bpt'!J24 -> 19814.482 | E35: 4 | F35: =D35*E35 -> 79257.928 | G35: ='[59]sum cost_All'!D26 -> 12956.91 | H35: 2 | I35: =G35*H35 -> 25913.82 | J35: =E35+H35 -> 6 | K35: =F35+I35 -> 105171.75
A36: 20 | B36: Washout Valve Chamber | C36: no | D36: ='vc-bpt'!J62 -> 43416.613 | E36: 7 | F36: =D36*E36 -> 303916.29 | G36: ='[59]sum cost_All'!D27 -> 28436.44 | H36: 3 | I36: =G36*H36 -> 85309.32 | J36: =E36+H36 -> 10 | K36: =F36+I36 -> 389225.61
A37: 21 | B37: Sectional Valve Chamber at Junction | C37: no | D37: ='vc-bpt'!J62 -> 43416.613 | E37: =FittingsSummary!S6 -> 6 | F37: =D37*E37 -> 260499.68 | G37: ='[59]sum cost_All'!D28 -> 28436.44 | H37: 1 | I37: =G37*H37 -> 28436.44 | J37: =E37+H37 -> 7 | K37: =F37+I37 -> 288936.12
A38: 22 | B38: BPC/IC | C38: no | D38: ='vc-bpt'!J114 -> 60794.113 | E38: 1 | F38: =D38*E38 -> 60794.113 | G38: ='[59]sum cost_All'!D29 -> 43505.51 | H38: 1 | I38: =G38*H38 -> 43505.51 | J38: =E38+H38 -> 2 | K38: =F38+I38 -> 104299.62
A39: 23 | B39: Roof Truss in existing | C39: no | D39: =Abstract_TRUSS!$F$15 -> 2819891.3 | E39: 1 | F39: =D39*E39 -> 2819891.3 | G39: =Abstract_TRUSS!$F$15 -> 2819891.3 | H39: 1 | I39: =G39*H39 -> 2819891.3 | J39: =E39+H39 -> 2 | K39: =F39+I39 -> 5639782.7
A40: 24 | B40: Sump Well System | D40: ='Sump well'!$I$55 -> 2095279.7 | E40: 1 | F40: =D40*E40 -> 2095279.7 | J40: =E40+H40 -> 1 | K40: =F40+I40 -> 2095279.7
A41: 25 | B41: Pipe Support for pipeline | C41: no | D41: ='Pipe Support'!J33 -> 23323.227 | E41: 20 | F41: =E41*D41 -> 466464.53 | G41: =$D$41 -> 23323.227 | H41: 12 | I41: =G41*H41 -> 279878.72 | J41: =E41+H41 -> 32 | K41: =F41+I41 -> 746343.26
A42: 26 | B42: Pipeline works ( E/W and jointing )
B43: i. Transmission | C43: Km | E43: 0.175 | H43: ='[59]sum cost_All'!E33 -> 1.18 | J43: =E43+H43 -> 1.355 | K43: ='pip-line'!I24 -> 434010.58
B44: ii. Distribution | C44: Km | E44: 2.87 | H44: ='[59]sum cost_All'!E34 -> 3.2 | J44: =E44+H44 -> 6.07 | K44: ='pip-line'!I47 -> 5716854
A45: 27 | B45: Transportation of Pipes, Fittings & Tools from store to site) | C45: % | E45: 1 | H45: ='[59]sum cost_All'!E35 -> 1 | J45: =E45+H45 -> 2 | K45: ='pip-line'!I56 -> 0
B46: Sub-Total (B1) | F46: =SUM(F15:F45) -> 20471239 | I46: =SUM(I15:I45) -> 35387582 | K46: =SUM(K16:K45) -> 65785662
A47: B2 | B47: Materials & Equipments
A48: 1 | B48: Pipes | C48: km | E48: =Pipe!E50/1000 -> 5.332 | F48: =Pipe!G50 -> 18965527 | H48: ='[59]sum cost_All'!E39 -> 3.97 | J48: =E48+H48 -> 9.302 | K48: =F48+I48 -> 18965527
A49: 2 | B49: Fittings | C49: % | J49: 1 | K49: =FittingsSummary!AC128 -> 1119506.3
A50: 3 | B50: Tools & Plants | C50: % | J50: 1 | K50: =tools!H41 -> 141602.11
B51: Sub-Total (B2) | F51: =SUM(F48:F50) -> 18965527 | I51: ='[59]sum cost_All'!F42 -> 2275899.6 | K51: =SUM(K48:K50) -> 20226636
B52: Total B (B1+B2) | F52: =F46+F51 -> 39436766 | I52: ='[59]sum cost_All'!F43 -> 20027828 | K52: =K51+K46 -> 86012297
B54: Total (A+B) | F54: =F12+F52 -> 39436766 | I54: ='[59]sum cost_All'!F44 -> 20106828 | K54: =K12+K52 -> 86091297
A55: C | B55: Contingencies & Overhead
A56: 1 | B56: Contingencies 2 % of (A+B) | F56: =F54*0.02 -> 788735.33 | I56: =I54*0.02 -> 402136.56 | K56: =K54*0.02 -> 1721825.9
A57: 2 | B57: Sanitation Component 2 % of (A+B) | F57: =F54*0.02 -> 788735.33 | I57: =I54*0.02 -> 402136.56 | K57: =K54*0.02 -> 1721825.9
B58: Total C | F58: =SUM(F56:F57) -> 1577470.7 | I58: =SUM(I56:I57) -> 804273.13 | K58: =SUM(K56:K57) -> 3443651.9
B59: Total Cost of Scheme (A+B+C) | F59: =F54+F58 -> 41014237 | I59: =I54+I58 -> 20911101 | K59: =K54+K58 -> 89534949
B60: Add Physical Contingencies@10% | F60: =F59*0.1 -> 4101423.7 | I60: =I59*0.1 -> 2091110.1 | K60: =K59*0.1 -> 8953494.9
B61: Add Price Escalation@10% | F61: =F59*0.1 -> 4101423.7 | I61: =I59*0.1 -> 2091110.1 | K61: =K59*0.1 -> 8953494.9
B62: Total Cost of Project : | F62: =SUM(F59:F61) -> 49217085 | I62: =SUM(I59:I61) -> 25093322 | K62: =SUM(K59:K61) -> 1.0744194e+08

Sheet COST_ALL
A1: Abstract of Cost
A3: Component: Plain Sedimentation Tank
A5: S.N. | B5: Description of Works | C5: No. | D5: Quantity | E5: Unit | F5: Unit Rate | G5: Total Amount
A6: 1 | B6: Site Clearence | C6: 1 | D6: =Qnty_ALL!G6 -> 84 | E6: m2 | F6: =Rates!F7 -> 149.5 | G6: =ROUND((C6*D6*F6),2) -> 12558
A7: 2 | B7: Earth Work in Excavation in
B8: Foundation in Boulder Mixed Soil | C8: 1 | D8: =Qnty_ALL!G13 -> 142.92 | E8: m 3 | F8: =Rates!F10 -> 1883.36 | G8: =ROUND((C8*D8*F8),2) -> 269169.81
A9: 3 | B9: Earth Filling in Foundation | C9: 1 | D9: =Qnty_ALL!G25 -> 30.13 | E9: m 3 | F9: =Rates!F16 -> 710.7 | G9: =ROUND((C9*D9*F9),2) -> 21413.39
A10: 4 | B10: Stone Soling with sand packing on
B11: Base of Foundation, | C11: 1 | D11: =Qnty_ALL!G30 -> 15.02 | E11: m 3 | F11: =Rates!F20 -> 11802.3 | G11: =ROUND((C11*D11*F11),2) -> 177270.55
A12: 5 | B12: Laying of P.C.C. 1:3:6 on Base of
B13: Foundation | C13: 1 | D13: =Qnty_ALL!G35 -> 7.8 | E13: m 3 | F13: =Rates!F31 -> 14810.58 | G13: =ROUND((C13*D13*F13),2) -> 115522.52
A14: 6 | B14: Laying of One Layer Tarfelt Over
B15: Lean Concrete | C15: 1 | D15: =Qnty_ALL!G38 -> 72.04 | E15: m 2 | F15: =Analysis!$R$192 -> 912.3 | G15: =ROUND((C15*D15*F15),2) -> 65722.09
A16: 7 | B16: P.C.C (1: 1.5:3) Works for R.C.C | C16: 1 | D16: =Qnty_ALL!G62 -> 27.78 | E16: m 3 | F16: =Rates!F33 -> 17163.13 | G16: =ROUND((C16*D16*F16),2) -> 476791.75
A17: 8 | B17: Centring and Shuttering Works for
B18: P.C.C. and R.C.C Works | C18: 1 | D18: =Qnty_ALL!G83 -> 191.39 | E18: m 2 | F18: =Rates!F40 -> 1322.68 | G18: =ROUND((C18*D18*F18),2) -> 253147.73
A19: 9 | B19: Reiforcement Works with Deformed
B20: bars Bars Including supplying,
B21: Cutting, Bending and Placing in
B22: Position | C22: 1 | D22: =Qnty_ALL!G131 -> 5003.04 | E22: kg | F22: =Rates!F39 -> 125.35 | G22: =ROUND((C22*D22*F22),2) -> 627131.06
A23: 10 | B23: Brick Masonry Work in 1:6
B24: Cement Sand mortar | C24: 1 | D24: =Qnty_ALL!G138 -> 2.62 | E24: m 2 | F24: =Rates!F28 -> 19440.44 | G24: =ROUND((C24*D24*F24),2) -> 50933.95
A25: 11 | B25: 12.5 mm Thick Cement Sand Plaster
B26: in 1:3 Mortar with 2% Water Proof
B27: Compound | C27: 1 | D27: =Qnty_ALL!G174 -> 171.55 | E27: m 2 | F27: =Rates!F65 -> 497.69 | G27: =ROUND((C27*D27*F27),2) -> 85378.72
A28: 12 | B28: 20 mm Thick Cement Sand Plaster in
B29: 1:4 Mortar in Base Slab | C29: 1 | D29: =Qnty_ALL!G178 -> 96 | E29: m 2 | F29: =Rates!F62 -> 637.57 | G29: =ROUND((C29*D29*F29),2) -> 61206.72
A30: 13 | B30: 3 mm Thick Punning in 1: 1 Cement
B31: Sand Mortar | C31: 1 | D31: =Qnty_ALL!G184 -> 7.8 | E31: m 2 | F31: =Rates!F67 -> 346.26 | G31: =ROUND((C31*D31*F31),2) -> 2700.83
A32: 14 | B32: Two Coat of Enamel Paint of
B33: Appropriate Colour on Exposed
B34: Surface of Tank | C34: 1 | D34: =Qnty_ALL!G187 -> 68.89 | E34: m 2 | F34: =Rates!F70 -> 400.29 | G34: =ROUND((C34*D34*F34),2) -> 27575.98
A35: 15 | B35: Installation of 4 inch dia. Pipe
B36: Pieces and Fittings for Inlet, Outlet and
B37: W/O Complete as per Drawing and
B38: Specification | D38: lump sum | G38: 2000
A39: 16 | B39: Standard Manhole Cover (60cm dia)
B40: including M.S. Angle of 1.5" in
B41: Size including Fixing all Complete as
B42: per Drawing and Specification | C42: 1 | D42: =Qnty_ALL!G194 -> 2 | E42: No. | F42: 6500 | G42: =ROUND((C42*D42*F42),2) -> 13000
A43: 17 | B43: Site Development around the
B44: Sedimentation Unit | C44: 1 | D44: 30 | E44: m | F44: =$E$213 -> 4110.88 | G44: =ROUND((C44*D44*F44),2) -> 123326.4
D45: Total | G45: =ROUND(SUM(G6:G44),2) -> 2384849.5
A47: Component: Horizontal Roughing Filter
A49: S.N. | B49: Description of Works | C49: No. | D49: Quantity | E49: Unit | F49: Unit Rate | G49: Total Amount
A50: 1 | B50: Site Clearence | C50: 1 | D50: =Qnty_ALL!G199 -> 81 | E50: m2 | F50: =Rates!F7 -> 149.5 | G50: =ROUND((C50*D50*F50),2) -> 12109.5
A51: 2 | B51: Earth Work in Excavation in
B52: Foundation in Boulder Mixed Soil | C52: 1 | D52: =Qnty_ALL!G205 -> 129.38 | E52: m 3 | F52: =Rates!F10 -> 1883.36 | G52: =ROUND((C52*D52*F52),2) -> 243669.12
A53: 3 | B53: Earth Filling in Foundation in Boulder
B54: Mixed Soil | C54: 1 | D54: =Qnty_ALL!G221 -> 9.54 | E54: m 3 | F54: =Rates!F16 -> 710.7 | G54: =ROUND((C54*D54*F54),2) -> 6780.08
A55: 4 | B55: Stone Soling with sand packing on
B56: Base of Foundation | C56: 1 | D56: =Qnty_ALL!G226 -> 16.87 | E56: m 3 | F56: =Rates!F20 -> 11802.3 | G56: =ROUND((C56*D56*F56),2) -> 199104.8
A57: 5 | B57: Laying of P.C.C. 1:3:6 on Base of
B58: Foundation | C58: 1 | D58: =Qnty_ALL!G231 -> 8.58 | E58: m 3 | F58: =Rates!F31 -> 14810.58 | G58: =ROUND((C58*D58*F58),2) -> 127074.78
A59: 6 | B59: Laying of One Layer Tarfelt Over
B60: Lean Concrete | C60: 1 | D60: =Qnty_ALL!G233 -> 89.3 | E60: m 2 | F60: =Analysis!$R$192 -> 912.3 | G60: =ROUND((C60*D60*F60),2) -> 81468.39
A61: 7 | B61: P.C.C (1: 1.5:3) Works for R.C.C | C61: 1 | D61: =Qnty_ALL!G254 -> 36.44 | E61: m 3 | F61: =Rates!F33 -> 17163.13 | G61: =ROUND((C61*D61*F61),2) -> 625424.46
A62: 8 | B62: Centring and Shuttering Works for
B63: P.C.C. and R.C.C Works | C63: 1 | D63: =Qnty_ALL!G274 -> 252.93 | E63: m 2 | F63: =Rates!F40 -> 1322.68 | G63: =ROUND((C63*D63*F63),2) -> 334545.45
A64: 9 | B64: Reiforcement Works with Deformed bars
B65: Bars Including Supplying,Cutting,
B66: Bending and Placing in Position | C66: 1 | D66: =Qnty_ALL!G286 -> 1935.66 | E66: kg | F66: =Rates!F39 -> 125.35 | G66: =ROUND((C66*D66*F66),2) -> 242634.98
A67: 10 | B67: Brick Masonry Work in 1:4
B68: Cement Sand mortar | C68: 1 | D68: =Qnty_ALL!G327 -> 1.22 | E68: m 3 | F68: =Rates!F28 -> 19440.44 | G68: =ROUND((C68*D68*F68),2) -> 23717.34
A69: 11 | B69: 12.5 mm Thick Cement Sand Plaster in
B70: 1:3 Mortar with 2% Water Proof
B71: Compound | C71: 1 | D71: =Qnty_ALL!G368 -> 271.17 | E71: m 2 | F71: =Rates!F65 -> 497.69 | G71: =ROUND((C71*D71*F71),2) -> 134958.6
A72: 12 | B72: 20 mm Thick Cement Sand Plaster in
B73: 1:4 Mortar in | C73: 1 | D73: =Qnty_ALL!G374 -> 67.2 | E73: m 2 | F73: =Rates!F62 -> 637.57 | G73: =ROUND((C73*D73*F73),2) -> 42844.7
A74: 13 | B74: 3 mm Thick Punning in 1: 1 Cement
B75: Sand Mortar | C75: 1 | D75: =Qnty_ALL!G380 -> 250.76 | E75: m 2 | F75: =Rates!F67 -> 346.26 | G75: =ROUND((C75*D75*F75),2) -> 86828.16
A76: 14 | B76: Two Coat of Enamel Paint of
B77: Appropriate Colour on Exposed
B78: Surface of Tank | C78: 1 | D78: =Qnty_ALL!G381 -> 78.53 | E78: m 2 | F78: =Rates!F70 -> 400.29 | G78: =ROUND((C78*D78*F78),2) -> 31434.77
A79: 15 | B79: Preparation and Placing of 40-20 mm
B80: dia. Gravel Filter Media as per
B81: Specification | C81: 1 | D81: =Qnty_ALL!G386 -> 21 | E81: m 3 | F81: ='Mat-Collect_2'!$G$189 -> 9888.55 | G81: =ROUND((C81*D81*F81),2) -> 207659.55
A82: 16 | B82: Preparation and Placing of 20-10 mm
B83: dia. Gravel Filter Media as per
B84: Specification | C84: 1 | D84: =Qnty_ALL!G389 -> 31.5 | E84: m 3 | F84: ='Mat-Collect_2'!$G$169 -> 12331.61 | G84: =ROUND((C84*D84*F84),2) -> 388445.72
A85: 17 | B85: Preparation and Placing of 04-10 mm
B86: dia. Gravel Filter Media as per
B87: Specification | C87: 1 | D87: =Qnty_ALL!G392 -> 31.5 | E87: m 3 | F87: ='Mat-Collect_2'!$G$150 -> 17685.55 | G87: =ROUND((C87*D87*F87),2) -> 557094.83
A88: 18 | B88: Installation of 4 inch dia. Pipe
B89: Pipe Pieces and Fittings for Inlet,
B90: Outlet and W/O Complete including
B91: gates as per Drawing and Specification | C91: 1 | D91: =Qnty_ALL!G396 -> 1 | E91: Job | F91: 5000 | G91: =C91*D91*F91 -> 5000
A92: 19 | B92: Standard Manhole Cover (60cm dia)
B93: including M.S. Angle of 1.5" in
B94: Size including Fixing all Complete as
B95: per Drawing and Specification | C95: 1 | D95: =Qnty_ALL!G400 -> 2 | E95: Nos. | F95: 6500 | G95: =ROUND((C95*D95*F95),2) -> 13000
A96: 20 | B96: Site Development around the HRF | C96: 1 | D96: 24 | E96: m | F96: =$E$213 -> 4110.88 | G96: =ROUND((C96*D96*F96),2) -> 98661.12
D97: Total | G97: =ROUND(SUM(G50:G96),2) -> 3462456.4
A99: Component: Slow Sand Filter
A101: S.N. | B101: Description of Works | C101: No. | D101: Quantity | E101: Unit | F101: Unit Rate | G101: Total Amount
A102: 1 | B102: Site Clearence | C102: 1 | D102: =Qnty_ALL!G405 -> 196 | E102: m2 | F102: =Rates!F7 -> 149.5 | G102: =ROUND((C102*D102*F102),2) -> 29302
A103: 2 | B103: Earth Work in Excavation in
B104: Foundation in Boulder Mixed Soil | C104: 1 | D104: =Qnty_ALL!G413 -> 381.56 | E104: m 3 | F104: =Rates!F10 -> 1883.36 | G104: =ROUND((C104*D104*F104),2) -> 718614.84
A105: 3 | B105: Earth Filling in Foundation | C105: 1 | D105: =Qnty_ALL!G417 -> 31.97 | E105: m 3 | F105: =Rates!F16 -> 710.7 | G105: =ROUND((C105*D105*F105),2) -> 22721.08
A106: 4 | B106: Stone Soling with sand packing on Base of Foundation | C106: 1 | D106: =Qnty_ALL!G423 -> 40.1 | E106: m 3 | F106: =Rates!F20 -> 11802.3 | G106: =ROUND((C106*D106*F106),2) -> 473272.23
...

Sheet Cost RVT-400
A1: COST ESTIMATE OF CIRCULAR RCC RESERVOIR 400 Cu m
A3: Type of Building :- Circular RCC Reservoir 400 cu m | G3: Civil Works
A4: S.No. | B4: Description | C4: Unit | D4: Quantity | E4: Rate | F4: Amount | G4: Remarks
A6: 1 | B6: Site Clearance | C6: m2 | D6: =[60]QTY.Reservoir_400m3!G7 -> 153.93804 | E6: =Rates!F7 -> 149.5 | F6: =D6*E6 -> 23013.737
F7: =D7*E7 -> 0
A8: 2 | B8: Earthwork in excavation in foundation | C8: m3 | D8: =[60]QTY.Reservoir_400m3!G9 -> 207.81635 | E8: =Rates!F10 -> 1883.36 | F8: =D8*E8 -> 391393.01
F9: =D9*E9 -> 0
A10: 3 | B10: Stone soling | C10: m3 | D10: =[60]QTY.Reservoir_400m3!G11 -> 30.349356 | E10: =Rates!F19 -> 5523.35 | F10: =D10*E10 -> 167630.11
F11: =D11*E11 -> 0 | I11: 1810.191 | J11: 1.578 | K11: =I11*J11 -> 2856.4814
A12: 4 | B12: Plain Cement Concrete P.C.C. (M10) in 1:3:6 | C12: m3 | D12: =[60]QTY.Reservoir_400m3!G14 -> 22.762017 | E12: =Rates!F31 -> 14810.58 | F12: =D12*E12 -> 337118.67 | I12: 2278.72 | J12: 0.888 | K12: =I12*J12 -> 2023.5034
F13: =D13*E13 -> 0 | I13: 3731.636 | J13: 0.62 | K13: =I13*J13 -> 2313.6143
A14: 5 | B14: Cement Concrete work for R.C.C (1:1.5:3) (M20) | C14: m3 | D14: =[60]QTY.Reservoir_400m3!G25 -> 202.75931 | E14: =Rates!F33 -> 17163.13 | F14: =D14*E14 -> 3479984.3 | I14: 2218.933 | J14: 0.395 | K14: =I14*J14 -> 876.47854
F15: =D15*E15 -> 0 | K15: =SUM(K11:K14) -> 8070.0776
A16: 6 | B16: Reinforcement Bar for RCC | C16: Kg | D16: =[60]QTY.Reservoir_400m3!G26 -> 12562 | E16: =Rates!F39 -> 125.35 | F16: =D16*E16 -> 1574646.7
F17: =D17*E17 -> 0 | K17: =0.1*K15 -> 807.00776
A18: 7 | B18: Erecting, centering and shuttering of formwork for RCC | C18: m2 | D18: =[60]QTY.Reservoir_400m3!G41 -> 524.22406 | E18: =Rates!F40 -> 1322.68 | F18: =D18*E18 -> 693380.68 | K18: =K15+K17 -> 8877.0854
F19: =D19*E19 -> 0
A20: 8 | B20: 12.5 mm thick outside cement plaster in 1:4 C/M | C20: m2 | D20: =[60]QTY.Reservoir_400m3!G51 -> 320.40604 | E20: =Rates!F60 -> 503.61 | F20: =D20*E20 -> 161359.68
F21: =D21*E21 -> 0
A22: 9 | B22: 20 mm thick cement plaster inside tank 1:3 C/M | C22: m2 | D22: =[60]QTY.Reservoir_400m3!G55 -> 270.39688 | E22: =Rates!F61 -> 649.91 | F22: =D22*E22 -> 175733.64 | I22: 3179.6555 | J22: -0.084 | K22: =I22*J22 -> -267.09106
F23: =D23*E23 -> 0 | I23: 3447.5697 | J23: -0.4657 | K23: =I23*J23 -> -1605.5332
A24: 10 | B24: 12.5 mm thick Cement Sand plaster in 1:4 C/M in Ceiling | C24: m2 | D24: =[60]QTY.Reservoir_400m3!G58 -> 111.5944 | E24: =Rates!F62 -> 637.57 | F24: =D24*E24 -> 71149.24 | I24: 3715.4839 | J24: -0.8474 | K24: =I24*J24 -> -3148.5011
F25: =D25*E25 -> 0 | I25: 3983.3981 | J25: -1.2291 | K25: =I25*J25 -> -4895.9946
A26: 11-a | B26: Providing Crystalline Water Proof Treatment | C26: m2 | D26: =[60]QTY.Reservoir_400m3!G59 -> 381.99128 | E26: 893.56089 | F26: =D26*E26 -> 341332.47 | K26: =SUM(K22:K25) -> -9917.1199
F27: =D27*E27 -> 0
A28: 11-b | B28: 3 mm thick Cement Punning | C28: m2 | D28: =[60]QTY.Reservoir_400m3!G59 -> 381.99128 | E28: =Rates!F67 -> 346.26 | F28: =D28*E28 -> 132268.3 | I28: 3879.2092 | J28: -1.0806611 | K28: =I28*J28 -> -4192.1106
F29: =D29*E29 -> 0 | I29: 3983.3981 | J29: -1.2291 | K29: =I29*J29 -> -4895.9946
A30: 12 | B30: Earthwork in backfilling | C30: m3 | D30: =[60]QTY.Reservoir_400m3!G64 -> 11.353716 | E30: =Rates!F16 -> 710.7 | F30: =D30*E30 -> 8069.0859 | I30: 4087.587 | J30: -1.3775389 | K30: =I30*J30 -> -5630.81
F31: =D31*E31 -> 0 | I31: 4191.7758 | J31: -1.5259778 | K31: =I31*J31 -> -6396.5567
A32: 13 | B32: 25 mm thick Plain G.l. Sheet of 16 SWG as a water-stop supplying and fixing | C32: m | D32: =[60]QTY.Reservoir_400m3!G65 -> 39.269908 | E32: =Rates!F49 -> 1070.18 | F32: =D32*E32 -> 42025.87 | I32: 4295.9647 | J32: -1.6744167 | K32: =SUM(K28:K31) -> -21115.472
F33: =D33*E33 -> 0 | I33: 4400.1535 | J33: -1.8228556
A34: 14 | B34: 32mm día. Gl pipe railings and staircase | C34: m | D34: =[60]QTY.Reservoir_400m3!G66 -> 48 | E34: 755.97406 | F34: =D34*E34 -> 36286.755 | I34: 4504.3424 | J34: -1.9712944 | K34: =0.1*K32 -> -2111.5472
F35: =D35*E35 -> 0
A36: 15 | B36: 2 coat enamel paint in railing & inspection ladders on top of primer | C36: m2 | D36: =[60]QTY.Reservoir_400m3!G67 -> 48 | E36: =Rates!F70 -> 400.29 | F36: =D36*E36 -> 19213.92
A37: 16 | B37: Ventilations of Wooden Frame With Chicken Wire Mesh & Mosquito Mesh | C37: Set | D37: 4 | E37: 8000 | F37: =D37*E37 -> 32000
A38: 16 | B38: Ventilations of Wooden Frame With Chicken Wire Mesh & Mosquito Mesh | C38: Set | D38: =[60]QTY.Reservoir_400m3!G68 -> 4 | E38: 6.45 | F38: =D38*E38 -> 25.8
F39: =D39*E39 -> 0
A40: 17 | B40: Manhole Cover | C40: Set | D40: =[60]QTY.Reservoir_400m3!G69 -> 2 | E40: =Rates!$F$93 -> 2479.6125 | F40: =D40*E40 -> 4959.225
F41: =D41*E41 -> 0
B42: Total | F42: =SUM(F6:F41) -> 7691591.2 | I42: 5040469.3
E53: 1 | F53: 4.047 | G53: 0.5 | H53: =F53+G53 -> 4.547
E54: 2 | F54: 4.675 | G54: 0.5 | H54: =F54+G54 -> 5.175
E55: 3 | F55: 5.304 | G55: 0.5 | H55: =F55+G55 -> 5.804
E56: 4 | F56: 5.932 | G56: 0.5 | H56: =F56+G56 -> 6.432
E57: 5 | F57: 6.56 | G57: 0.5 | H57: =F57+G57 -> 7.06
E58: 6 | F58: 7.187 | G58: 0.5 | H58: =F58+G58 -> 7.687
E59: 7 | F59: 7.814 | G59: 0.5 | H59: =F59+G59 -> 8.314
E60: 8 | F60: 8.44 | G60: 0.5 | H60: =F60+G60 -> 8.94
E61: 9 | F61: 9.065 | G61: 0.5 | H61: =F61+G61 -> 9.565
E62: 10 | F62: 9.69 | G62: 0.5 | H62: =F62+G62 -> 10.19
E63: 11 | F63: 10.314 | G63: 0.5 | H63: =F63+G63 -> 10.814
E64: 12 | F64: 10.938 | G64: 0.5 | H64: =F64+G64 -> 11.438
... E89: 37 | F89: 26.148 | G89: 0.5 | H89: =F89+G89 -> 26.648
E90: 38 | F90: 26.736 | G90: 0.5 | H90: =F90+G90 -> 27.236 | J90: 72 | K90: 5.514 | L90: =J90*K90 -> 397.008
E91: 39 | F91: 27.323 | G91: 0.5 | H91: =F91+G91 -> 27.823 | J91: 66 | K91: 4.5 | L91: =J91*K91 -> 297
E92: 40 | F92: 27.907 | G92: 0.5 | H92: =F92+G92 -> 28.407 | L92: =SUM(L90:L91) -> 694.008
E93: 41 | F93: 28.489 | G93: 0.5 | H93: =F93+G93 -> 28.989
E94: 42 | F94: 29.069 | G94: 0.5 | H94: =F94+G94 -> 29.569
E95: 43 | F95: 29.647 | G95: 0.5 | H95: =F95+G95 -> 30.147
E96: 44 | F96: 30.223 | G96: 0.5 | H96: =F96+G96 -> 30.723
E97: 45 | F97: 30.797 | G97: 0.5 | H97: =F97+G97 -> 31.297
E98: 46 | F98: 31.368 | G98: 0.5 | H98: =F98+G98 -> 31.868
E99: 47 | F99: 31.937 | G99: 0.5 | H99: =F99+G99 -> 32.437 | L99: =L92+H109 -> 1891.061
E100: 48 | F100: 32.504 | G100: 0.5 | H100: =F100+G100 -> 33.004
E101: 49 | F101: 33.068 | G101: 0.5 | H101: =F101+G101 -> 33.568
E102: 50 | F102: 33.63 | G102: 0.5 | H102: =F102+G102 -> 34.13
E103: 51 | F103: 34.19 | G103: 0.5 | H103: =F103+G103 -> 34.69
E104: 52 | F104: 34.747 | G104: 0.5 | H104: =F104+G104 -> 35.247
E105: 53 | F105: 35.301 | G105: 0.5 | H105: =F105+G105 -> 35.801
E106: 54 | F106: 35.853 | G106: 0.5 | H106: =F106+G106 -> 36.353
E107: 55 | F107: 36.403 | G107: 0.5 | H107: =F107+G107 -> 36.903
E108: 56 | F108: 36.949 | G108: 0.5 | H108: =F108+G108 -> 37.449
H109: =SUM(H53:H108) -> 1197.053
J114: =PI()*1.25 -> 3.9269908
J115: 0.5
J116: =SUM(J114:J115) -> 4.4269908
J119: 3.79 | K119: 2 | L119: =J119*K119 -> 7.58
J120: 4.42 | K120: 2 | L120: =J120*K120 -> 8.84
H126: =4*5.15 -> 20.6

Sheet Sump well
A1: QUANTITY ESTIMATES
A2: SUMP WELL FOR PUMPS IN GROUND RESERVOIR
A3: S.No. | B3: Description of Works | C3: No. | D3: Length (m) | E3: Breadth (m) | F3: Height (m) | G3: Quantity | H3: Rate | I3: Amount
A4: a | B4: E/W in Excavation | C4: 1 | D4: 6.1 | E4: 4.9 | F4: 4.75 | G4: 141.98 | H4: =Rates!F10 -> 1883.36 | I4: =H4*G4 -> 267399.45
A6: b | B6: Back Filling | C6: 1 | D6: 35% of Total Earth Work | G6: 49.69 | H6: =Rates!F16 -> 710.7 | I6: =H6*G6 -> 35314.683
A8: c | B8: Stone Soling | C8: 1 | D8: 4.1 | E8: 2.9 | F8: 0.15 | G8: 1.78 | H8: =Rates!F19 -> 5523.35 | I8: =H8*G8 -> 9831.563
A10: d | B10: M10 Cement Concrete Work for PCC | C10: 1 | D10: 4.1 | E10: 2.9 | F10: 0.1 | G10: 1.19 | H10: =Rates!F31 -> 14810.58 | I10: =H10*G10 -> 17624.59
A12: e | B12: M20 Cement Concrete Work for PCC
B13: Bottom Slab | C13: 1 | D13: 4.1 | E13: 2.9 | F13: 0.4 | G13: 4.76
B14: Long Wall | C14: 2 | D14: 3.4 | E14: 0.35 | F14: 5.1 | G14: 12.14
B15: Short Wall | C15: 2 | D15: 1.5 | E15: 0.35 | F15: 5.1 | G15: 5.36
B16: Roof Slab | C16: 1 | D16: 3.4 | E16: 2.2 | F16: 0.1 | G16: 0.75
F17: Total | G17: 23.01 | H17: =Rates!F33 -> 17163.13 | I17: =H17*G17 -> 394923.62
A19: f | B19: Formwork
B20: Foundation | C20: 1 | D20: 14 | F20: 0.5 | G20: 7
B21: Outer Side of Wall | C21: 1 | D21: 11.2 | F21: 5.2 | G21: 58.24
B22: Inner Side of Wall | C22: 1 | D22: 8.4 | F22: 5.1 | G22: 42.84
B23: Bottom Face of Slab | C23: 1 | D23: 2.7 | F23: 1.5 | G23: 4.05
F24: Total | G24: 112.13 | H24: =Rates!F40 -> 1322.68 | I24: =H24*G24 -> 148312.11
A26: g | B26: Reinforcement
B27: 12 Dia. Bar in Base Slab in Longer Dir. | C27: 38 | D27: 5.3 | E27: Unit Wt. | F27: 0.899 | G27: 181.06
B28: 12 Dia. Bar in Base Slab in Short Dir. | C28: 52 | D28: 4.1 | E28: Unit Wt. | F28: 0.899 | G28: 191.67
B29: 16 Dia. Vertical Wall (Long) | C29: 116 | D29: 6.78 | E29: Unit Wt. | F29: 1.598 | G29: 1256.8
B30: 16 Dia. Vertical Wall (Short) | C30: 44 | D30: 6.78 | E30: Unit Wt. | F30: 1.598 | G30: 476.72
B31: 12 Dia. Horizontal Bar | C31: 31 | D31: 22.4 | E31: Unit Wt. | F31: 0.899 | G31: 624.27
B32: 17 Dia. Bar in Base Slab in Longer Dir. | C32: 20 | D32: 3.7 | E32: Unit Wt. | F32: 0.4 | G32: 29.6
B33: 8 Dia. Main Bar in Roof Slab | C33: 14 | D33: 2.5 | E33: Unit Wt. | F33: 0.4 | G33: 14
B34: 8 Dia. Mainor Bar in Roof Slab | C34: 34 | D34: 1.9 | E34: Unit Wt. | F34: 0.4 | G34: 25.84
B35: 8 Extra Bar in Roof Slab | C35: 70 | D35: 1.7 | E35: Unit Wt. | F35: 0.899 | G35: 106.98
B36: 21 Dia. Chair Bar | C36: 0.15 | G36: 436.04
B37: Extra for Lapping, Chiar, etc. | F37: Total | G37: 3343 | H37: =Rates!F39 -> 125.35 | I37: =H37*G37 -> 419045.05
A39: h | B39: Plaster (1:4) 12.5 and Punning
B40: Wall of Tank | D40: Same as Inner form Work | G40: 42.84
B41: Base of Tank | C41: 1 | D41: 2.7 | E41: 1.5 | G41: 4.05
F42: Total | G42: 46.89 | H42: =Rates!F67 -> 346.26 | I42: =H42*G42 -> 16236.131
A44: i | B44: Plaster (1:4) 12.5 in Ceiling | C44: 1 | D44: 2.7 | E44: 1.5 | G44: 4.05 | H44: =Rates!F60 -> 503.61 | I44: =H44*G44 -> 2039.6205
A46: j | B46: Providing Crystalline Cater Proof Treatment | G46: 48.89 | H46: 5000 | I46: =H46*G46 -> 244450
A48: k | B48: Mild Steel Iron Step | C48: 54 | G48: 54 | H48: 225 | I48: =H48*G48 -> 12150
A50: l | B50: 600 X 600 Manhole Cover (Cash Iron) | C50: 3 | G50: 3 | H50: =Rates!$F$93 -> 2479.6125 | I50: =H50*G50 -> 7438.8375
A52: m | B52: 18 SWG Water Stopper (with 15% for Lapping) | C52: 3 | D52: 11.2 | G52: 39 | H52: 526 | I52: =H52*G52 -> 20514
A54: n | B54: Pump Set and all accessories | C54: 1 | G54: 1 | H54: 500000 | I54: =H54*G54 -> 500000
I55: =SUM(I4:I54) -> 2095279.7

Sheet Abstract_TRUSS
B1: Abstract of Cost of Truss and Roofing
A2: S.No. | B2: Items Of works | C2: Unit | D2: Quantity | E2: Unit rate | F2: Amount | G2: Remarks
A3: 1 | B3: Clearing the site from trees, logs, bushes, weeds, grass, debris & rubbish of any nature to make the site suitable for construction work and clearing the site from construction materials and equipment after completion of the work as per instruction of the engineer. | C3: Job | D3: 1 | E3: 20000 | F3: =E3*D3 -> 20000
A4: 2 | B4: Earthwork in excavation in foundation in hard with a lead of 10 m. i> Upto depth 4M | C4: cum | D4: ='Qty Truss'!G9 -> 90 | E4: =Rates!$F$9 -> 1480.63 | F4: =E4*D4 -> 133256.7
A5: 3 | B5: Providing and backfilling the earth in the trenches in layers not exceeding more than 225 mm with watering and ramming for the proper compaction as per the instruction and specification all complete. | C5: cum | D5: ='Qty Truss'!G11 -> 27 | E5: =Rates!$F$14 -> 592.25 | F5: =E5*D5 -> 15990.75
A6: 4 | B6: Providing and laying first class chimney made brick soling on flat as per the instruction of the Engineer | C6: sqm | D6: ='Qty Truss'!G14 -> 36 | E6: =Rates!$F$28 -> 19440.44 | F6: =E6*D6 -> 699855.84
A7: 5 | B7: Providing and laying of 75mm thick PCC (1:3:6) in foundation with a size of aggregate not exceeding 38 mm all complete as per the specification and instruction of the engineer | C7: sqm | D7: ='Qty Truss'!G18*0.075 -> 2.7 | E7: =Rates!$F$31 -> 14810.58 | F7: =E7*D7 -> 39988.566
A8: 6 | B8: Supplying, mixing, placing, compacting and cure concrete PCC (1:1.5:3) for lintel as per drawing, specification and instruction of Engineer | C8: cum | D8: ='Qty Truss'!G21 -> 4.5 | E8: =Rates!$F$33 -> 17163.13 | F8: =E8*D8 -> 77234.085
A9: 7 | B9: Brickwork in walls and foundation in cement sand mortar (1:4) with 1st class chimney bricks in perfect lines and levels with necessary scaffolding including wetting the brick, properly packing the joint with cement mortar and curing the works all complete | C9: cum | D9: ='Qty Truss'!G26 -> 58.5 | E9: =Rates!F28 -> 19440.44 | F9: =E9*D9 -> 1137265.7
A10: 8 | B10: Providing and fitting of roof truss with black iron pipe including all necessary joints and accessories as per drawing and instruction, all complete. | C10: Kgs | D10: ='Qty Truss'!G33 -> 546.31326 | E10: =Rates!F39 -> 125.35 | F10: =E10*D10 -> 68480.367
A11: 9 | B11: Roofing with 0.5 mm thick corrugated coloured GI Sheet with necessary 8mm nut bolts, J-hooks, bitumin washers as per drawing and instruction, all complete. | C11: Sft | D11: ='Qty Truss'!G36 -> 485.76 | E11: =Rates!$F$49 -> 1070.18 | F11: =E11*D11 -> 519850.64
A12: 10 | B12: Providing and fixing gutter of 0.5mm coloured plain sheet 150 mm width and 450 mm depth with 40*3 mm iron braket, nutbolt, washer, all complete | C12: Rft | D12: ='Qty Truss'!G42 -> 36.8 | E12: =Rates!F49 -> 1070.18 | F12: =E12*D12 -> 39382.624
A13: 11 | B13: Providing and fixing ridge of 0.5mm coloured plain sheet , nutbolt, washer, all complete | C13: Rft | D13: ='Qty Truss'!G39 -> 18.4 | E13: =Rates!F50 -> 1010.11 | F13: =E13*D13 -> 18586.024
A14: 17 | B14: providing 10 SWG 3"X3" Chain mesh Fecing on all faces of the truss structure with metal door and proper locking system along with required support system | C14: job | D14: 1 | E14: 50000 | F14: =E14*D14 -> 50000
E15: Total | F15: =SUM(F3:F14) -> 2819891.3

Sheet Pipe Support
A1: Detailed Quantity Estimate
A2: ='sum cost_All'!$B$2 -> Name of Scheme: Sankhu Drinking Water Supply Project
A3: Component: Pipe Suppor Pillars
A4: 2 | B4: 2m
B5: Earthwork Excavation | C5: cu.m | D5: 1 | E5: 0.6 | F5: 0.6 | G5: 0.5 | H5: 0.18 | I5: =Rates!F10 -> 1883.36 | J5: =H5*I5 -> 339.0048
B6: Filling of trenches, | C6: cu.m | D6: 2 | E6: 0.6 | F6: 0.1 | G6: 0.15 | H6: 0.018 | I6: =Rates!F16 -> 710.7 | J6: =H6*I6 -> 12.7926
D7: 2 | E7: 0.4 | F7: 0.1 | G7: 0.15 | H7: 0.012 | I7: =I6 -> 710.7 | J7: =H7*I7 -> 8.5284
B8: Stone soling | C8: cu.m | D8: 1 | E8: 0.6 | F8: 0.6 | G8: 0.2 | H8: 0.072 | I8: =Rates!F19 -> 5523.35 | J8: =H8*I8 -> 397.6812
B9: PCC 1:3:6 | C9: cu.m | D9: 1 | E9: 0.6 | F9: 0.6 | G9: 0.15 | H9: 0.054 | I9: =Rates!F31 -> 14810.58 | J9: =H9*I9 -> 799.77132
B10: RRM in CM 1:4 | C10: cu.m | D10: 1 | E10: 0.4 | F10: 0.4 | G10: 1 | H10: 0.16 | I10: =Rates!F24 -> 15619.64 | J10: =H10*I10 -> 2499.1424
B11: PCC 1:2:4 | C11: cu.m | D11: 1 | E11: 0.4 | F11: 0.4 | G11: 0.1 | H11: 0.016 | I11: =Rates!F32 -> 16022.87 | J11: =H11*I11 -> 256.36592
J12: =SUM(J5:J11) -> 4313.2866
A13: 2 | B13: 2m
B14: Earthwork Excavation | C14: cu.m | D14: 1 | E14: 1 | F14: 1 | G14: 0.8 | H14: 0.8 | I14: =I5 -> 1883.36 | J14: =H14*I14 -> 1506.688
B15: Filling of trenches, | C15: cu.m | D15: 2 | E15: 1 | F15: 0.1 | G15: 0.45 | H15: 0.09 | I15: =I6 -> 710.7 | J15: =H15*I15 -> 63.963
C16: cu.m | D16: 2 | E16: 0.8 | F16: 0.1 | G16: 0.45 | H16: 0.072 | I16: =I7 -> 710.7 | J16: =H16*I16 -> 51.1704
B17: Stone soling | C17: cu.m | D17: 1 | E17: 1 | F17: 1 | G17: 0.2 | H17: 0.2 | I17: =I8 -> 5523.35 | J17: =H17*I17 -> 1104.67
B18: PCC 1:3:6 | C18: cu.m | D18: 1 | E18: 1 | F18: 1 | G18: 0.15 | H18: 0.15 | I18: =I9 -> 14810.58 | J18: =H18*I18 -> 2221.587
B19: RRM in CM 1:4 | C19: cu.m | D19: 1 | E19: 0.8 | F19: 0.8 | G19: 1 | H19: 0.64 | I19: =I10 -> 15619.64 | J19: =H19*I19 -> 9996.5696
C20: cu.m | D20: 1 | E20: 0.4 | F20: 0.4 | G20: 1 | H20: 0.16 | I20: =I10 -> 15619.64 | J20: =H20*I20 -> 2499.1424
B21: PCC 1:2:4 | C21: cu.m | D21: 1 | E21: 0.4 | F21: 0.4 | G21: 0.1 | H21: 0.016 | I21: =I11 -> 16022.87 | J21: =H21*I21 -> 256.36592
J22: =SUM(J14:J21) -> 17700.156
A23: 3 | B23: 3m
B24: Earthwork Excavation | C24: cu.m | D24: 1 | E24: 1 | F24: 1 | G24: 0.8 | H24: 0.8 | I24: =I14 -> 1883.36 | J24: =H24*I24 -> 1506.688
B25: Filling of trenches, | C25: cu.m | D25: 2 | E25: 1 | F25: 0.1 | G25: 0.45 | H25: 0.09 | I25: =I15 -> 710.7 | J25: =H25*I25 -> 63.963
C26: cu.m | D26: 2 | E26: 0.8 | F26: 0.1 | G26: 0.45 | H26: 0.072 | I26: =I16 -> 710.7 | J26: =H26*I26 -> 51.1704
B27: Stone soling | C27: cu.m | D27: 1 | E27: 1 | F27: 1 | G27: 0.2 | H27: 0.2 | I27: =I17 -> 5523.35 | J27: =H27*I27 -> 1104.67
B28: PCC 1:3:6 | C28: cu.m | D28: 1 | E28: 1 | F28: 1 | G28: 0.15 | H28: 0.15 | I28: =I18 -> 14810.58 | J28: =H28*I28 -> 2221.587
B29: RRM in CM 1:4 | C29: cu.m | D29: 1 | E29: 0.8 | F29: 0.8 | G29: 1 | H29: 0.64 | I29: =I19 -> 15619.64 | J29: =H29*I29 -> 9996.5696
C30: cu.m | D30: 1 | E30: 0.6 | F30: 0.6 | G30: 1 | H30: 0.36 | I30: =I19 -> 15619.64 | J30: =H30*I30 -> 5623.0704
C31: cu.m | D31: 1 | E31: 0.4 | F31: 0.4 | G31: 1 | H31: 0.16 | I31: =I19 -> 15619.64 | J31: =H31*I31 -> 2499.1424
B32: PCC 1:2:4 | C32: cu.m | D32: 1 | E32: 0.4 | F32: 0.4 | G32: 0.1 | H32: 0.016 | I32: =I21 -> 16022.87 | J32: =H32*I32 -> 256.36592
J33: =SUM(J24:J32) -> 23323.227
A34: SN | B34: >3m
A35: 1 | B35: Earthwork Excavation | C35: cu.m | D35: 1 | E35: 1.2 | F35: 1.2 | G35: 0.9 | H35: 1.296 | I35: =I24 -> 1883.36 | J35: =H35*I35 -> 2440.8346
A36: 2 | B36: Filling of trenches, | C36: cu.m | D36: 2 | E36: 1.2 | F36: 0.4 | G36: 0.4 | H36: 0.384 | I36: =I25 -> 710.7 | J36: =H36*I36 -> 272.9088
A37: 3 | C37: cu.m | D37: 2 | E37: 0.4 | F37: 0.4 | G37: 0.4 | H37: 0.128 | I37: =I25 -> 710.7 | J37: =H37*I37 -> 90.9696
A38: 4 | B38: Stone soling | C38: cu.m | D38: 1 | E38: 1.2 | F38: 1.2 | G38: 0.2 | H38: 0.288 | I38: =I27 -> 5523.35 | J38: =H38*I38 -> 1590.7248
A39: 5 | B39: RCC 1:2:4 | C39: cu.m | D39: 1 | E39: 1.2 | F39: 1.2 | G39: 0.3 | H39: 0.432 | I39: =I11 -> 16022.87 | J39: =H39*I39 -> 6921.8798
C40: cu.m | D40: 1 | E40: 0.4 | F40: 0.4 | G40: 4 | H40: 0.64 | I40: =I39 -> 16022.87 | J40: =H40*I40 -> 10254.637
A41: 6 | B41: TMT bars | C41: kg | D41: 16 | E41: 1.2 | F41: - | G41: - | H41: 19.2
C42: kg | D42: 4 | E42: 5 | F42: - | G42: - | H42: 20
H43: 39.2
B44: 12mmØ | H44: 34.888 | I44: =Rates!F39 -> 125.35 | J44: =H44*I44 -> 4373.2108
C45: kg | D45: 20 | E45: 1.6 | H45: 32
B46: 8mmØ | H46: 12.64 | I46: =I44 -> 125.35 | J46: =H46*I46 -> 1584.424
A47: 7 | B47: Shuttering | C47: sq.m | D47: 4 | E47: 1.2 | F47: - | G47: 0.3 | H47: 1.44 | I47: =Rates!F40 -> 1322.68 | J47: =H47*I47 -> 1904.6592
D48: 4 | E48: 0.4 | F48: - | G48: 4 | H48: 6.4 | I48: =I47 -> 1322.68 | J48: =H48*I48 -> 8465.152
I49: Total | J49: =SUM(J35:J48) -> 37899.4
A50: Component: Thrust Block
B51: 90°
B52: Description | C52: Unit | D52: No. | E52: L | F52: B | G52: H | H52: Qty | I52: Rate
A54: 1 | B54: Excavation | C54: cu.m | D54: 1 | E54: 1 | F54: 1 | G54: 1.2 | H54: 1.2 | I54: =I35 -> 1883.36 | J54: 140.244
A55: 2 | B55: PCC 1:2:4, 40mm agg | C55: cu.m | D55: 1 | E55: 1 | F55: 1 | G55: 1 | H55: 1 | I55: =I39 -> 16022.87 | J55: 4263.96
A56: 3 | B56: Shuttering | C56: sq.m | D56: 4 | E56: 1 | F56: - | G56: 1 | H56: 4 | I56: =I47 -> 1322.68 | J56: 1091.08
J57: =SUM(J54:J56) -> 5495.284

Sheet Cost_In_1
A1: ABSTRACT OF COST
A3: TYPE OF WORK : Intake Construction-Fedi
A5: S.no. | B5: Description of works | C5: Unit | D5: Quantity | E5: Rate | F5: Amount | G5: Remarks
A6: 1 | B6: Site Clearance | C6: sqm | D6: =Qty_in_1!H4 -> 170.4 | E6: =Rates!$F$7 -> 149.5 | F6: =+ROUND(D6*E6,2) -> 25474.8 | I6: =F7+F35 -> 170082.36
A7: 2 | B7: Earthwork Excavation in River Bed | C7: Cum | D7: =Qty_in_1!H11 -> 32.23 | E7: =Rates!$F$11 -> 3553.5 | F7: =+ROUND(D7*E7,2) -> 114529.31
A8: 3 | B8: =Qty_in_1!B12 -> Stone Soling | C8: =Qty_in_1!C16 -> Cum | D8: =Qty_in_1!H16 -> 6.93 | E8: =Rates!$F$19 -> 5523.35 | F8: =+ROUND(D8*E8,2) -> 38276.82 | H8: =+F8 -> 38276.82 | I8: =F8+F38+#REF! -> #REF!
A9: 4 | B9: P.C.C Works
A10: 4.1 | B10: =Qty_in_1!B18 -> PCC M10 | C10: =Qty_in_1!C22 -> Cum | D10: =Qty_in_1!H22 -> 3.46 | E10: =Rates!$F$31 -> 14810.58 | F10: =+ROUND(D10*E10,2) -> 51244.61 | H10: =+F10 -> 51244.61 | I10: =F10+F42 -> 51244.61
A11: 4.2 | B11: RCC works M20 | C11: cum | D11: =Qty_in_1!H35 -> 24.95 | E11: =Rates!$F$33 -> 17163.13 | F11: =+ROUND(D11*E11,2) -> 428220.09
A12: 5 | B12: Form Works | C12: sqm | D12: =Qty_in_1!H53 -> 125.78 | E12: =Rates!$F$40 -> 1322.68 | F12: =+ROUND(D12*E12,2) -> 166366.69 | H12: =+F12+#REF!+F50 -> #REF! | I12: =F12+F43 -> 166366.69
A13: 6 | B13: Reinforcement | C13: kg | D13: =Qty_in_1!H54 -> 3965.553 | E13: =Rates!$F$39 -> 125.35 | F13: =+ROUND(D13*E13,2) -> 497082.07 | H13: =+F13+#REF!+#REF! -> #REF!
A14: 7 | B14: 20 to 25mm thick screeding (1:4) on floors | C14: sqm | D14: =Qty_in_1!H59 -> 5.25 | E14: =+'[61]Analysis of rates'!E793 -> 439.26889 | F14: =+ROUND(D14*E14,2) -> 2306.16
A15: 8 | B15: Cement punning | C15: sqm | D15: =Qty_in_1!H65 -> 61.15 | E15: =+'[61]Analysis of rates'!E807 -> 220.97709 | F15: =+ROUND(D15*E15,2) -> 13512.75
A16: 9 | B16: 12.5 mm thick cement plaster on concrete surface with 1:3 cement sand mortar | C16: sqm | D16: =Qty_in_1!H74 -> 79.09 | E16: ='[61]Analysis of rates'!E859 -> 351.50553 | F16: =+ROUND(D16*E16,2) -> 27800.57 | I16: =F16+F44 -> 27800.57 | K16: 2016 | L16: 2073
A17: 10 | B17: Gabion Works | K17: =+K16-#REF! -> #REF! | L17: 2060
B18: Launching Apron | H18: =+#REF!/12 -> #REF!
B19: 2mx1mx0.3m | C19: Cum | D19: =Qty_in_1!H77 -> 44.52 | E19: ='[61]Analysis of rates'!E2318 -> 6073.622 | F19: =+ROUND(D19*E19,2) -> 270397.65
A20: 12 | B20: 600dia. Manhole Cover | C20: No. | D20: =Qty_in_1!H78 -> 2 | E20: 15000 | F20: =+ROUND(D20*E20,2) -> 30000
A21: 13 | B21: Supplying and laying Pipes Fittings
B22: 75∅ Tee | C22: No. | E22: =320*1.1 -> 352 | F22: =+ROUND(D22*E22,2) -> 0
B23: 75∅ Elbow | C23: No. | E23: =285*1.1 -> 313.5 | F23: =+ROUND(D23*E23,2) -> 0
B24: 75∅ Pipe Piece | C24: No. | E24: ='[61]rate73-74'!O46 -> 452.18 | F24: =+ROUND(D24*E24,2) -> 0
B25: 65∅ Gate Valve | C25: No. | E25: =11087+'[61]GI fittings'!K17 -> 11221.096 | F25: =+ROUND(D25*E25,2) -> 0
B26: 65∅ Union | C26: No. | E26: =976+'[61]GI fittings'!K35 -> 1046.2785 | F26: =+ROUND(D26*E26,2) -> 0
B27: 65∅ Nipple | C27: No. | E27: =373+'[61]GI fittings'!K35 -> 443.27849 | F27: =+ROUND(D27*E27,2) -> 0
B28: 65/75 GI/PE Flanged set | C28: No. | E28: =1586+'[61]GI fittings'!K35 -> 1656.2785 | F28: =+ROUND(D28*E28,2) -> 0
B29: 75∅ PE Stainer | C29: No. | E29: ='[61]rate73-74'!O46*1.15 -> 520.007 | F29: =+ROUND(D29*E29,2) -> 0
F30: =SUM(F6:F29) -> 1665211.5
A33: TYPE OF WORK : Pitching works in river
A34: S.no. | B34: Description of works | C34: Unit | D34: Quantity | E34: Rate | F34: Amount | G34: Remarks
A35: 1 | B35: Earthwork Excavation in River Bed | C35: Cum | D35: =Qty_in_1!H93 -> 134 | E35: ='[61]Analysis of rates'!E67 -> 414.575 | F35: =+ROUND(D35*E35,2) -> 55553.05
A36: 2 | B36: Back filling | C36: Cum | D36: =Qty_in_1!H96 -> 30 | E36: ='[61]Analysis of rates'!E78 -> 296.125 | F36: =+ROUND(D36*E36,2) -> 8883.75
A37: 3 | B37: Masonary Works
A38: 3.1 | B38: Stone Soling | C38: Cum | D38: =Qty_in_1!H100 -> 16.8 | E38: ='[61]Analysis of rates'!E1593 -> 4565 | F38: =+ROUND(D38*E38,2) -> 76692
A39: 3.2 | B39: Stone Masonary(1:6) | C39: Cum | D39: 0 | E39: ='[61]Analysis of rates'!E1534 -> 8027 | F39: =+ROUND(D39*E39,2) -> 0
A40: 4 | B40: P.C.C Works
A41: 4.1 | B41: M10 | C41: Cum | D41: =Qty_in_1!H110 -> 8.45 | E41: ='[61]Analysis of rates'!E166 -> 10715.088 | F41: =+ROUND(D41*E41,2) -> 90542.49
A42: 4.2 | B42: M15 | C42: Cum | D42: 0 | E42: ='[61]Analysis of rates'!E181 -> 12897.013 | F42: =+ROUND(D42*E42,2) -> 0
A43: 5 | B43: Form Works | C43: sqm | D43: 0 | E43: ='[61]Analysis of rates'!E343 -> 764.33148 | F43: =+ROUND(D43*E43,2) -> 0 | L43: =2.4*3*1.5 -> 10.8
A44: 6 | B44: 12.5mm thick c/s plaster (1:3) in wall (both sides) and 100mm below GL | C44: sqm | D44: 0 | E44: =E16 -> 351.50553 | F44: =+ROUND(D44*E44,2) -> 0 | K44: =3.6/3.281 -> 1.0972265
A45: 7 | B45: Fencing by galvanised chain link of 10SWG with 50mm bore MS pipe (@2m c/c), 25x25x4 mm MS angle & 100 mm long 3x20mm MS strip | C45: sqm | D45: 0 | E45: ='[61]Analysis of rates'!E2333 -> 2250.18 | F45: =+ROUND(D45*E45,2) -> 0
A46: 8 | B46: Gabions Works
B47: 2x1x1 | C47: Cum | D47: 0 | E47: ='[61]Analysis of rates'!E2263 -> 2605.6285 | F47: =+ROUND(D47*E47,2) -> 0
E49: Total | F49: =SUM(F35:F41) -> 231671.29

Sheet Qnty_ALL
A1: Detailed Quantity Estimate
A3: Component: Plain Sedimentation Tank
A5: S.N. | B5: Description of Works | C5: No | D5: Length (m) | E5: Breadth (m) | F5: Height (m) | G5: Quantity | H5: Units
A6: 1 | B6: Site Clearence | C6: 1 | D6: 14 | E6: 6 | G6: =ROUND((C6*D6*E6),2) -> 84 | H6: m2
A7: 2 | B7: Earth Work in Excavation in Boulder Mixed Soil
B8: Levelling work | C8: 1 | D8: 13.52 | E8: 5.52 | F8: 0.3 | G8: =ROUND((C8*D8*E8*F8),2) -> 22.39
B9: Foundation in Boulder Mixed Soil
B10: PS | C10: 1 | D10: 13.52 | E10: 5.52 | F10: 1.48 | G10: =ROUND((C10*D10*E10*F10),2) -> 110.45
B11: Inlet VC | C11: 1 | D11: 1.83 | E11: 1.86 | F11: 1.48 | G11: =ROUND((C11*D11*E11*F11),2) -> 5.04
B12: Outlet VC | C12: 1 | D12: 1.83 | E12: 1.86 | F12: 1.48 | G12: =ROUND((C12*D12*E12*F12),2) -> 5.04
E13: Total | G13: =ROUND(SUM(G8:G12),2) -> 142.92 | H13: m3
A14: 3 | B14: Earth Filling in Foundation
B15: Long wall | C15: 2 | D15: 13.52 | E15: 0.6 | F15: 1.48 | G15: =ROUND((C15*D15*E15*F15),2) -> 24.01
B16: short wall | C16: 2 | D16: 4.32 | E16: 0.6 | F16: 1.48 | G16: =ROUND((C16*D16*E16*F16),2) -> 7.67
B17: Inlet VC | C17: 1 | D17: 1.83 | E17: 0.2 | F17: 1.48 | G17: =ROUND((C17*D17*E17*F17),2) -> 0.54
B18: Outlet VC | C18: 1 | D18: 1.83 | E18: 0.2 | F18: 1.48 | G18: =ROUND((C18*D18*E18*F18),2) -> 0.54
E19: Sub Total | G19: =ROUND(SUM(G15:G18),2) -> 32.76 | H19: m3
B20: Deduct
B21: Long wall | C21: 2 | D21: 13.52 | E21: 0.15 | F21: 0.48 | G21: =ROUND((C21*D21*E21*F21),2) -> 1.95
B22: short wall | C22: 2 | D22: 4.32 | E22: 0.15 | F22: 0.48 | G22: =ROUND((C22*D22*E22*F22),2) -> 0.62
B23: Inlet VC | C23: 1 | D23: 1.83 | E23: 0.05 | F23: 0.35 | G23: =ROUND((C23*D23*E23*F23),2) -> 0.03
B24: Outlet VC | C24: 1 | D24: 1.83 | E24: 0.05 | F24: 0.35 | G24: =ROUND((C24*D24*E24*F24),2) -> 0.03
E25: Total | G25: =ROUND((G19-G21-G22-G23-G24),2) -> 30.13 | H25: m3
A26: 4 | B26: Stone Soling with sand packing on
B27: Base of Foundation, PS | C27: 1 | D27: 13.22 | E27: 5.22 | F27: 0.2 | G27: =ROUND((C27*D27*E27*F27),2) -> 13.8
B28: Inlet VC | C28: 1 | D28: 1.73 | E28: 1.76 | F28: 0.2 | G28: =ROUND((C28*D28*E28*F28),2) -> 0.61
B29: Outlet VC | C29: 1 | D29: 1.73 | E29: 1.76 | F29: 0.2 | G29: =ROUND((C29*D29*E29*F29),2) -> 0.61
E30: Total | G30: =ROUND(SUM(G27:G29),2) -> 15.02 | H30: m3
A31: 5 | B31: Laying of P.C.C. 1:3:6 on Base of
B32: Foundation PS | C32: 1 | D32: 13.8 | E32: 5.22 | F32: 0.1 | G32: =ROUND((C32*D32*E32*F32),2) -> 7.2
B33: Inlet VC | C33: 1 | D33: 1.73 | E33: 1.76 | F33: 0.1 | G33: =ROUND((C33*D33*E33*F33),2) -> 0.3
B34: Outlet VC | C34: 1 | D34: 1.73 | E34: 1.76 | F34: 0.1 | G34: =ROUND((C34*D34*E34*F34),2) -> 0.3
E35: Total | G35: =ROUND(SUM(G32:G34),2) -> 7.8 | H35: m3
A36: 6 | B36: Laying of One Layer Tarfelt Over
B37: Lean Concrete PS | C37: 1 | D37: 13.8 | E37: 5.22 | G37: =ROUND((C37*D37*E37),2) -> 72.04
E38: Total | G38: =ROUND(SUM(G37:G37),2) -> 72.04 | H38: m3
A39: 7 | B39: P.C.C (1: 1.5:3) Works for R.C.C
B40: SSF
B41: Base Slab | C41: 1 | D41: 13.22 | E41: 5.22 | F41: 0.18 | G41: =ROUND((C41*D41*E41*F41),2) -> 12.42
B42: Long Wall | C42: 2 | D42: 12.32 | E42: 0.16 | F42: 1 | G42: =ROUND((C42*D42*E42*F42),2) -> 3.94
B43: Long Wall | C43: 2 | D43: 12.32 | E43: 0.18 | F43: 1.4 | G43: =ROUND((C43*D43*E43*F43),2) -> 6.21
B44: Short Wall | C44: 2 | D44: 4 | E44: 0.16 | F44: 1 | G44: =ROUND((C44*D44*E44*F44),2) -> 1.28
B45: Short Wall | C45: 2 | D45: 4 | E45: 0.18 | F45: 1.4 | G45: =ROUND((C45*D45*E45*F45),2) -> 2.02
B46: Channel base | C46: 2 | D46: 4.16 | E46: 0.35 | F46: 0.075 | G46: =ROUND((C46*D46*E46*F46),2) -> 0.22
B47: height | C47: 2 | D47: 4.16 | E47: 0.15 | F47: 0.075 | G47: =ROUND((C47*D47*E47*F47),2) -> 0.09
B48: Scum through collector base | C48: 1 | D48: 4.16 | E48: 0.35 | F48: 0.075 | G48: =ROUND((C48*D48*E48*F48),2) -> 0.11
B49: height | C49: 1 | D49: 4.16 | E49: 0.15 | F49: 0.075 | G49: =ROUND((C49*D49*E49*F49),2) -> 0.05
B50: Baffle | C50: 1 | D50: 4 | E50: 0.075 | F50: 1.2 | G50: =ROUND((C50*D50*E50*F50),2) -> 0.36
A52: Component: Plain Sedimentation Tank
A54: S.N. | B54: Description of Works | C54: No | D54: Length (m) | E54: Breadth (m) | F54: Height (m) | G54: Quantity | H54: Units
B55: Baffle slab | C55: 1 | D55: 2 | E55: 0.4 | F55: 0.075 | G55: =ROUND((C55*D55*E55*F55),2) -> 0.06
B56: Inlet VC | C56: 1 | D56: 1.73 | E56: 1.76 | F56: 0.1 | G56: =ROUND((C56*D56*E56*F56),2) -> 0.3
B57: Outlet VC | C57: 1 | D57: 1.73 | E57: 1.76 | F57: 0.1 | G57: =ROUND((C57*D57*E57*F57),2) -> 0.3
B58: Slab cover of Inlet VC | C58: 1 | D58: 1.66 | E58: 1.46 | F58: 0.1 | G58: =ROUND((C58*D58*E58*F58),2) -> 0.24
B59: Slab cover of Outlet VC | C59: 1 | D59: 1.66 | E59: 1.46 | F59: 0.1 | G59: =ROUND((C59*D59*E59*F59),2) -> 0.24
E60: Sub Total | G60: =ROUND(SUM(G41:G59),2) -> 27.84 | H60: m3
B61: Deduct manhole opening | C61: 2 | D61: 0.2826 | F61: 0.1 | G61: =ROUND((C61*D61*F61),2) -> 0.06
E62: Total | G62: =ROUND((G60-G61),2) -> 27.78 | H62: m3
A63: 8 | B63: Centring and Shuttering Works for
B64: P.C.C. and R.C.C Works, PST
B65: Base Slab Long wall | C65: 2 | D65: 13.22 | F65: 0.28 | G65: =ROUND((C65*D65*F65),2) -> 7.4
B66: Short Wall | C66: 2 | E66: 5.22 | F66: 0.28 | G66: =ROUND((C66*E66*F66),2) -> 2.92
B67: Outer part of Long Wall | C67: 2 | D67: 12.32 | F67: 2.4 | G67: =ROUND((C67*D67*F67),2) -> 59.14
B68: Inner part of Long Wall | C68: 2 | D68: 12 | F68: 2.4 | G68: =ROUND((C68*D68*F68),2) -> 57.6
B69: Outer part of Short Wall | C69: 2 | D69: 4.32 | F69: 2.4 | G69: =ROUND((C69*D69*F69),2) -> 20.74
B70: Inner part of Short Wall | C70: 4 | D70: 4 | F70: 2.4 | G70: =ROUND((C70*D70*F70),2) -> 38.4
B71: Channel | C71: 2 | D71: 4.16 | E71: 0.35 | F71: 0.375 | G71: =ROUND((C71*D71*E71*F71),2) -> 1.09
B72: Scum collector | C72: 1 | D72: 4.16 | E72: 0.35 | F72: 0.375 | G72: =ROUND((C72*D72*E72*F72),2) -> 0.55
B73: Slab cover of Inlet VC | C73: 1 | D73: 1.2 | E73: 1 | G73: =ROUND((C73*D73*E73),2) -> 1.2
B74: Slab cover of Outlet VC | C74: 1 | D74: 1.2 | E74: 1 | G74: =ROUND((C74*D74*E74),2) -> 1.2
B75: sides Inlet VC | C75: 2 | D75: 4.32 | E75: 0.1 | G75: =ROUND((C75*D75*E75),2) -> 0.86
B76: sides outlet VC | C76: 2 | D76: 4.32 | E76: 0.1 | G76: =ROUND((C76*D76*E76),2) -> 0.86
B77: Baffle bottom | C77: 1 | D77: 4 | E77: 0.075 | G77: =ROUND((C77*D77*E77),2) -> 0.3
B78: Baffle wall | C78: 2 | D78: 4 | F78: 1.2 | G78: =ROUND((C78*D78*F78),2) -> 9.6
B79: Baffle slab | C79: 1 | D79: 2 | E79: 0.4 | G79: =ROUND((C79*D79*E79),2) -> 0.8
B80: sides | C80: 1 | D80: 3.2 | F80: 0.075 | G80: =ROUND((C80*D80*F80),2) -> 0.24
E81: Sub Total | G81: =ROUND(SUM(G65:G76),2) -> 191.96
B82: Deduct manhole opening | C82: 2 | D82: 0.2826 | G82: =ROUND((C82*D82),2) -> 0.57
E83: Total | G83: =ROUND((G81-G82),2) -> 191.39 | H83: m2
A84: 9 | B84: Reiforcement Works with Deformed
B85: bars Including supplying, Cutting,
B86: Bending and Placing in Position
B87: Base Slab
B88: Main bar 12 mm dia at 175mm c/c Hor top | C88: 77 | D88: 6.42 | E88: 0.881712 | F88: kg/m | G88: =ROUND((C88*D88*E88),2) -> 435.87
B89: Dist bar 10 mm dia at 200mm c/c Hor top | C89: 28 | D89: 14.22 | E89: 0.6123 | F89: kg/m | G89: =ROUND((C89*D89*E89),2) -> 243.79
B90: Main bar 12 mm dia at 175 mm c/c Hor bot | C90: 77 | D90: 6.42 | E90: 0.881712 | F90: kg/m | G90: =ROUND((C90*D90*E90),2) -> 435.87
B91: Dist bar 10 mm dia at 200 mm c/c Hor bot | C91: 28 | D91: 14.22 | E91: 0.6123 | F91: kg/m | G91: =ROUND((C91*D91*E91),2) -> 243.79
B92: Haunch Bar
B93: Haunch bar 12 mm dia at 200mm c/c diag | C93: 135 | D93: 1.2 | E93: 0.881712 | F93: kg/m | G93: =ROUND((C93*D93*E93),2) -> 142.84
B94: Haunch bar 12 mm dia at 200mm c/c diag | C94: 55 | D94: 1.2 | E94: 0.881712 | F94: kg/m | G94: =ROUND((C94*D94*E94),2) -> 58.19
G95: =ROUND(SUM(G88:G94),2) -> 1560.35 | H95: kg
B96: Long Walls
B97: Main bar inner 12 mm dia 150mm c/c verIF | C97: 167 | D97: 3.18 | E97: 0.881712 | F97: kg/m | G97: =ROUND((C97*D97*E97),2) -> 468.24
B98: Dist bar 10 mm dia at 300 mm c/c Hor IF | C98: 18 | D98: 13.32 | E98: 0.6123 | F98: kg/m | G98: =ROUND((C98*D98*E98),2) -> 146.81
B99: Main bar outer 12 mm dia200mm c/c verOF | C99: 126 | D99: 3.18 | E99: 0.881712 | F99: kg/m | G99: =ROUND((C99*D99*E99),2) -> 353.28
B100: Dist bar 10 mm dia at 300 mm c/c Hor OF | C100: 18 | D100: 13.32 | E100: 0.6123 | F100: kg/m | G100: =ROUND((C100*D100*E100),2) -> 146.81
G101: =ROUND(SUM(G97:G100),2) -> 1115.14 | H101: kg
A103: Component: Plain Sedimentation Tank
A105: S.N. | B105: Description of Works | C105: No | D105: Length (m) | E105: Breadth (m) | F105: Height (m) | G105: Quantity | H105: Units
B106: Short Wall
...

Sheet QTY.Reservoir_400m3
A1: DETAIL QUANTITY ESTIMATES OF CIRCULAR RCC RESERVOIR 400 m3
A3: Description of Work :- Circular RCC Ground Reservoir (400 cu m)
A4: S.No. | B4: Description of Works | C4: No. | D4: Length | E4: Breadth | F4: Height | G4: Quantity | H4: Remarks
A5: I. | K5: =11.4+2*0.65+2*0.6 -> 13.9
A6: 1 | B6: Site Clearance | C6: 1 | D6: =PI()*(14^2)/4 -> 153.93804 | E6: Area | G6: =C6*D6 -> 153.93804
F7: Total | G7: =G6 -> 153.93804 | H7: m2
A8: 2 | B8: Earthwork in excavation in foundation | C8: 1 | D8: =PI()*(14^2)/4 -> 153.93804 | E8: Area | F8: 1.35 | G8: =C8*D8*F8 -> 207.81635
F9: Total | G9: =G8 -> 207.81635 | H9: m3
A10: 3 | B10: Stone soling | C10: 1 | D10: =PI()*(13.9^2)/4 -> 151.74678 | E10: Area | F10: 0.2 | G10: =C10*D10*F10 -> 30.349356
F11: Total | G11: =G10 -> 30.349356 | H11: m3
A12: 4 | B12: Plain Cement Concrete P.C.C. (M10) in 1:3:6
B13: Base | C13: 1 | D13: =D10 -> 151.74678 | E13: Area | F13: 0.15 | G13: =C13*D13*F13 -> 22.762017
F14: Total | G14: =G13 -> 22.762017 | H14: m3
A15: 5 | B15: Cement Concrete work for R.C.C (1:1.5:3) (M20) for
B16: Base | C16: 1 | D16: =PI()*(13.9^2)/4 -> 151.74678 | E16: Area | F16: 0.72 | G16: =F16*D16*C16 -> 109.25768
B17: Wall L = pi * 11.825m | C17: 1 | D17: =PI()*(11.4+2*0.425) -> 38.48451 | E17: =(0.2+0.65)/2 -> 0.425 | F17: 4.35 | G17: =+F17*E17*D17*C17 -> 71.148238
B18: Ring Beam | C18: 1 | D18: =PI()*(11.4+2*0.45+2*0.175) -> 39.741147 | E18: 0.35 | F18: 0.35 | G18: =+F18*E18*D18*C18 -> 4.8682905
B19: Top slab | C19: 1 | D19: 17.3025 | E19: Cu m | G19: =D19*C19 -> 17.3025
B20: Deduction for ventilation | C20: -1 | D20: =PI()*(1^2)/4 -> 0.78539816 | E20: Area | F20: 0.15 | G20: =C20*D20*F20 -> -0.11780972
B21: Wall of ventilation | C21: 1 | D21: =PI()*1.15 -> 3.6128316 | E21: 0.15 | F21: 0.42 | G21: =C21*D21*E21*F21 -> 0.22760839
C22: 1 | D22: =PI()*1.25 -> 3.9269908 | E22: 0.05 | F22: 0.08 | G22: =C22*D22*E22*F22 -> 0.015707963
B23: Ventilation slab cover on top | C23: 1 | D23: =PI()*1.18^2/4 -> 1.0935884 | E23: Area | F23: 0.075 | G23: =C23*D23*F23 -> 0.08201913
B24: Deduction for ventilating holes on slab tob | C24: -4 | D24: =PI()*(0.23^2)/4 -> 0.041547563 | E24: Area | F24: 0.15 | G24: =C24*D24*F24 -> -0.024928538
F25: Total | G25: =SUM(G16:G24) -> 202.75931 | H25: m3
A26: 6 | B26: Reinforcement Bar for RCC | G26: 12562 | H26: Kg
A27: 7 | B27: Erecting, centering and shuttering of formwork for RCC
B28: Base edge | C28: 1 | D28: =PI()*13.9 -> 43.668138 | F28: 0.15 | G28: =F28*D28*C28 -> 6.5502207
B29: Tank Base edge | C29: 1 | D29: =PI()*13.9 -> 43.668138 | F29: 0.6 | G29: =F29*D29*C29 -> 26.200883
B30: Inner Wall | C30: 1 | D30: =PI()*11.4 -> 35.814156 | F30: 4.7 | G30: =F30*D30*C30 -> 168.32653
B31: Outer Wall | C31: 1 | D31: =PI()*(11.4+2*0.65) -> 39.898227 | F31: 4.35 | G31: =F31*D31*C31 -> 173.55729
B32: Ring Beam | C32: 1 | D32: =PI()*(11.4+2*0.45+0.35) -> 39.741147 | F32: =3*0.35-0.2 -> 0.85 | G32: =F32*D32*C32 -> 33.779975
B33: Top Slab Bottom | C33: 1 | D33: =PI()*11.92^2/4 -> 111.5944 | E33: Area | G33: =D33*C33 -> 111.5944
B34: Ventilation Wall (Inner) | C34: 1 | D34: =PI()*1 -> 3.1415927 | F34: 0.56 | G34: =C34*D34*F34 -> 1.7592919
C35: 1 | D35: =PI()*1.2 -> 3.7699112 | F35: 0.08 | G35: =C35*D35*F35 -> 0.30159289
B36: Ventilation Wall (Outer) | C36: 1 | D36: =PI()*1.3 -> 4.0840704 | F36: 0.5 | G36: =C36*D36*F36 -> 2.0420352
B37: Deduction for ventilation | C37: -1 | D37: =PI()*1^2/4 -> 0.78539816 | E37: Area | G37: =C37*D37 -> -0.78539816
B38: Deduction for ventilating holes on slab tob | C38: -4 | D38: =D24 -> 0.041547563 | E38: Area | G38: =C38*D38 -> -0.16619025
B39: Top Ventilating Slab | C39: 1 | D39: =PI()*(1^2)/4 -> 0.78539816 | E39: Area | G39: =C39*D39 -> 0.78539816
B40: Edge of top ventilating slab | C40: 1 | D40: =PI()*1.18 -> 3.7070793 | F40: 0.075 | G40: =C40*D40*F40 -> 0.27803095
F41: Total | G41: =SUM(G28:G40) -> 524.22406 | H41: m2
A42: 8 | B42: 12.5 mm thick outside cement plaster in 1:4 C/M | P42: =SQRT(4*77.86/PI()) -> 9.9566275
B43: Outer Wall | C43: 1 | D43: =PI()*(11.4+2*0.65) -> 39.898227 | F43: 4 | G43: =C43*D43*F43 -> 159.59291
B44: Ring Beam | C44: 1 | D44: =D32 -> 39.741147 | F44: =F32 -> 0.85 | G44: =C44*D44*F44 -> 33.779975
B45: Slab tob | C45: 1 | D45: =PI()*(12.594^2)/4 -> 124.57109 | E45: Area | G45: =C45*D45 -> 124.57109
B46: Ventilation Wall | C46: 1 | D46: =PI()*1.3 -> 4.0840704 | F46: 0.5 | G46: =C46*D46*F46 -> 2.0420352
B47: Cover slab | C47: 1 | D47: =PI()*1.18^2/4 -> 1.0935884 | E47: Area | G47: =C47*D47 -> 1.0935884
B48: Cover slab edge | C48: 1 | D48: =PI()*1.18 -> 3.7070793 | F48: 0.075 | G48: =C48*D48*F48 -> 0.27803095
B49: Deduction for ventilation | C49: -1 | D49: =PI()*1^2/4 -> 0.78539816 | E49: Area | G49: =C49*D49 -> -0.78539816
B50: Deduction for ventilating holes on slab tob | C50: -4 | D50: =PI()*(0.23^2)/4 -> 0.041547563 | E50: Area | G50: =C50*D50 -> -0.16619025
F51: Total | G51: =SUM(G43:G50) -> 320.40604 | H51: m2 | P51: =K51-O51 -> 0 | Q51: =P51/4.5 -> 0 | R51: =Q51/PI() -> 0
A52: 9 | B52: 20 mm thick cement plaster inside tank 1:3 C/M | P52: =K52-O52 -> 0
B53: Inner Wall | C53: 1 | D53: =PI()*11.4 -> 35.814156 | F53: 4.7 | G53: =F53*D53*C53 -> 168.32653
B54: Floor | C54: 1 | D54: =PI()*11.4^2/4 -> 102.07035 | E54: Area | G54: =D54*C54 -> 102.07035
F55: Total | G55: =SUM(G53:G54) -> 270.39688 | H55: m2
A56: 10 | B56: 12.5 mm thick Cement Sand plaster in 1:4 C/M in Ceiling
B57: Ceiling | C57: 1 | D57: =PI()*(11.92^2)/4 -> 111.5944 | E57: Area | G57: =D57*C57 -> 111.5944
F58: Total | G58: =G57 -> 111.5944 | H58: m2
A59: 11-a | B59: Providing Crystalline Water Proof Treatment | C59: 1 | G59: =G55+G58 -> 381.99128 | H59: m2
A60: 11-b | B60: 3 mm thick Cement Punning | C60: 1 | G60: =G55 -> 270.39688 | H60: m2
A61: 12 | B61: Earthwork in backfilling
C62: 1 | D62: =PI()*13.9 -> 43.668138 | E62: 0.6 | F62: 0.4 | G62: =F62*E62*D62*C62 -> 10.480353
C63: 1 | D63: =PI()*13.9 -> 43.668138 | E63: 0.1 | F63: 0.2 | G63: =F63*E63*D63*C63 -> 0.87336276
F64: Total | G64: =SUM(G62:G63) -> 11.353716 | H64: m3
A65: 13 | B65: 250 mm thick Plain G.l. Sheet of 16SW Gas a water-stop supplying and fixing | C65: 1 | D65: =PI()*(11.4+2*0.45+0.2) -> 39.269908 | G65: =C65*D65 -> 39.269908 | H65: m
A66: 14 | B66: 32mm día. Gl pipe railings and staircase | G66: 48 | H66: m
A67: 15 | B67: 2 coat enamel paint in railing & inspection ladders on top of primer | G67: 48 | H67: m2
A68: 16 | B68: Ventilations of Wooden Frame With Chicken Wire Mesh & Mosquito Mesh | G68: 4 | H68: set
A69: 16 | B69: Manhole Cover | G69: 2 | H69: set
A70: 17 | B70: Supply and installation Pipes & Fittings
B71: 250mm dia DI Pipes | C71: 5 | G71: =C71 -> 5 | H71: m
B72: 250mm dia Sluice Valve | C72: 1 | G72: =C72 -> 1 | H72: No.
B73: Mechanical Coupling 250mm dia | C73: 1 | G73: =C73 -> 1 | H73: No.
B74: 250 Bend 90 | C74: 2 | G74: =C74 -> 2 | H74: No.
A76: II. | B76: Surface Drainage Works
A77: 1 | B77: Earthwork in Excavation | C77: 1 | D77: 78.32 | E77: 1.6 | F77: 1.03031 | G77: =C77*D77*E77*F77 -> 129.11021 | H77: Cu m
F78: Total | G78: =G77 -> 129.11021 | H78: Cu m
A79: 2 | B79: Fiat Brick Soiing | C79: 1 | D79: =PI()*24.93003 -> 78.319999 | E79: 1 | G79: =C79*D79*E79 -> 78.319999 | H79: Sq m
F80: Total | G80: =G79 -> 78.319999 | H80: Sq m
A81: 3 | B81: M-10 Grade Concreting Work for Lean Concrete (1:3:6) in Foundation | C81: 1 | D81: 78.32 | E81: 1 | F81: 0.075 | G81: =C81*D81*E81*F81 -> 5.874 | H81: Cu m
F82: Total | G82: =G81 -> 5.874 | H82: Cu m
A83: 4 | B83: Formwork
B84: Base | C84: 1 | D84: =2*81.43+2*1 -> 164.86 | F84: 0.075 | G84: =C84*D84*F84 -> 12.3645 | H84: Sq m
F85: Total | G85: =G84 -> 12.3645 | H85: Sq m
A86: 5 | B86: Brick Work in 1:4 C/S | C86: 2 | D86: 80 | E86: 0.23 | F86: 0.448 | G86: =F86*E86*D86*C86 -> 16.4864 | H86: Cu m
F87: Total | G87: =G86 -> 16.4864 | H87: Cu m
A88: 6 | B88: 12.5 mm thick cement plaster in 1:4 C/M | C88: 1 | D88: 80.247 | E88: 3.3 | G88: =C88*D88*E88 -> 264.8151 | H88: Sq m
A89: 7 | B89: Earth Work in Back Filling | G89: 124.86 | H89: Cu m
A90: 8 | B90: Grass Turfing Around Tank Área | C90: 1 | D90: 75 | E90: 6 | G90: =C90*D90*E90 -> 450 | H90: Sq m

Sheet Source
A1: Description of Sources
E4: Discharge | F4: Date | G4: Yield | I4: Quality | J4: Dispute | K4: Remarks
A5: S.No. | B5: Name of Source | C5: Location of source | D5: Type of Source | E5: measured | F5: of | G5: Safe | H5: Tapped | I5: (by eye observation) | K5: (Specify if land slide upstream settlement, pollution, etc)
C6: Place, VDC-wards | E6: Lps | F6: Measurement | G6: Lps | H6: Lps
A8: 1 | B8: Kakune Khola | C8: Bame | D8: Stream | E8: 0.88 | G8: =E8*0.9 -> 0.792 | H8: 0.88 | I8: Good | J8: No | K8: Not any
A9: 2 | B9: Bara Khola | C9: Bame | D9: Stream | E9: 0.29 | G9: =E9*0.9 -> 0.261 | H9: 0.29 | I9: Good | J9: No | K9: Not any
A10: 3 | C10: Bame | D10: Spring | E10: 0.5 | G10: =E10*0.9 -> 0.45 | H10: 0.5 | I10: Good | J10: No | K10: Not any

Sheet Pipe-existing
A1: Procurement of Pipes
I2: Rate of HDPE Pipe = | J2: 250
A3: S.No. | B3: Pipe size and series | D3: Unit | E3: Quantity | F3: Rate | G3: Amount
F4: Rs./unit | G4: Rs.
A5: 1 | B5: HDPE pipes
K6: Scheme 1
B7: 32 | C7: 6 | D7: m | E7: =N19 -> 0 | F7: Existing | G7: Existing | K7: Tr | L7: Dr | M7: Total | N7: DL
B8: 40 | C8: 6 | D8: m | E8: =N20 -> 0 | F8: Existing | G8: Existing | J8: GPM-15 | K8: 0 | L8: 0 | M8: =K8+L8 -> 0 | N8: =ROUNDUP(M8*1.1,0) -> 0
B9: 50 | C9: 6 | D9: m | E9: =N21 -> 0 | F9: Existing | G9: Existing | J9: GPM-20 | K9: 0 | L9: 0 | M9: =K9+L9 -> 0 | N9: =ROUNDUP(M9*1.1,0) -> 0
B10: 63 | C10: 6 | D10: m | E10: =N22 -> 0 | F10: Existing | G10: Existing | J10: GPM-25 | K10: 0 | L10: 0 | M10: =K10+L10 -> 0 | N10: =ROUNDUP(M10*1.1,0) -> 0
B11: 75 | C11: 6 | D11: m | E11: =N23 -> 0 | F11: Existing | G11: Existing | J11: GPM-32 | K11: 0 | L11: 0 | M11: =K11+L11 -> 0 | N11: =ROUNDUP(M11*1.1,0) -> 0
B12: 90 | C12: 6 | D12: m | E12: =N24 -> 0 | F12: Existing | G12: Existing | J12: GPM-40 | K12: 0 | L12: 0 | M12: =K12+L12 -> 0 | N12: =ROUNDUP(M12*1.1,0) -> 0
B13: 110 | C13: 6 | D13: m | E13: =N25 -> 0 | F13: Existing | G13: Existing | J13: GPM-50 | K13: 0 | L13: 0 | M13: =K13+L13 -> 0 | N13: =ROUNDUP(M13*1.1,0) -> 0
B14: 125 | C14: 6 | D14: m | E14: =N26 -> 0 | F14: Existing | G14: Existing | J14: GPM-65 | M14: =K14+L14 -> 0 | N14: =ROUNDUP(M14*1.1,0) -> 0
B15: 16 | C15: 10 | D15: m | E15: =N27 -> 0 | F15: Existing | G15: Existing | J15: GPM-80 | M15: =K15+L15 -> 0 | N15: =ROUNDUP(M15*1.1,0) -> 0
B16: 20 | C16: 10 | D16: m | E16: =N28 -> 0 | F16: Existing | G16: Existing | J16: GPM-100 | M16: =K16+L16 -> 0 | N16: =ROUNDUP(M16*1.1,0) -> 0 | O16: scheme 2
B17: 25 | C17: 10 | D17: m | E17: =N29 -> 0 | F17: Existing | G17: Existing | J17: GPM-125 | M17: =K17+L17 -> 0 | N17: =ROUNDUP(M17*1.1,0) -> 0 | O17: scheme 1
B18: 32 | C18: 10 | D18: m | E18: =N30 -> 0 | F18: Existing | G18: Existing | J18: GPM-150 | M18: =K18+L18 -> 0 | N18: =ROUNDUP(M18*1.1,0) -> 0
B19: 40 | C19: 10 | D19: m | E19: =N31 -> 0 | F19: Existing | G19: Existing | J19: HP6-32 | M19: =K19+L19 -> 0 | N19: =ROUNDUP(M19*1.1,0) -> 0
B20: 50 | C20: 10 | D20: m | E20: =N32 -> 1565 | F20: Existing | G20: Existing | J20: HP6-40 | M20: =K20+L20 -> 0 | N20: =ROUNDUP(M20*1.1,0) -> 0
B21: 63 | C21: 10 | D21: m | E21: =N33 -> 1138 | F21: Existing | G21: Existing | J21: HP6-50 | M21: =K21+L21 -> 0 | N21: =ROUNDUP(M21*1.1,0) -> 0
B22: 75 | C22: 10 | D22: m | E22: =N34 -> 2657 | F22: Existing | G22: Existing | J22: HP6-63 | M22: =K22+L22 -> 0 | N22: =ROUNDUP(M22*1.1,0) -> 0
B23: 90 | C23: 10 | D23: m | E23: =N35 -> 1362 | F23: Existing | G23: Existing | J23: HP6-75 | M23: =K23+L23 -> 0 | N23: =ROUNDUP(M23*1.1,0) -> 0 | Q23: 1379.6
B24: 110 | C24: 10 | D24: m | E24: =N36 -> 772 | F24: Existing | G24: Existing | J24: HP6-90 | M24: =K24+L24 -> 0 | N24: =ROUNDUP(M24*1.1,0) -> 0
B25: 125 | C25: 10 | D25: m | E25: =N37 -> 0 | F25: Existing | G25: Existing | J25: HP6-110 | M25: =K25+L25 -> 0 | N25: =ROUNDUP(M25*1.1,0) -> 0
B26: 110 | C26: 4 | D26: m | F26: Existing | G26: Existing | J26: HP6-125 | M26: =K26+L26 -> 0 | N26: =ROUNDUP(M26*1.1,0) -> 0
B27: 63 | C27: 4 | D27: m | F27: Existing | G27: Existing | J27: HP10-16 | M27: =K27+L27 -> 0 | N27: =ROUNDUP(M27*1.1,0) -> 0
B28: 250 | C28: 10 | D28: m | E28: =N43 -> 27 | F28: Existing | G28: Existing | J28: HP10-20 | M28: =K28+L28 -> 0 | N28: =ROUNDUP(M28*1.1,0) -> 0
J29: HP10-25 | M29: =K29+L29 -> 0 | N29: =ROUNDUP(M29*1.1,0) -> 0
C30: Subtotal | E30: =SUM(E7:E29) -> 7521 | F30: Rs. | G30: =SUM(G7:G29) -> 0 | J30: HP10-32 | M30: =K30+L30 -> 0 | N30: =ROUNDUP(M30*1.1,0) -> 0
B31: Add transportation cost | F31: 5 | G31: =F31*G30/100 -> 0 | J31: HP10-40 | M31: =K31+L31 -> 0 | N31: =ROUNDUP(M31*1.1,0) -> 0
C32: Total | G32: =SUM(G30:G31) -> 0 | J32: HP10-50 | L32: 1422 | M32: =K32+L32 -> 1422 | N32: =ROUNDUP(M32*1.1,0) -> 1565
B33: Value added Tax | F33: ='Entry for Rates'!$F$114 -> 13 | G33: =F33*G32/100 -> 0 | J33: HP10-63 | L33: 1034 | M33: =K33+L33 -> 1034 | N33: =ROUNDUP(M33*1.1,0) -> 1138
B34: Total cost of HDPE pipes | F34: Rs. | G34: =+G33+G32 -> 0 | J34: HP10-75 | K34: 0 | L34: 2415 | M34: =K34+L34 -> 2415 | N34: =ROUNDUP(M34*1.1,0) -> 2657
A35: 2 | B35: GI pipes | J35: HP10-90 | K35: 0 | L35: 1238 | M35: =K35+L35 -> 1238 | N35: =ROUNDUP(M35*1.1,0) -> 1362
B36: 15 | C36: GI (Heavy) | D36: m | E36: =N8 -> 0 | F36: =IF(C36="GI (Medium)",VLOOKUP(B36,data!$A$4:$D$14,4,FALSE),IF(C36="GI (Heavy)",VLOOKUP(B36,data!$A$17:$D$27,4,FALSE),0)) -> 203 | G36: =+ROUND(E36*F36,2) -> 0 | J36: HP10-110 | K36: 0 | L36: 701 | M36: =K36+L36 -> 701 | N36: =ROUNDUP(M36*1.1,0) -> 772
B37: 25 | C37: GI (Heavy) | D37: m | E37: =N10 -> 0 | F37: =IF(C37="GI (Medium)",VLOOKUP(B37,data!$A$4:$D$14,4,FALSE),IF(C37="GI (Heavy)",VLOOKUP(B37,data!$A$17:$D$27,4,FALSE),0)) -> 383 | G37: =+ROUND(E37*F37,2) -> 0 | J37: HP10-125 | K37: 0 | L37: 0 | M37: =K37+L37 -> 0 | N37: =ROUNDUP(M37*1.1,0) -> 0
B38: 32 | C38: GI (Heavy) | D38: m | E38: =N11 -> 0 | F38: =IF(C38="GI (Medium)",VLOOKUP(B38,data!$A$4:$D$14,4,FALSE),IF(C38="GI (Heavy)",VLOOKUP(B38,data!$A$17:$D$27,4,FALSE),0)) -> 490 | G38: =+ROUND(E38*F38,2) -> 0 | J38: HP10-140 | L38: 0 | M38: =K38+L38 -> 0 | N38: =ROUNDUP(M38*1.1,0) -> 0
B39: 40 | C39: GI (Heavy) | D39: m | E39: =N12 -> 0 | F39: =IF(C39="GI (Medium)",VLOOKUP(B39,data!$A$4:$D$14,4,FALSE),IF(C39="GI (Heavy)",VLOOKUP(B39,data!$A$17:$D$27,4,FALSE),0)) -> 565 | G39: =+ROUND(E39*F39,2) -> 0 | J39: HP10-160 | L39: 726 | M39: =K39+L39 -> 726 | N39: =ROUNDUP(M39*1.1,0) -> 799
B40: 50 | C40: GI (Heavy) | D40: m | E40: =N13 -> 0 | F40: =IF(C40="GI (Medium)",VLOOKUP(B40,data!$A$4:$D$14,4,FALSE),IF(C40="GI (Heavy)",VLOOKUP(B40,data!$A$17:$D$27,4,FALSE),0)) -> 823 | G40: =+ROUND(E40*F40,2) -> 0 | J40: HP10-180 | L40: 0 | M40: =K40+L40 -> 0 | N40: =ROUNDUP(M40*1.1,0) -> 0
B41: 80 | C41: GI (Heavy) | D41: m | E41: =N14 -> 0 | F41: =IF(C41="GI (Medium)",VLOOKUP(B41,data!$A$4:$D$14,4,FALSE),IF(C41="GI (Heavy)",VLOOKUP(B41,data!$A$17:$D$27,4,FALSE),0)) -> 1215 | G41: =+ROUND(E41*F41,2) -> 0 | J41: HP10-200 | L41: 145 | M41: =K41+L41 -> 145 | N41: =ROUNDUP(M41*1.1,0) -> 160
B42: 100 | C42: GI (Heavy) | D42: m | E42: =N16 -> 0 | F42: =IF(C42="GI (Medium)",VLOOKUP(B42,data!$A$4:$D$14,4,FALSE),IF(C42="GI (Heavy)",VLOOKUP(B42,data!$A$17:$D$27,4,FALSE),0)) -> 1883 | G42: =+ROUND(E42*F42,2) -> 0 | J42: HP10-225 | L42: 0 | M42: =K42+L42 -> 0 | N42: =ROUNDUP(M42*1.1,0) -> 0
B43: 125 | C43: GI (Heavy) | D43: m | E43: =N17 -> 0 | F43: =IF(C43="GI (Medium)",VLOOKUP(B43,data!$A$4:$D$14,4,FALSE),IF(C43="GI (Heavy)",VLOOKUP(B43,data!$A$17:$D$27,4,FALSE),0)) -> 2440 | G43: =+ROUND(E43*F43,2) -> 0 | J43: HP10-250 | L43: 24 | M43: =K43+L43 -> 24 | N43: =ROUNDUP(M43*1.1,0) -> 27
B44: 150 | C44: GI (Heavy) | D44: m | E44: =N18 -> 0 | F44: =IF(C44="GI (Medium)",VLOOKUP(B44,data!$A$4:$D$14,4,FALSE),IF(C44="GI (Heavy)",VLOOKUP(B44,data!$A$17:$D$27,4,FALSE),0)) -> 2767 | G44: =+ROUND(E44*F44,2) -> 0
B45: Total cost of GI pipes | E45: =SUM(E36:E44) -> 0 | G45: =SUM(G36:G44) -> 0
B46: Add transportation cost | F46: 5 | G46: =F46*G45/100 -> 0
C47: Total | G47: =SUM(G45:G46) -> 0 | M47: =SUM(M8:M43) -> 7705 | N47: =SUM(N8:N43) -> 8480
B48: Value added Tax | F48: ='[62]Entry for Rates'!$F$114 -> 13 | G48: =F48*G45/100 -> 0
B49: Total Cost of GI Pipes With VAT | G49: =G47+G48 -> 0
C50: Total cost of HDPE and GI pipes | E50: =+E45+E30 -> 7521 | F50: Rs. | G50: =+G49+G34 -> 0
A52: Detailed Quantities of Pipes & Fittings and Transportation
A54: S.No. | B54: Pipe size and series | D54: Unit | E54: Actual length | F54: Unit weight | G54: Total weight ( kg )
B55: Scheme No - 1
A56: 1 | B56: HDPE pipes
B57: =B7 -> 32 | C57: =C7 -> 6 | D57: =D7 -> m | E57: =E7 -> 0 | F57: =VLOOKUP(B57+C57,data!$A$31:$E$89,4,FALSE) -> 0.226 | G57: =E57*F57 -> 0
B58: =B8 -> 40 | C58: =C8 -> 6 | D58: =D8 -> m | E58: =E8 -> 0 | F58: =VLOOKUP(B58+C58,data!$A$31:$E$89,4,FALSE) -> 0.35 | G58: =E58*F58 -> 0
B59: =B9 -> 50 | C59: =C9 -> 6 | D59: =D9 -> m | E59: =E9 -> 0 | F59: =VLOOKUP(B59+C59,data!$A$31:$E$89,4,FALSE) -> 0.542 | G59: =E59*F59 -> 0
B60: =B10 -> 63 | C60: =C10 -> 6 | D60: =D10 -> m | E60: =E10 -> 0 | F60: =VLOOKUP(B60+C60,data!$A$31:$E$89,4,FALSE) -> 0.85 | G60: =E60*F60 -> 0
B61: =B11 -> 75 | C61: =C11 -> 6 | D61: =D11 -> m | E61: =E11 -> 0 | F61: =VLOOKUP(B61+C61,data!$A$31:$E$89,4,FALSE) -> 1.191 | G61: =E61*F61 -> 0
B62: =B12 -> 90 | C62: =C12 -> 6 | D62: =D12 -> m | E62: =E12 -> 0 | F62: =VLOOKUP(B62+C62,data!$A$31:$E$89,4,FALSE) -> 1.715 | G62: =E62*F62 -> 0
B63: =B13 -> 110 | C63: =C13 -> 6 | D63: =D13 -> m | E63: =E13 -> 0 | F63: =VLOOKUP(B63+C63,data!$A$31:$E$89,4,FALSE) -> 2.545 | G63: =E63*F63 -> 0
B64: =B14 -> 125 | C64: =C14 -> 6 | D64: =D14 -> m | E64: =E14 -> 0 | F64: =VLOOKUP(B64+C64,data!$A$31:$E$89,4,FALSE) -> 3.293 | G64: =E64*F64 -> 0
B65: =B15 -> 16 | C65: =C15 -> 10 | D65: =D15 -> m | E65: =E15 -> 0 | F65: =VLOOKUP(B65+C65,data!$A$31:$E$89,4,FALSE) -> 0.092 | G65: =E65*F65 -> 0
B66: =B16 -> 20 | C66: =C16 -> 10 | D66: =D16 -> m | E66: =E16 -> 0 | F66: =VLOOKUP(B66+C66,data!$A$31:$E$89,4,FALSE) -> 0.134 | G66: =E66*F66 -> 0
B67: =B17 -> 25 | C67: =C17 -> 10 | D67: =D17 -> m | E67: =E17 -> 0 | F67: =VLOOKUP(B67+C67,data!$A$31:$E$89,4,FALSE) -> 0.202 | G67: =E67*F67 -> 0
B68: =B18 -> 32 | C68: =C18 -> 10 | D68: =D18 -> m | E68: =E18 -> 0 | F68: =VLOOKUP(B68+C68,data!$A$31:$E$89,4,FALSE) -> 0.334 | G68: =E68*F68 -> 0
... B77: =B27 -> 63 | C77: =C27 -> 4 | D77: =D27 -> m | E77: =E27 -> 0 | F77: =VLOOKUP(B77+C77,data!$A$31:$E$89,4,FALSE) -> 0.585 | G77: =E77*F77 -> 0
B78: 250 | C78: 10 | D78: m | E78: =E28 -> 27 | F78: =VLOOKUP(B78+C78,data!$A$31:$E$89,4,FALSE) -> 19.757 | G78: =E78*F78 -> 533.439
C79: Subtotal | E79: =SUM(E57:E78) -> 7521 | G79: =SUM(G57:G78) -> 14390.063
B80: GI pipes
B81: =B36 -> 15 | C81: =C36 -> GI (Heavy) | D81: =D36 -> m | E81: =E36 -> 0 | F81: =IF(C81="GI (Medium)",VLOOKUP(B81,data!$A$4:$D$14,3,FALSE),IF(C81="GI (Heavy)",VLOOKUP(B81,data!$A$17:$D$27,3,FALSE),0)) -> 1.513 | G81: =E81*F81 -> 0
B82: =B37 -> 25 | C82: =C37 -> GI (Heavy) | D82: =D37 -> m | E82: =E37 -> 0 | F82: =IF(C82="GI (Medium)",VLOOKUP(B82,data!$A$4:$D$14,3,FALSE),IF(C82="GI (Heavy)",VLOOKUP(B82,data!$A$17:$D$27,3,FALSE),0)) -> 3.077 | G82: =E82*F82 -> 0
B83: =B38 -> 32 | C83: =C38 -> GI (Heavy) | D83: =D38 -> m | E83: =E38 -> 0 | F83: =IF(C83="GI (Medium)",VLOOKUP(B83,data!$A$4:$D$14,3,FALSE),IF(C83="GI (Heavy)",VLOOKUP(B83,data!$A$17:$D$27,3,FALSE),0)) -> 3.968 | G83: =E83*F83 -> 0
B84: =B39 -> 40 | C84: =C39 -> GI (Heavy) | D84: =D39 -> m | E84: =E39 -> 0 | F84: =IF(C84="GI (Medium)",VLOOKUP(B84,data!$A$4:$D$14,3,FALSE),IF(C84="GI (Heavy)",VLOOKUP(B84,data!$A$17:$D$27,3,FALSE),0)) -> 4.587 | G84: =E84*F84 -> 0
B85: =B40 -> 50 | C85: =C40 -> GI (Heavy) | D85: =D40 -> m | E85: =E40 -> 0 | F85: =IF(C85="GI (Medium)",VLOOKUP(B85,data!$A$4:$D$14,3,FALSE),IF(C85="GI (Heavy)",VLOOKUP(B85,data!$A$17:$D$27,3,FALSE),0)) -> 6.369 | G85: =E85*F85 -> 0
B86: =B41 -> 80 | C86: =C41 -> GI (Heavy) | D86: =D41 -> m | E86: =E41 -> 0 | F86: =IF(C86="GI (Medium)",VLOOKUP(B86,data!$A$4:$D$14,3,FALSE),IF(C86="GI (Heavy)",VLOOKUP(B86,data!$A$17:$D$27,3,FALSE),0)) -> 10.417 | G86: =E86*F86 -> 0
B87: =B42 -> 100 | C87: =C42 -> GI (Heavy) | D87: =D42 -> m | E87: =E42 -> 0 | F87: =IF(C87="GI (Medium)",VLOOKUP(B87,data!$A$4:$D$14,3,FALSE),IF(C87="GI (Heavy)",VLOOKUP(B87,data!$A$17:$D$27,3,FALSE),0)) -> 15.436 | G87: =E87*F87 -> 0
B88: =B43 -> 125 | C88: =C43 -> GI (Heavy) | D88: =D43 -> m | E88: =E43 -> 0 | F88: =IF(C88="GI (Medium)",VLOOKUP(B88,data!$A$4:$D$14,3,FALSE),IF(C88="GI (Heavy)",VLOOKUP(B88,data!$A$17:$D$27,3,FALSE),0)) -> 18.52 | G88: =E88*F88 -> 0
B89: =B44 -> 150 | C89: =C44 -> GI (Heavy) | D89: =D44 -> m | E89: =E44 -> 0 | F89: =IF(C89="GI (Medium)",VLOOKUP(B89,data!$A$4:$D$14,3,FALSE),IF(C89="GI (Heavy)",VLOOKUP(B89,data!$A$17:$D$27,3,FALSE),0)) -> 22.22 | G89: =E89*F89 -> 0
B90: Subtotal | E90: =SUM(E81:E89) -> 0 | G90: =SUM(G81:G89) -> 0
B92: Weight of fittings and tools | G92: =(G79+G90)*0.15+FittingsSummary!AA126+tools!F39 -> 4376.6696
B93: Total weight of pipe and fittings for transportation | G93: =G79+G90+G92 -> 18766.733

Sheet Pipe
A1: Procurement of Pipes
I2: Rate of HDPE Pipe = | J2: 250
A3: S.No. | B3: Pipe size and series | D3: Unit | E3: Quantity | F3: Rate | G3: Amount
F4: Rs./unit | G4: Rs.
A5: 1 | B5: HDPE pipes
K6: Scheme 1
B7: 32 | C7: 6 | D7: m | E7: =N19 -> 0 | F7: =ROUND(VLOOKUP(B7+C7,data!$A$31:$E$89,4,FALSE)*J$2,2) -> 56.5 | G7: =+ROUND(E7*F7,2) -> 0 | K7: Tr | L7: Dr | M7: Total | N7: DL
B8: 40 | C8: 6 | D8: m | E8: =N20 -> 0 | F8: =ROUND(VLOOKUP(B8+C8,data!$A$31:$E$89,4,FALSE)*J$2,2) -> 87.5 | G8: =+ROUND(E8*F8,2) -> 0 | J8: GPM-15 | K8: 0 | L8: 0 | M8: =K8+L8 -> 0 | N8: =ROUNDUP(M8*1.1,0) -> 0
B9: 50 | C9: 6 | D9: m | E9: =N21 -> 0 | F9: =ROUND(VLOOKUP(B9+C9,data!$A$31:$E$89,4,FALSE)*J$2,2) -> 135.5 | G9: =+ROUND(E9*F9,2) -> 0 | J9: GPM-20 | K9: 0 | L9: 0 | M9: =K9+L9 -> 0 | N9: =ROUNDUP(M9*1.1,0) -> 0
B10: 63 | C10: 6 | D10: m | E10: =N22 -> 0 | F10: =ROUND(VLOOKUP(B10+C10,data!$A$31:$E$89,4,FALSE)*J$2,2) -> 212.5 | G10: =+ROUND(E10*F10,2) -> 0 | J10: GPM-25 | K10: 0 | L10: 0 | M10: =K10+L10 -> 0 | N10: =ROUNDUP(M10*1.1,0) -> 0
B11: 75 | C11: 6 | D11: m | E11: =N23 -> 0 | F11: =ROUND(VLOOKUP(B11+C11,data!$A$31:$E$89,4,FALSE)*J$2,2) -> 297.75 | G11: =+ROUND(E11*F11,2) -> 0 | J11: GPM-32 | K11: 0 | L11: 0 | M11: =K11+L11 -> 0 | N11: =ROUNDUP(M11*1.1,0) -> 0
B12: 90 | C12: 6 | D12: m | E12: =N24 -> 0 | F12: =ROUND(VLOOKUP(B12+C12,data!$A$31:$E$89,4,FALSE)*J$2,2) -> 428.75 | G12: =+ROUND(E12*F12,2) -> 0 | J12: GPM-40 | K12: 0 | L12: 0 | M12: =K12+L12 -> 0 | N12: =ROUNDUP(M12*1.1,0) -> 0
B13: 110 | C13: 6 | D13: m | E13: =N25 -> 0 | F13: =ROUND(VLOOKUP(B13+C13,data!$A$31:$E$89,4,FALSE)*J$2,2) -> 636.25 | G13: =+ROUND(E13*F13,2) -> 0 | J13: GPM-50 | K13: 0 | L13: 0 | M13: =K13+L13 -> 0 | N13: =ROUNDUP(M13*1.1,0) -> 0
B14: 125 | C14: 6 | D14: m | E14: =N26 -> 0 | F14: =ROUND(VLOOKUP(B14+C14,data!$A$31:$E$89,4,FALSE)*J$2,2) -> 823.25 | G14: =+ROUND(E14*F14,2) -> 0 | J14: GPM-65 | K14: 0 | L14: 0 | M14: =K14+L14 -> 0 | N14: =ROUNDUP(M14*1.1,0) -> 0
B15: 16 | C15: 10 | D15: m | E15: =N27 -> 0 | F15: =ROUND(VLOOKUP(B15+C15,data!$A$31:$E$89,4,FALSE)*J$2,2) -> 23 | G15: =+ROUND(E15*F15,2) -> 0 | J15: GPM-80 | K15: 0 | L15: 0 | M15: =K15+L15 -> 0 | N15: =ROUNDUP(M15*1.1,0) -> 0
B16: 20 | C16: 10 | D16: m | E16: =N28 -> 0 | F16: =ROUND(VLOOKUP(B16+C16,data!$A$31:$E$89,4,FALSE)*J$2,2) -> 33.5 | G16: =+ROUND(E16*F16,2) -> 0 | J16: GPM-100 | K16: 100 | L16: =1334.8+641.68 -> 1976.48 | M16: =K16+L16 -> 2076.48 | N16: =ROUNDUP(M16*1.1,0) -> 2285 | O16: scheme 2
B17: 25 | C17: 10 | D17: m | E17: =N29 -> 0 | F17: =ROUND(VLOOKUP(B17+C17,data!$A$31:$E$89,4,FALSE)*J$2,2) -> 50.5 | G17: =+ROUND(E17*F17,2) -> 0 | J17: GPM-125 | M17: =K17+L17 -> 0 | N17: =ROUNDUP(M17*1.1,0) -> 0 | O17: scheme 1
B18: 32 | C18: 10 | D18: m | E18: =N30 -> 0 | F18: =ROUND(VLOOKUP(B18+C18,data!$A$31:$E$89,4,FALSE)*J$2,2) -> 83.5 | G18: =+ROUND(E18*F18,2) -> 0 | J18: GPM-150 | K18: 158.63 | L18: 1231 | M18: =K18+L18 -> 1389.63 | N18: =ROUNDUP(M18*1.1,0) -> 1529
B19: 40 | C19: 10 | D19: m | E19: =N31 -> 0 | F19: =ROUND(VLOOKUP(B19+C19,data!$A$31:$E$89,4,FALSE)*J$2,2) -> 128.5 | G19: =+ROUND(E19*F19,2) -> 0 | J19: HP6-32 | M19: =K19+L19 -> 0 | N19: =ROUNDUP(M19*1.1,0) -> 0
B20: 50 | C20: 10 | D20: m | E20: =N32 -> 0 | F20: =ROUND(VLOOKUP(B20+C20,data!$A$31:$E$89,4,FALSE)*J$2,2) -> 199 | G20: =+ROUND(E20*F20,2) -> 0 | J20: HP6-40 | M20: =K20+L20 -> 0 | N20: =ROUNDUP(M20*1.1,0) -> 0
B21: 63 | C21: 10 | D21: m | E21: =N33 -> 0 | F21: =ROUND(VLOOKUP(B21+C21,data!$A$31:$E$89,4,FALSE)*J$2,2) -> 317.25 | G21: =+ROUND(E21*F21,2) -> 0 | J21: HP6-50 | M21: =K21+L21 -> 0 | N21: =ROUNDUP(M21*1.1,0) -> 0
B22: 75 | C22: 10 | D22: m | E22: =N34 -> 0 | F22: =ROUND(VLOOKUP(B22+C22,data!$A$31:$E$89,4,FALSE)*J$2,2) -> 445.5 | G22: =+ROUND(E22*F22,2) -> 0 | J22: HP6-63 | M22: =K22+L22 -> 0 | N22: =ROUNDUP(M22*1.1,0) -> 0
B23: 90 | C23: 10 | D23: m | E23: =N35 -> 0 | F23: =ROUND(VLOOKUP(B23+C23,data!$A$31:$E$89,4,FALSE)*J$2,2) -> 642 | G23: =+ROUND(E23*F23,2) -> 0 | J23: HP6-75 | M23: =K23+L23 -> 0 | N23: =ROUNDUP(M23*1.1,0) -> 0 | Q23: 1379.6
B24: 110 | C24: 10 | D24: m | E24: =N36 -> 0 | F24: =ROUND(VLOOKUP(B24+C24,data!$A$31:$E$89,4,FALSE)*J$2,2) -> 950.25 | G24: =+ROUND(E24*F24,2) -> 0 | J24: HP6-90 | M24: =K24+L24 -> 0 | N24: =ROUNDUP(M24*1.1,0) -> 0
B25: 125 | C25: 10 | D25: m | E25: =N37 -> 0 | F25: =ROUND(VLOOKUP(B25+C25,data!$A$31:$E$89,4,FALSE)*J$2,2) -> 1240.5 | G25: =+ROUND(E25*F25,2) -> 0 | J25: HP6-110 | M25: =K25+L25 -> 0 | N25: =ROUNDUP(M25*1.1,0) -> 0
B26: 110 | C26: 4 | D26: m | F26: =ROUND(VLOOKUP(B26+C26,data!$A$31:$E$89,4,FALSE)*J$2,2) -> 425.75 | G26: =+ROUND(E26*F26,2) -> 0 | J26: HP6-125 | M26: =K26+L26 -> 0 | N26: =ROUNDUP(M26*1.1,0) -> 0
B27: 63 | C27: 4 | D27: m | F27: =ROUND(VLOOKUP(B27+C27,data!$A$31:$E$89,4,FALSE)*J$2,2) -> 146.25 | G27: =+ROUND(E27*F27,2) -> 0 | J27: HP10-16 | M27: =K27+L27 -> 0 | N27: =ROUNDUP(M27*1.1,0) -> 0
B28: 250 | C28: 10 | D28: m | E28: =N43 -> 1518 | F28: =ROUND(VLOOKUP(B28+C28,data!$A$31:$E$89,4,FALSE)*J$2,2) -> 4939.25 | G28: =+ROUND(E28*F28,2) -> 7497781.5 | J28: HP10-20 | M28: =K28+L28 -> 0 | N28: =ROUNDUP(M28*1.1,0) -> 0
J29: HP10-25 | M29: =K29+L29 -> 0 | N29: =ROUNDUP(M29*1.1,0) -> 0
C30: Subtotal | E30: =SUM(E7:E29) -> 1518 | F30: Rs. | G30: =SUM(G7:G29) -> 7497781.5 | J30: HP10-32 | M30: =K30+L30 -> 0 | N30: =ROUNDUP(M30*1.1,0) -> 0
B31: Add transportation cost | F31: 5 | G31: =F31*G30/100 -> 374889.08 | J31: HP10-40 | M31: =K31+L31 -> 0 | N31: =ROUNDUP(M31*1.1,0) -> 0
C32: Total | G32: =SUM(G30:G31) -> 7872670.6 | J32: HP10-50 | M32: =K32+L32 -> 0 | N32: =ROUNDUP(M32*1.1,0) -> 0
B33: Value added Tax | F33: ='Entry for Rates'!$F$114 -> 13 | G33: =F33*G32/100 -> 1023447.2 | J33: HP10-63 | M33: =K33+L33 -> 0 | N33: =ROUNDUP(M33*1.1,0) -> 0
B34: Total cost of HDPE pipes | F34: Rs. | G34: =+G33+G32 -> 8896117.7 | J34: HP10-75 | K34: 0 | L34: 0 | M34: =K34+L34 -> 0 | N34: =ROUNDUP(M34*1.1,0) -> 0
A35: 2 | B35: GI pipes | J35: HP10-90 | K35: 0 | L35: 0 | M35: =K35+L35 -> 0 | N35: =ROUNDUP(M35*1.1,0) -> 0
B36: 15 | C36: GI (Heavy) | D36: m | E36: =N8 -> 0 | F36: =IF(C36="GI (Medium)",VLOOKUP(B36,data!$A$4:$D$14,4,FALSE),IF(C36="GI (Heavy)",VLOOKUP(B36,data!$A$17:$D$27,4,FALSE),0)) -> 203 | G36: =+ROUND(E36*F36,2) -> 0 | J36: HP10-110 | K36: 0 | L36: 0 | M36: =K36+L36 -> 0 | N36: =ROUNDUP(M36*1.1,0) -> 0
B37: 25 | C37: GI (Heavy) | D37: m | E37: =N10 -> 0 | F37: =IF(C37="GI (Medium)",VLOOKUP(B37,data!$A$4:$D$14,4,FALSE),IF(C37="GI (Heavy)",VLOOKUP(B37,data!$A$17:$D$27,4,FALSE),0)) -> 383 | G37: =+ROUND(E37*F37,2) -> 0 | J37: HP10-125 | K37: 0 | L37: 0 | M37: =K37+L37 -> 0 | N37: =ROUNDUP(M37*1.1,0) -> 0
B38: 32 | C38: GI (Heavy) | D38: m | E38: =N11 -> 0 | F38: =IF(C38="GI (Medium)",VLOOKUP(B38,data!$A$4:$D$14,4,FALSE),IF(C38="GI (Heavy)",VLOOKUP(B38,data!$A$17:$D$27,4,FALSE),0)) -> 490 | G38: =+ROUND(E38*F38,2) -> 0 | J38: HP10-140 | M38: =K38+L38 -> 0 | N38: =ROUNDUP(M38*1.1,0) -> 0
B39: 40 | C39: GI (Heavy) | D39: m | E39: =N12 -> 0 | F39: =IF(C39="GI (Medium)",VLOOKUP(B39,data!$A$4:$D$14,4,FALSE),IF(C39="GI (Heavy)",VLOOKUP(B39,data!$A$17:$D$27,4,FALSE),0)) -> 565 | G39: =+ROUND(E39*F39,2) -> 0 | J39: HP10-160 | M39: =K39+L39 -> 0 | N39: =ROUNDUP(M39*1.1,0) -> 0
B40: 50 | C40: GI (Heavy) | D40: m | E40: =N13 -> 0 | F40: =IF(C40="GI (Medium)",VLOOKUP(B40,data!$A$4:$D$14,4,FALSE),IF(C40="GI (Heavy)",VLOOKUP(B40,data!$A$17:$D$27,4,FALSE),0)) -> 823 | G40: =+ROUND(E40*F40,2) -> 0 | J40: HP10-180 | M40: =K40+L40 -> 0 | N40: =ROUNDUP(M40*1.1,0) -> 0
B41: 80 | C41: GI (Heavy) | D41: m | E41: =N14 -> 0 | F41: =IF(C41="GI (Medium)",VLOOKUP(B41,data!$A$4:$D$14,4,FALSE),IF(C41="GI (Heavy)",VLOOKUP(B41,data!$A$17:$D$27,4,FALSE),0)) -> 1215 | G41: =+ROUND(E41*F41,2) -> 0 | J41: HP10-200 | M41: =K41+L41 -> 0 | N41: =ROUNDUP(M41*1.1,0) -> 0
B42: 100 | C42: GI (Heavy) | D42: m | E42: =N16 -> 2285 | F42: =IF(C42="GI (Medium)",VLOOKUP(B42,data!$A$4:$D$14,4,FALSE),IF(C42="GI (Heavy)",VLOOKUP(B42,data!$A$17:$D$27,4,FALSE),0)) -> 1883 | G42: =+ROUND(E42*F42,2) -> 4302655 | J42: HP10-225 | M42: =K42+L42 -> 0 | N42: =ROUNDUP(M42*1.1,0) -> 0
B43: 125 | C43: GI (Heavy) | D43: m | E43: =N17 -> 0 | F43: =IF(C43="GI (Medium)",VLOOKUP(B43,data!$A$4:$D$14,4,FALSE),IF(C43="GI (Heavy)",VLOOKUP(B43,data!$A$17:$D$27,4,FALSE),0)) -> 2440 | G43: =+ROUND(E43*F43,2) -> 0 | J43: HP10-250 | L43: 1380 | M43: =K43+L43 -> 1380 | N43: =ROUNDUP(M43*1.1,0) -> 1518
B44: 150 | C44: GI (Heavy) | D44: m | E44: =N18 -> 1529 | F44: =IF(C44="GI (Medium)",VLOOKUP(B44,data!$A$4:$D$14,4,FALSE),IF(C44="GI (Heavy)",VLOOKUP(B44,data!$A$17:$D$27,4,FALSE),0)) -> 2767 | G44: =+ROUND(E44*F44,2) -> 4230743
B45: Total cost of GI pipes | E45: =SUM(E36:E44) -> 3814 | G45: =SUM(G36:G44) -> 8533398
B46: Add transportation cost | F46: 5 | G46: =F46*G45/100 -> 426669.9
C47: Total | G47: =SUM(G45:G46) -> 8960067.9 | M47: =SUM(M8:M43) -> 4846.11 | N47: =SUM(N8:N43) -> 5332
B48: Value added Tax | F48: ='[62]Entry for Rates'!$F$114 -> 13 | G48: =F48*G45/100 -> 1109341.7
B49: Total Cost of GI Pipes With VAT | G49: =G47+G48 -> 10069410
C50: Total cost of HDPE and GI pipes | E50: =+E45+E30 -> 5332 | F50: Rs. | G50: =+G49+G34 -> 18965527
A52: Detailed Quantities of Pipes & Fittings and Transportation
A54: S.No. | B54: Pipe size and series | D54: Unit | E54: Actual length | F54: Unit weight | G54: Total weight ( kg )
B55: Scheme No - 1
A56: 1 | B56: HDPE pipes
B57: =B7 -> 32 | C57: =C7 -> 6 | D57: =D7 -> m | E57: =E7 -> 0 | F57: =VLOOKUP(B57+C57,data!$A$31:$E$89,4,FALSE) -> 0.226 | G57: =E57*F57 -> 0
B58: =B8 -> 40 | C58: =C8 -> 6 | D58: =D8 -> m | E58: =E8 -> 0 | F58: =VLOOKUP(B58+C58,data!$A$31:$E$89,4,FALSE) -> 0.35 | G58: =E58*F58 -> 0
B59: =B9 -> 50 | C59: =C9 -> 6 | D59: =D9 -> m | E59: =E9 -> 0 | F59: =VLOOKUP(B59+C59,data!$A$31:$E$89,4,FALSE) -> 0.542 | G59: =E59*F59 -> 0
B60: =B10 -> 63 | C60: =C10 -> 6 | D60: =D10 -> m | E60: =E10 -> 0 | F60: =VLOOKUP(B60+C60,data!$A$31:$E$89,4,FALSE) -> 0.85 | G60: =E60*F60 -> 0
B61: =B11 -> 75 | C61: =C11 -> 6 | D61: =D11 -> m | E61: =E11 -> 0 | F61: =VLOOKUP(B61+C61,data!$A$31:$E$89,4,FALSE) -> 1.191 | G61: =E61*F61 -> 0
B62: =B12 -> 90 | C62: =C12 -> 6 | D62: =D12 -> m | E62: =E12 -> 0 | F62: =VLOOKUP(B62+C62,data!$A$31:$E$89,4,FALSE) -> 1.715 | G62: =E62*F62 -> 0
B63: =B13 -> 110 | C63: =C13 -> 6 | D63: =D13 -> m | E63: =E13 -> 0 | F63: =VLOOKUP(B63+C63,data!$A$31:$E$89,4,FALSE) -> 2.545 | G63: =E63*F63 -> 0
B64: =B14 -> 125 | C64: =C14 -> 6 | D64: =D14 -> m | E64: =E14 -> 0 | F64: =VLOOKUP(B64+C64,data!$A$31:$E$89,4,FALSE) -> 3.293 | G64: =E64*F64 -> 0
B65: =B15 -> 16 | C65: =C15 -> 10 | D65: =D15 -> m | E65: =E15 -> 0 | F65: =VLOOKUP(B65+C65,data!$A$31:$E$89,4,FALSE) -> 0.092 | G65: =E65*F65 -> 0
B66: =B16 -> 20 | C66: =C16 -> 10 | D66: =D16 -> m | E66: =E16 -> 0 | F66: =VLOOKUP(B66+C66,data!$A$31:$E$89,4,FALSE) -> 0.134 | G66: =E66*F66 -> 0
B67: =B17 -> 25 | C67: =C17 -> 10 | D67: =D17 -> m | E67: =E17 -> 0 | F67: =VLOOKUP(B67+C67,data!$A$31:$E$89,4,FALSE) -> 0.202 | G67: =E67*F67 -> 0
B68: =B18 -> 32 | C68: =C18 -> 10 | D68: =D18 -> m | E68: =E18 -> 0 | F68: =VLOOKUP(B68+C68,data!$A$31:$E$89,4,FALSE) -> 0.334 | G68: =E68*F68 -> 0
... B77: =B27 -> 63 | C77: =C27 -> 4 | D77: =D27 -> m | E77: =E27 -> 0 | F77: =VLOOKUP(B77+C77,data!$A$31:$E$89,4,FALSE) -> 0.585 | G77: =E77*F77 -> 0
B78: 250 | C78: 10 | D78: m | E78: =E28 -> 1518 | F78: =VLOOKUP(B78+C78,data!$A$31:$E$89,4,FALSE) -> 19.757 | G78: =E78*F78 -> 29991.126
C79: Subtotal | E79: =SUM(E57:E78) -> 1518 | G79: =SUM(G57:G78) -> 29991.126
B80: GI pipes
B81: =B36 -> 15 | C81: =C36 -> GI (Heavy) | D81: =D36 -> m | E81: =E36 -> 0 | F81: =IF(C81="GI (Medium)",VLOOKUP(B81,data!$A$4:$D$14,3,FALSE),IF(C81="GI (Heavy)",VLOOKUP(B81,data!$A$17:$D$27,3,FALSE),0)) -> 1.513 | G81: =E81*F81 -> 0
B82: =B37 -> 25 | C82: =C37 -> GI (Heavy) | D82: =D37 -> m | E82: =E37 -> 0 | F82: =IF(C82="GI (Medium)",VLOOKUP(B82,data!$A$4:$D$14,3,FALSE),IF(C82="GI (Heavy)",VLOOKUP(B82,data!$A$17:$D$27,3,FALSE),0)) -> 3.077 | G82: =E82*F82 -> 0
B83: =B38 -> 32 | C83: =C38 -> GI (Heavy) | D83: =D38 -> m | E83: =E38 -> 0 | F83: =IF(C83="GI (Medium)",VLOOKUP(B83,data!$A$4:$D$14,3,FALSE),IF(C83="GI (Heavy)",VLOOKUP(B83,data!$A$17:$D$27,3,FALSE),0)) -> 3.968 | G83: =E83*F83 -> 0
B84: =B39 -> 40 | C84: =C39 -> GI (Heavy) | D84: =D39 -> m | E84: =E39 -> 0 | F84: =IF(C84="GI (Medium)",VLOOKUP(B84,data!$A$4:$D$14,3,FALSE),IF(C84="GI (Heavy)",VLOOKUP(B84,data!$A$17:$D$27,3,FALSE),0)) -> 4.587 | G84: =E84*F84 -> 0
B85: =B40 -> 50 | C85: =C40 -> GI (Heavy) | D85: =D40 -> m | E85: =E40 -> 0 | F85: =IF(C85="GI (Medium)",VLOOKUP(B85,data!$A$4:$D$14,3,FALSE),IF(C85="GI (Heavy)",VLOOKUP(B85,data!$A$17:$D$27,3,FALSE),0)) -> 6.369 | G85: =E85*F85 -> 0
B86: =B41 -> 80 | C86: =C41 -> GI (Heavy) | D86: =D41 -> m | E86: =E41 -> 0 | F86: =IF(C86="GI (Medium)",VLOOKUP(B86,data!$A$4:$D$14,3,FALSE),IF(C86="GI (Heavy)",VLOOKUP(B86,data!$A$17:$D$27,3,FALSE),0)) -> 10.417 | G86: =E86*F86 -> 0
B87: =B42 -> 100 | C87: =C42 -> GI (Heavy) | D87: =D42 -> m | E87: =E42 -> 2285 | F87: =IF(C87="GI (Medium)",VLOOKUP(B87,data!$A$4:$D$14,3,FALSE),IF(C87="GI (Heavy)",VLOOKUP(B87,data!$A$17:$D$27,3,FALSE),0)) -> 15.436 | G87: =E87*F87 -> 35271.26
B88: =B43 -> 125 | C88: =C43 -> GI (Heavy) | D88: =D43 -> m | E88: =E43 -> 0 | F88: =IF(C88="GI (Medium)",VLOOKUP(B88,data!$A$4:$D$14,3,FALSE),IF(C88="GI (Heavy)",VLOOKUP(B88,data!$A$17:$D$27,3,FALSE),0)) -> 18.52 | G88: =E88*F88 -> 0
B89: =B44 -> 150 | C89: =C44 -> GI (Heavy) | D89: =D44 -> m | E89: =E44 -> 1529 | F89: =IF(C89="GI (Medium)",VLOOKUP(B89,data!$A$4:$D$14,3,FALSE),IF(C89="GI (Heavy)",VLOOKUP(B89,data!$A$17:$D$27,3,FALSE),0)) -> 22.22 | G89: =E89*F89 -> 33974.38
B90: Subtotal | E90: =SUM(E81:E89) -> 3814 | G90: =SUM(G81:G89) -> 69245.64
B92: Weight of fittings and tools | G92: =(G79+G90)*0.15+FittingsSummary!AA126+tools!F39 -> 17103.675
B93: Total weight of pipe and fittings for transportation | G93: =G79+G90+G92 -> 116340.44

Sheet Qty Truss
A1: Details Quantity Estimate Truss
A2: S.N. | B2: Description of Works | C2: Nos. | D2: Length (ft) | E2: Breadth (ft) | F2: Height (ft) | G2: Quantity | H2: Unit | I2: Remark
A3: 1 | B3: Site Clearance Work:
C4: 1 | G4: =F4*E4*D4*C4 -> 0 | H4: Job
A6: 2 | B6: Earthwork in Excavation:
C7: 9 | D7: 2 | E7: 2 | F7: 2.5 | G7: =PRODUCT(C7:F7) -> 90
G8: =PRODUCT(C8:F8) -> 0
E9: Total (Cft) | G9: =SUM(G7:G8) -> 90 | H9: Cft
A10: 3 | B10: Earthwork in Backfilling:
C11: 1 | D11: @ 30% of Excavation: | G11: =0.3*G9 -> 27 | H11: Cft
A12: 4 | B12: Brick Soling Works
B13: At Foundation | C13: 9 | D13: 2 | E13: 2 | G13: =PRODUCT(C13:F13) -> 36
E14: Total (Sft) | G14: =SUM(G13:G13) -> 36 | H14: Sft
A15: 5 | B15: 3" PCC Work:
B16: At Foundation | C16: 9 | D16: 2 | E16: 2 | G16: =PRODUCT(C16:F16) -> 36
G17: =PRODUCT(C17:F17) -> 0
E18: Total (Sft) | G18: =SUM(G16:G17) -> 36 | H18: Sft
A19: 6 | B19: PCC for lintel ( 1:1.5:3)
B20: For Foundation of 4" Pipe | C20: 9 | D20: 1 | E20: 1 | F20: 0.5 | G20: =PRODUCT(C20:F20) -> 4.5
B21: Total | G21: =SUM(G20:G20) -> 4.5 | H21: Cft
A23: 7 | B23: Brick Work:
B24: Below DPC: 1st step | C24: 9 | D24: 4 | E24: CSA | F24: 1 | G24: =PRODUCT(C24:F24) -> 36
B25: 2nd and 3rd step | C25: 9 | D25: 2.5 | E25: CSA | F25: 1 | G25: =PRODUCT(C25:F25) -> 22.5
E26: Total (Cft): | G26: =SUM(G24:G25) -> 58.5 | H26: Cft
A27: 8 | B27: Black Iron Pipe Truss Work:
B28: 4'' Iron Post | C28: 9 | D28: =9.75+2 -> 11.75 | E28: 6.01 | F28: Kg/m | G28: =PRODUCT(C28:F28)/3.28 -> 193.76753
B29: 2" Base Tie | C29: 3 | D29: 11.5 | E29: 2.3 | F29: Kg/m | G29: =PRODUCT(C29:F29)/3.28 -> 24.192073
B30: 2" Rafter | C30: 6 | D30: 7 | E30: 2.3 | F30: Kg/m | G30: =PRODUCT(C30:F30)/3.28 -> 29.45122
B31: 1.5" Purlins: | C31: 6 | D31: 15 | E31: 1.72 | F31: Kg/m | G31: =PRODUCT(C31:F31)/3.28 -> 47.195122
B32: 1.5" Struts: | C32: 12 | D32: 40 | E32: 1.72 | F32: Kg/m | G32: =PRODUCT(C32:F32)/3.28 -> 251.70732
E33: Total (Kg): | G33: =SUM(G28:G32) -> 546.31326 | H33: Kg
A34: 9 | B34: Coloured CGI Roofing Work:
C35: 2 | D35: 18.4 | E35: 13.2 | G35: =PRODUCT(C35:F35) -> 485.76
E36: Total (Sft): | G36: =SUM(G35) -> 485.76 | H36: Sft
A38: 16 | B38: Ridge Work: | C38: 1 | D38: 18.4 | G38: =PRODUCT(C38:F38) -> 18.4
E39: Total (Rft): | G39: =SUM(G38) -> 18.4 | H39: Rft
A41: 10 | B41: Gutter Work: | C41: 2 | D41: 18.4 | G41: =PRODUCT(C41:F41) -> 36.8
E42: Total (Rft): | G42: =SUM(G41) -> 36.8 | H42: Rft

Sheet pip-line
A1: Abstract of costs | J1: ='[63]Design-2'!$D$10 -> 1.4811111
A2: Pipeline Works | L2: 250
L3: (per kg)
A5: Sn | B5: Description | C5: Length | D5: Breadth | E5: Height | F5: Quantity | G5: Unit | H5: Rate | I5: Amount
A7: A | B7: Transmission line
A8: 1 | B8: E/W in excavation in hard soil | C8: =SUM(M9:M38)*1.1 -> 284.493 | D8: 0.45 | E8: 0.9 | F8: =ROUND(C8*D8*E8,2) -> 115.22 | G8: m3 | H8: =+Rates!$F$9 -> 1480.63 | I8: =+ROUND(F8*H8,2) -> 170598.19 | M8: Tr | N8: Dr | O8: Tr | P8: Dr | Q8: Total | R8: DL
A9: 2 | B9: E/W in backfilling with hard soil | C9: =C8 -> 284.493 | D9: 0.45 | E9: 0.9 | F9: =ROUND(C9*D9*E9,2) -> 115.22 | G9: m3 | H9: =+Rates!$F$15 -> 746.24 | I9: =+ROUND(F9*H9,2) -> 85981.77 | L9: =Pipe!J8 -> GPM-15 | M9: =Pipe!K8 -> 0 | N9: =Pipe!L8 -> 0 | O9: =M9*1.1 -> 0 | P9: =N9*1.1 -> 0 | Q9: =M9+N9 -> 0 | R9: =Q9*1.1 -> 0
L10: =Pipe!J9 -> GPM-20 | M10: =Pipe!K9 -> 0 | N10: =Pipe!L9 -> 0 | O10: =M10*1.1 -> 0 | P10: =N10*1.1 -> 0 | Q10: =M10+N10 -> 0 | R10: =Q10*1.1 -> 0
A11: 3 | B11: Laying & Jointing of Pipes | L11: =Pipe!J10 -> GPM-25 | M11: =Pipe!K10 -> 0 | N11: =Pipe!L10 -> 0 | O11: =M11*1.1 -> 0 | P11: =N11*1.1 -> 0 | Q11: =M11+N11 -> 0 | R11: =Q11*1.1 -> 0
B12: 32 mmØ HDPE pipe | C12: =O20+O29+O30+Q262921+O31 -> 0 | F12: =+C12 -> 0 | G12: m | H12: =Rates!F76 -> 6.55 | I12: =+ROUND(F12*H12,2) -> 0 | L12: =Pipe!J11 -> GPM-32 | M12: =Pipe!K11 -> 0 | N12: =Pipe!L11 -> 0 | O12: =M12*1.1 -> 0 | P12: =N12*1.1 -> 0 | Q12: =M12+N12 -> 0 | R12: =Q12*1.1 -> 0
B13: 40,50 mmØ HDPE pipe | C13: =O21+O22+O32+O33 -> 0 | F13: =+C13 -> 0 | G13: m | H13: =Rates!F77 -> 7.95 | I13: =+ROUND(F13*H13,2) -> 0 | L13: =Pipe!J12 -> GPM-40 | M13: =Pipe!K12 -> 0 | N13: =Pipe!L12 -> 0 | O13: =M13*1.1 -> 0 | P13: =N13*1.1 -> 0 | Q13: =M13+N13 -> 0 | R13: =Q13*1.1 -> 0
B14: 63-90 mmØ HDPE | C14: =O23+O24+O25+O34+O35+O36 -> 0 | F14: =+C14 -> 0 | G14: m | H14: =Rates!F78 -> 105.27 | I14: =+ROUND(F14*H14,2) -> 0 | L14: =Pipe!J13 -> GPM-50 | M14: =Pipe!K13 -> 0 | N14: =Pipe!L13 -> 0 | O14: =M14*1.1 -> 0 | P14: =N14*1.1 -> 0 | Q14: =M14+N14 -> 0 | R14: =Q14*1.1 -> 0
B15: 25,32 mmØ GI pipe | C15: =SUM(O9:O12) -> 0 | F15: =+C15 -> 0 | G15: m | H15: =Rates!F84 -> 158.05 | I15: =+ROUND(F15*H15,2) -> 0 | L15: =Pipe!J14 -> GPM-65 | M15: =Pipe!K14 -> 0 | N15: =Pipe!L14 -> 0 | O15: =M15*1.1 -> 0 | P15: =N15*1.1 -> 0 | Q15: =M15+N15 -> 0 | R15: =Q15*1.1 -> 0
B16: 40,50 mmØ GI pipe | C16: =SUM(O13:O14) -> 0 | F16: =+C16 -> 0 | G16: m | H16: =Rates!F85 -> 215.52 | I16: =+ROUND(F16*H16,2) -> 0 | L16: =Pipe!J15 -> GPM-80 | M16: =Pipe!K15 -> 0 | N16: =Pipe!L15 -> 0 | O16: =M16*1.1 -> 0 | P16: =N16*1.1 -> 0 | Q16: =M16+N16 -> 0 | R16: =Q16*1.1 -> 0
B17: 65,80 mmØ GI pipe | C17: =SUM(O15:O16) -> 0 | F17: =+C17 -> 0 | G17: m | H17: =Rates!F86 -> 287.32 | I17: =+ROUND(F17*H17,2) -> 0 | L17: =Pipe!J16 -> GPM-100 | M17: =Pipe!K16 -> 100 | N17: =Pipe!L16 -> 1976.48 | O17: =M17*1.1 -> 110 | P17: =N17*1.1 -> 2174.128 | Q17: =M17+N17 -> 2076.48 | R17: =Q17*1.1 -> 2284.128
B18: 100 mmØ GI pipe | C18: =ROUNDUP(O17,0) -> 110 | F18: =+C18 -> 110 | G18: m | H18: =Rates!F87 -> 359.12 | I18: =+ROUND(F18*H18,2) -> 39503.2 | L18: =Pipe!J17 -> GPM-125 | M18: =Pipe!K17 -> 0 | N18: =Pipe!L17 -> 0 | O18: =M18*1.1 -> 0 | P18: =N18*1.1 -> 0 | Q18: =M18+N18 -> 0 | R18: =Q18*1.1 -> 0
B19: 125 mmØ GI pipe | C19: =ROUNDUP(O18,0) -> 0 | F19: =+C19 -> 0 | G19: m | H19: =Rates!F88 -> 438.15 | I19: =+ROUND(F19*H19,2) -> 0 | L19: =Pipe!J18 -> GPM-150 | M19: =Pipe!K18 -> 158.63 | N19: =Pipe!L18 -> 1231 | O19: =M19*1.1 -> 174.493 | P19: =N19*1.1 -> 1354.1 | Q19: =M19+N19 -> 1389.63 | R19: =Q19*1.1 -> 1528.593
B20: 150 mmØ GI pipe | C20: =ROUNDUP(O19,0) -> 175 | F20: =+C20 -> 175 | G20: m | H20: =Rates!F89 -> 502.84 | I20: =+ROUND(F20*H20,2) -> 87997 | L20: HP6-32 | M20: =Pipe!K19 -> 0 | N20: =Pipe!L19 -> 0 | O20: =M20*1.1 -> 0 | P20: =N20*1.1 -> 0 | Q20: =M20+N20 -> 0 | R20: =Q20*1.1 -> 0
L21: HP6-40 | M21: =Pipe!K20 -> 0 | N21: =Pipe!L20 -> 0 | O21: =M21*1.1 -> 0 | P21: =N21*1.1 -> 0 | Q21: =M21+N21 -> 0 | R21: =Q21*1.1 -> 0
B22: Sub-total | C22: =SUM(C12:C20) -> 285 | F22: =SUM(F12:F20) -> 285 | I22: =SUM(I8:I20) -> 384080.16 | L22: HP6-50 | M22: =Pipe!K21 -> 0 | N22: =Pipe!L21 -> 0 | O22: =M22*1.1 -> 0 | P22: =N22*1.1 -> 0 | Q22: =M22+N22 -> 0 | R22: =Q22*1.1 -> 0
B23: ='Entry for Rates'!$F$114 -> 13 | I23: =I22*B23/100 -> 49930.421 | L23: HP6-63 | M23: =Pipe!K22 -> 0 | N23: =Pipe!L22 -> 0 | O23: =M23*1.1 -> 0 | P23: =N23*1.1 -> 0 | Q23: =M23+N23 -> 0 | R23: =Q23*1.1 -> 0
B24: Total cost of transmission pipe line works | H24: Rs. | I24: =I23+I22 -> 434010.58 | L24: HP6-75 | M24: =Pipe!K23 -> 0 | N24: =Pipe!L23 -> 0 | O24: =M24*1.1 -> 0 | P24: =N24*1.1 -> 0 | Q24: =M24+N24 -> 0 | R24: =Q24*1.1 -> 0
A25: B | B25: Distribution line | L25: HP6-90 | M25: =Pipe!K24 -> 0 | N25: =Pipe!L24 -> 0 | O25: =M25*1.1 -> 0 | P25: =N25*1.1 -> 0 | Q25: =M25+N25 -> 0 | R25: =Q25*1.1 -> 0
L26: HP6-110 | M26: =Pipe!K25 -> 0 | N26: =Pipe!L25 -> 0 | O26: =M26*1.1 -> 0 | P26: =N26*1.1 -> 0 | Q26: =M26+N26 -> 0 | R26: =Q26*1.1 -> 0
A27: 1 | B27: E/W in excavation in hard soil | C27: =SUM(N9:N38)*1.1 -> 3528.228 | D27: 0.45 | E27: 0.9 | F27: =ROUND(C27*D27*E27,2) -> 1428.93 | G27: m³ | H27: =+Rates!F9 -> 1480.63 | I27: =+ROUND(F27*H27,2) -> 2115716.6 | L27: HP6-125 | M27: =Pipe!K26 -> 0 | N27: =Pipe!L26 -> 0 | O27: =M27*1.1 -> 0 | P27: =N27*1.1 -> 0 | Q27: =M27+N27 -> 0 | R27: =Q27*1.1 -> 0
A28: 2 | B28: E/W in backfilling with hard soil | C28: =C27 -> 3528.228 | D28: 0.45 | E28: 0.9 | F28: =ROUND(C28*D28*E28,2) -> 1428.93 | G28: m³ | H28: =+Rates!F15 -> 746.24 | I28: =+ROUND(F28*H28,2) -> 1066324.7 | L28: HP10-16 | M28: =Pipe!K27 -> 0 | N28: =Pipe!L27 -> 0 | O28: =M28*1.1 -> 0 | P28: =N28*1.1 -> 0 | Q28: =M28+N28 -> 0 | R28: =Q28*1.1 -> 0
A29: 3 | B29: Laying & Jointing of Pipes | L29: HP10-20 | M29: =Pipe!K28 -> 0 | N29: =Pipe!L28 -> 0 | O29: =M29*1.1 -> 0 | P29: =N29*1.1 -> 0 | Q29: =M29+N29 -> 0 | R29: =Q29*1.1 -> 0
B30: 16 mmØ HDPE pipe | C30: =P28 -> 0 | F30: =+C30 -> 0 | G30: m | H30: =Rates!F74 -> 0 | I30: =+ROUND(F30*H30,2) -> 0 | L30: HP10-25 | M30: =Pipe!K29 -> 0 | N30: =Pipe!L29 -> 0 | O30: =M30*1.1 -> 0 | P30: =N30*1.1 -> 0 | Q30: =M30+N30 -> 0 | R30: =Q30*1.1 -> 0
B31: 20,25 mmØ HDPE pipe | C31: =SUM(P29:P30) -> 0 | F31: =+C31 -> 0 | G31: m | H31: =Rates!F75 -> 5.3 | I31: =+ROUND(F31*H31,2) -> 0 | L31: HP10-32 | M31: =Pipe!K30 -> 0 | N31: =Pipe!L30 -> 0 | O31: =M31*1.1 -> 0 | P31: =N31*1.1 -> 0 | Q31: =M31+N31 -> 0 | R31: =Q31*1.1 -> 0
B32: 32 mmØ HDPE pipe | C32: =SUM(P31+P20) -> 0 | F32: =+C32 -> 0 | G32: m | H32: =Rates!F76 -> 6.55 | I32: =+ROUND(F32*H32,2) -> 0 | L32: HP10-40 | M32: =Pipe!K31 -> 0 | N32: =Pipe!L31 -> 0 | O32: =M32*1.1 -> 0 | P32: =N32*1.1 -> 0 | Q32: =M32+N32 -> 0 | R32: =Q32*1.1 -> 0
B33: 40, 50 mmØ HDPE pipe | C33: =SUM(P21:P22,P32:P33) -> 0 | F33: =+C33 -> 0 | G33: m | H33: =Rates!F77 -> 7.95 | I33: =+ROUND(F33*H33,2) -> 0 | L33: HP10-50 | M33: =Pipe!K32 -> 0 | N33: =Pipe!L32 -> 0 | O33: =M33*1.1 -> 0 | P33: =N33*1.1 -> 0 | Q33: =M33+N33 -> 0 | R33: =Q33*1.1 -> 0
B34: 63-90 mmØ HDPE | C34: =SUM(P23:P25,P34:P36) -> 0 | F34: =+C34 -> 0 | G34: m | H34: =Rates!F78 -> 105.27 | I34: =+ROUND(F34*H34,2) -> 0 | L34: HP10-63 | M34: =Pipe!K33 -> 0 | N34: =Pipe!L33 -> 0 | O34: =M34*1.1 -> 0 | P34: =N34*1.1 -> 0 | Q34: =M34+N34 -> 0 | R34: =Q34*1.1 -> 0
B35: 110,125 mmØ HDPE pipe | C35: =SUM(P26,P37:P38) -> 0 | F35: =+C35 -> 0 | G35: m | H35: =Rates!F79 -> 155.06 | I35: =+ROUND(F35*H35,2) -> 0 | L35: HP10-75 | M35: =Pipe!K34 -> 0 | N35: =Pipe!L34 -> 0 | O35: =M35*1.1 -> 0 | P35: =N35*1.1 -> 0 | Q35: =M35+N35 -> 0 | R35: =Q35*1.1 -> 0
B36: 250 mmØ HDPE pipe | C36: =P43 -> 1518 | F36: =+C36 -> 1518 | G36: m | H36: =Rates!F81 -> 273.18 | I36: =+ROUND(F36*H36,2) -> 414687.24 | L36: HP10-90 | M36: =Pipe!K35 -> 0 | N36: =Pipe!L35 -> 0 | O36: =M36*1.1 -> 0 | P36: =N36*1.1 -> 0 | Q36: =M36+N36 -> 0 | R36: =Q36*1.1 -> 0
B37: 15,20 mmØ GI pipe | C37: =P9+P10 -> 0 | F37: =+C37 -> 0 | G37: m | H37: =Rates!F83 -> 114.93 | I37: =+ROUND(F37*H37,2) -> 0 | L37: HP10-110 | M37: =Pipe!K36 -> 0 | N37: =Pipe!L36 -> 0 | O37: =M37*1.1 -> 0 | P37: =N37*1.1 -> 0 | Q37: =M37+N37 -> 0 | R37: =Q37*1.1 -> 0
B38: 25,32 mmØ GI pipe | C38: =P11+P12 -> 0 | F38: =+C38 -> 0 | G38: m | H38: =Rates!F84 -> 158.05 | I38: =+ROUND(F38*H38,2) -> 0 | L38: HP10-125 | M38: =Pipe!K37 -> 0 | N38: =Pipe!L37 -> 0 | O38: =M38*1.1 -> 0 | P38: =N38*1.1 -> 0 | Q38: =M38+N38 -> 0 | R38: =Q38*1.1 -> 0
B39: 40,50 mmØ GI pipe | C39: =ROUNDUP(P13+P14,0) -> 0 | F39: =+C39 -> 0 | G39: m | H39: =Rates!F85 -> 215.52 | I39: =+ROUND(F39*H39,2) -> 0
B40: 65,80 mmØ GI pipe | C40: =ROUNDUP(P16+P15,0) -> 0 | F40: =+C40 -> 0 | G40: m | H40: =Rates!F86 -> 287.32 | I40: =+ROUND(F40*H40,2) -> 0 | L40: =Pipe!J40 -> HP10-180 | M40: =Pipe!K40 -> 0 | N40: =Pipe!L40 -> 0 | O40: =M40*1.1 -> 0 | P40: =N40*1.1 -> 0 | Q40: =M40+N40 -> 0 | R40: =Q40*1.1 -> 0
B41: 100 mmØ GI pipe | C41: =ROUNDUP(P17,0) -> 2175 | F41: =+C41 -> 2175 | G41: m | H41: =Rates!F87 -> 359.12 | I41: =+ROUND(F41*H41,2) -> 781086 | L41: =Pipe!J41 -> HP10-200 | M41: =Pipe!K47 -> 0 | N41: =Pipe!L47 -> 0 | O41: =M41*1.1 -> 0 | P41: =N41*1.1 -> 0 | Q41: =M41+N41 -> 0 | R41: =Q41*1.1 -> 0
B42: 125 mmØ GI pipe | C42: =ROUNDUP(P18,0) -> 0 | F42: =+C42 -> 0 | G42: m | H42: =Rates!F88 -> 438.15 | I42: =+ROUND(F42*H42,2) -> 0 | L42: =Pipe!J42 -> HP10-225 | M42: =Pipe!K48 -> 0 | N42: =Pipe!L48 -> 0 | O42: =M42*1.1 -> 0 | P42: =N42*1.1 -> 0 | Q42: =M42+N42 -> 0 | R42: =Q42*1.1 -> 0
B43: 150 mmØ GI pipe | C43: =ROUNDUP(P19,0) -> 1355 | F43: =+C43 -> 1355 | G43: m | H43: =Rates!F89 -> 502.84 | I43: =+ROUND(F43*H43,2) -> 681348.2 | L43: =Pipe!J43 -> HP10-250 | M43: =Pipe!K49 -> 0 | N43: =Pipe!L43 -> 1380 | O43: =M43*1.1 -> 0 | P43: =N43*1.1 -> 1518 | Q43: =M43+N43 -> 1380 | R43: =Q43*1.1 -> 1518
M44: =SUM(M9:M38) -> 258.63 | N44: =SUM(N9:N38) -> 3207.48 | O44: =SUM(O9:O38) -> 284.493 | P44: =SUM(P9:P38) -> 3528.228 | Q44: =SUM(Q9:Q43) -> 4846.11 | R44: =SUM(R9:R43) -> 5330.721
B45: Sub-total | C45: =SUM(C30:C43) -> 5048 | F45: =SUM(F30:F43) -> 5048 | H45: Rs. | I45: =SUM(I27:I44) -> 5059162.8
B46: ='Entry for Rates'!$F$114 -> 13 | I46: =I45*B46/100 -> 657691.16
B47: Total cost of distribution pipeline works | H47: Rs. | I47: =I46+I45 -> 5716854
A48: Transportation Cost of Pipes and fittings | B48: Total cost of pipeline works | H48: Rs. | I48: =+I47+I24 -> 6150864.5
A49: S.No.
A50: 1
B51: Description of items | F51: Quantity | G51: Unit | H51: Rate | I51: Amount
B52: Transportation Cost of Pipes and fittings from store to site
B53: Total | F53: =+Pipe!G93 -> 116340.44 | G53: kg | H53: =(10*'Rate-1'!I36+1*'Rate-1'!I28*100)/100 -> 0 | I53: =F53*H53 -> 0
B54: Sub Total | F54: =SUM(F53:F53) -> 116340.44 | G54: kg | I54: =SUM(I53:I53) -> 0
B55: ='Entry for Rates'!$F$114 -> 13 | I55: =I54*B55/100 -> 0
B56: Total transportation cost | H56: Rs | I56: =SUM(I54:I55) -> 0

Sheet bar+gate
A1: Barbed Wire Fencing & Gate
A2: ='Entry for Rates'!F4 -> 0
A3: Barbed Wire Fencing ( Type - A)
C4: Total length of fencing = | D4: 24 | E4: m
A5: S.N. | B5: Description | C5: No. | D5: Length | E5: Breadth | F5: Height | G5: Quantity | H5: Unit | I5: Rate | J5: Amount
A6: 1 | B6: Earthwork in excavation
C7: =D$4/1.5+1 -> 17 | D7: 0.35 | E7: 0.35 | F7: 0.6 | G7: =ROUND(C7*D7*E7*F7,2) -> 1.25 | H7: m³ | I7: =+Rates!F9 -> 1480.63 | J7: =+ROUND(G7*I7,2) -> 1850.79
A8: 2 | B8: PCC (1:2:4) for anchor blocks | C8: =D$4/1.5+1 -> 17 | D8: 0.35 | E8: 0.35 | F8: 0.6 | G8: =ROUND(C8*D8*E8*F8,2) -> 1.25 | H8: m³ | I8: =+Rates!F32 -> 16022.87 | J8: =+ROUND(G8*I8,2) -> 20028.59
A9: 3 | B9: MS angle post(40*40*6mm size and 2.1m long) | C9: =D$4/1.5+1 -> 17 | D9: 2.1 | E9: 3.5 | G9: =+ROUND(C9*D9*E9,2) -> 124.95 | H9: kg | I9: =+ROUND(MR!I16*1.15,2) -> 106.95 | J9: =+ROUND(G9*I9,2) -> 13363.4
A10: 4 | B10: Barbed wire fencing
B11: - horizontal ( 7 layers) | C11: 7 | D11: =D4 -> 24 | G11: =+ROUND(C11*D11,2) -> 168
B12: - Diagonals | C12: =2*D4/1.5 -> 32 | D12: =(1.5^2+1.03^2)^0.5 -> 1.8195879 | G12: =+ROUND(C12*D12,2) -> 58.23
B13: Total | G13: =SUM(G10:G12) -> 226.23 | H13: m | I13: =+Rates!F44 -> 99.291 | J13: =+ROUND(G13*I13,2) -> 22462.6
A15: 5 | B15: Enamel painting on MS angle | C15: =D$4/1.5+1 -> 17 | D15: 1.5 | E15: 0.16 | G15: =+ROUND(C15*D15*E15,2) -> 4.08 | H15: m² | I15: =+Rates!F70 -> 400.29 | J15: =+ROUND(G15*I15,2) -> 1633.18
B17: Total Amount ( Without VAT ) | I17: Rs. | J17: =SUM(J7:J16) -> 59338.56
B18: Rate per metre ( Without VAT ) | I18: Rs. | J18: =ROUND(J17/D4,2) -> 2472.44
A22: Entrance Gate
A23: For barbed wire fencing Type-A
A24: S.N. | B24: Description | C24: No. | D24: Length | E24: Breadth | F24: Height | G24: Quantity | H24: Unit | I24: Rates | J24: Amount
A26: 1 | B26: Earthwork in excavation in foundation
C27: 2 | D27: 0.45 | E27: 0.45 | F27: 0.6 | G27: =C27*D27*E27*F27 -> 0.243 | H27: m³ | I27: =+Rates!F9 -> 1480.63 | J27: =+ROUND(G27*I27,2) -> 359.79
A28: 2 | B28: Stone soling | C28: 2 | D28: 0.45 | E28: 0.45 | F28: 0.15 | G28: =C28*D28*E28*F28 -> 0.06075 | H28: m³ | I28: =+Rates!F19 -> 5523.35 | J28: =+ROUND(G28*I28,2) -> 335.54
A29: 3 | B29: Stone masonry in 1:6 c-s mortar | C29: for support pillars
B30: In foundation | C30: 2 | D30: 0.45 | E30: 0.45 | F30: 0.45 | G30: =C30*D30*E30*F30 -> 0.18225
B31: Above Ground | C31: 2 | D31: 0.45 | E31: 0.45 | F31: 1.6 | G31: =C31*D31*E31*F31 -> 0.648
B32: Deduct for holdfast PCC blocks | C32: 3 | D32: 0.45 | E32: 0.45 | F32: 0.2 | G32: =-ROUND(C32*D32*E32*F32,2) -> -0.12
B33: Total | G33: =SUM(G30:G32) -> 0.71025 | H33: m³ | I33: =+Rates!F25 -> 14917.39 | J33: =+ROUND(G33*I33,2) -> 10595.08
A34: 4 | B34: PCC (1:2:4) for holdfast blocks | C34: 3 | D34: 0.45 | E34: 0.45 | F34: 0.2 | G34: =C34*D34*E34*F34 -> 0.1215
B35: on top of pillar | C35: 2 | D35: 0.45 | E35: 0.45 | F35: 0.1 | G35: =C35*D35*E35*F35 -> 0.0405
B36: Total | G36: =SUM(G34:G35) -> 0.162 | H36: m³ | I36: =+Rates!F32 -> 16022.87 | J36: =+ROUND(G36*I36,2) -> 2595.7
A37: 5 | B37: 12.5mm 1:4 c - s plaster -Pillars | C37: 8 | D37: 0.45 | E37: - | F37: 1.6 | G37: =C37*D37*F37 -> 5.76
B38: -On top | C38: 2 | D38: 0.45 | E38: 0.45 | F38: - | G38: =C38*D38*E38 -> 0.405
B39: Total | G39: =SUM(G37:G38) -> 6.165 | H39: m² | I39: =+Rates!F60 -> 503.61 | J39: =+ROUND(G39*I39,2) -> 3104.76
A40: 6 | B40: Mild Steel angle ( 25 x 25 x 3 mm Size ) framed gate with Iron Grill shutter (0.95 x 1.5 m size) all complete including fixing | G40: 1 | H40: no | I40: =+ROUND(MR!$I$40*1.15,2) -> 1725 | J40: =+ROUND(G40*I40,2) -> 1725
A41: 7 | B41: Enamel Painting | C41: 1 | D41: 0.95 | E41: - | F41: 1.5 | G41: =C41*D41*F41 -> 1.425 | H41: m² | I41: =+Rates!F70 -> 400.29 | J41: =+ROUND(G41*I41,2) -> 570.41
B42: Total Amount ( Without VAT ) | I42: Rs. | J42: =SUM(J25:J41) -> 19286.28
A45: Barbed Wire Fencing ( Type - B )
A46: ='Entry for Rates'!F4 -> 0
C47: Total length of fencing = | D47: 24 | E47: m
A48: S.N. | B48: Description | C48: No. | D48: Length | E48: Breadth | F48: Height | G48: Quantity | H48: Unit | I48: Rates | J48: Amount
A50: 1 | B50: Earthwork in excavation in HS
C51: =D47/2 -> 12 | D51: 0.3 | E51: 0.3 | F51: 0.6 | G51: =C51*D51*E51*F51 -> 0.648 | H51: m³ | I51: =+Rates!F9 -> 1480.63 | J51: =+ROUND(G51*I51,2) -> 959.45
A53: 2 | B53: Dry stone soling | C53: =D47/2 -> 12 | D53: 0.3 | E53: 0.3 | F53: 0.1 | G53: =C53*D53*E53*F53 -> 0.108 | H53: m³ | I53: =+Rates!F19 -> 5523.35 | J53: =+ROUND(G53*I53,2) -> 596.52
A56: 2 | B56: PCC (1:3:6) | C56: =D47/2 -> 12 | D56: 0.2 | E56: 0.2 | F56: 0.5 | G56: =C56*D56*E56*F56 -> 0.24
B57: - deduction for RCC post | C57: =D47/2 -> 12 | D57: 0.1 | E57: 0.1 | F57: 0.5 | G57: =-C57*D57*E57*F57 -> -0.06
B58: Net PCC | G58: =SUM(G56:G57) -> 0.18 | H58: m³ | I58: =+Rates!F31 -> 14810.58 | J58: =+ROUND(G58*I58,2) -> 2665.9
A59: 3 | B59: Barbed wire fencing on pre-cast RCC post
B60: - Barbed wire fencing - 5 horizontals | C60: 5 | D60: =D47 -> 24 | G60: =C60*D60 -> 120
B61: - diagonals | C61: =D47/2*2 -> 24 | D61: 2.4 | G61: =C61*D61 -> 57.6
B62: Total | G62: =SUM(G60:G61) -> 177.6 | H62: m | I62: =+Rates!F44 -> 99.291 | J62: =+ROUND(G62*I62,2) -> 17634.08
A64: 4 | B64: PCC (1:2:4) for RCC posts | C64: =D47/2 -> 12 | D64: 2.1 | E64: 0.1 | F64: 0.1 | G64: =C64*D64*E64*F64 -> 0.252 | H64: m³ | I64: =+Rates!F32 -> 16022.87 | J64: =+ROUND(G64*I64,2) -> 4037.76
A65: 5 | B65: - Mild steel reinforcement
B66: 10 mm ø bar, 4 nos 2.2 m long | C66: =D47/2*4 -> 48 | D66: 2.2 | E66: 0.616 | F66: kg/m | G66: =C66*D66*E66 -> 65.0496
B67: - Stirrup - 6 mm ø bar, 240 mm long | C67: =D47/2*11 -> 132 | D67: 0.24 | E67: 0.22 | F67: kg/m | G67: =C67*D67*E67 -> 6.9696
B68: - Anchor hooks - 6 mm ø bar bent into shape to held barbed wire
C69: =5*D47/2 -> 60 | D69: 0.2 | E69: 0.22 | F69: kg/m | G69: =C69*D69*E69 -> 2.64
G70: =SUM(G66:G69) -> 74.6592 | H70: kg | I70: =+Rates!F39 -> 125.35 | J70: =+ROUND(G70*I70,2) -> 9358.53
A72: 6 | B72: Centering and shuttering | C72: =D47/2 -> 12 | D72: 0.3 | F72: 2.3 | G72: =C72*D72*F72 -> 8.28 | H72: m² | I72: =+Rates!F40 -> 1322.68 | J72: =+ROUND(G72*I72,2) -> 10951.79
B74: Total Amount ( Without VAT ) | I74: Rs. | J74: =+SUM(J51:J72) -> 46204.03
B75: Rate per metre ( Without VAT ) | I75: Rs. | J75: =ROUND(J74/D47,2) -> 1925.17
A78: Entrance Gate
A79: For barbed wire fencing Type-B
A80: S.N. | B80: Description | C80: No. | D80: Length | E80: Breadth | F80: Height | G80: Quantity | H80: Unit | I80: Rates | J80: Amount
A82: 1 | B82: Earth work in excavation in hard soil
C83: 2 | D83: 0.1 | E83: 0.1 | F83: 0.6 | G83: =C83*D83*E83*F83 -> 0.012 | H83: m³ | I83: =+Rates!F9 -> 1480.63 | J83: =+ROUND(G83*I83,2) -> 17.77
A85: 2 | B85: Boulder soling | C85: 2 | D85: 0.1 | E85: 0.1 | F85: 0.1 | G85: =C85*D85*E85*F85 -> 0.002 | H85: m³ | I85: =+Rates!F19 -> 5523.35 | J85: =+ROUND(G85*I85,2) -> 11.05
A86: 3 | B86: Wooden work for post & style
B87: Wooden post, 100 x 100mm | C87: 2 | D87: 1.9 | E87: 0.1 | F87: 0.1 | G87: =C87*D87*E87*F87 -> 0.038
B89: Door Style, 75 x 20mm | C89: 2 | D89: 1.3 | E89: 0.075 | F89: 0.02 | G89: =C89*D89*E89*F89 -> 0.0039
B90: Top, Bottom, 75 x 20mm | C90: 2 | D90: 1 | E90: 0.075 | F90: 0.02 | G90: =C90*D90*E90*F90 -> 0.003
B91: Diagonal Bracing 75 x 20mm | C91: 1 | D91: 1.64 | E91: 0.075 | F91: 0.02 | G91: =C91*D91*E91*F91 -> 0.00246
B92: Total | G92: =SUM(G87:G91) -> 0.04736 | H92: m³ | I92: =+Rates!F46 -> 330697.9 | J92: =+ROUND(G92*I92,2) -> 15661.85
A94: 4 | B94: Barbed wire 1 m long each | C94: 4 | G94: =C94 -> 4 | H94: m | I94: =+Rates!F44 -> 99.291 | J94: =+ROUND(G94*I94,2) -> 397.16
A96: 5 | B96: U - hooks | C96: 10 | G96: =C96 -> 10 | H96: no. | I96: =+ROUND(MR!I37*1.15,2) -> 16.79 | J96: =+ROUND(G96*I96,2) -> 167.9
A97: 6 | B97: Locking set | G97: 1 | H97: no | I97: =+ROUND(MR!I33*1.15,2) -> 318.55 | J97: =+ROUND(G97*I97,2) -> 318.55
B98: Total Amount ( Without VAT ) | I98: Rs. | J98: =SUM(J81:J97) -> 16574.28

Sheet CC-DC
A1: Collection Chamber
A2: ='Entry for Rates'!F4 -> 0
B3: Inner size of chamber = | C3: 2 | D3: x | E3: 1 | G3: Total height = | H3: 2.5
A5: S.N. | B5: Description | C5: No. | D5: Length | E5: Breadth | F5: Height | G5: Quantity | H5: Unit | I5: Rate | J5: Amount
A7: 1 | B7: Site clearance | D7: 3 | E7: 2 | G7: =D7*E7 -> 6 | H7: m² | I7: =Rates!$F$7 -> 149.5 | J7: =ROUND(G7*I7,2) -> 897
A8: 2 | B8: Earthwork in excavation for fondation work in hard soil
C9: 1 | D9: =C3+0.45*2 -> 2.9 | E9: =E3+0.45*2 -> 1.9 | F9: =H3 -> 2.5 | G9: =C9*D9*E9*F9 -> 13.775 | H9: m³ | I9: =Rates!$F$9 -> 1480.63 | J9: =ROUND(G9*I9,2) -> 20395.68
A11: 3 | B11: Dry stone soling | C11: 1 | D11: =C3+0.45*2 -> 2.9 | E11: =E3+0.45*2 -> 1.9 | F11: 0.15 | G11: =C11*D11*E11*F11 -> 0.8265 | H11: m³ | I11: =Rates!$F$19 -> 5523.35 | J11: =ROUND(G11*I11,2) -> 4565.05
A12: 4 | B12: Plain Cement Concrete (1:2:4)
B13: in foundation | C13: 1 | D13: =C3+0.45*2 -> 2.9 | E13: =E3+0.45*2 -> 1.9 | F13: 0.1 | G13: =C13*D13*E13*F13 -> 0.551
B14: Pipe embeddment block | C14: 5 | D14: 0.45 | E14: 0.2 | F14: 0.2 | G14: =C14*D14*E14*F14 -> 0.09
B15: top of baffle wall | C15: 1 | D15: =E3 -> 1 | E15: =E22 -> 0.35 | F15: 0.1 | G15: =C15*D15*E15*F15 -> 0.035
B16: Cover slab | C16: 1 | D16: =C3+0.45*2 -> 2.9 | E16: =E3+0.45*2 -> 1.9 | F16: 0.1 | G16: =C16*D16*E16*F16 -> 0.551
B17: Deduct:
B18: -Manhole cover | C18: 2 | D18: 0.6 | E18: 0.6 | F18: 0.05 | G18: =-C18*D18*E18*F18 -> -0.036
B19: Total | G19: =SUM(G12:G18) -> 1.191 | H19: m³ | I19: =Rates!$F$32 -> 16022.87 | J19: =ROUND(G19*I19,2) -> 19083.24
A20: 5 | B20: Stone masonry work in 1:4 c-s mortar
B21: CC portion | C21: 1 | D21: =(C3+0.9+E3)*2 -> 7.8 | E21: 0.45 | F21: =H3 -> 2.5 | G21: =C21*D21*E21*F21 -> 8.775
B22: baffle wall | C22: 1 | D22: =+E3 -> 1 | E22: 0.35 | F22: 0.6 | G22: =C22*D22*E22*F22 -> 0.21
B23: Deduct - for PCC blocks | C23: =C14 -> 5 | D23: =D14 -> 0.45 | E23: =E14 -> 0.2 | F23: =F14 -> 0.2 | G23: =-C23*D23*E23*F23 -> -0.09
B24: Total | G24: =SUM(G20:G23) -> 8.895 | H24: m³ | I24: =Rates!$F$24 -> 15619.64 | J24: =ROUND(G24*I24,2) -> 138936.7
A25: 6 | B25: Centering & shuttering work for PCC/RCC
B26: Bottom of cover slab - CC portion | C26: 1 | D26: =C3-E22 -> 1.65 | E26: =E3 -> 1 | G26: =D26*E26 -> 1.65
B27: -Outer edge of cover slab | C27: 1 | D27: =2*(D9+E9) -> 9.6 | E27: - | F27: =+F16 -> 0.1 | G27: =ROUND(+C27*D27*F27,2) -> 0.96
B28: Total form work | G28: =SUM(G26:G27) -> 2.61 | H28: m² | I28: =Rates!$F$40 -> 1322.68 | J28: =ROUND(G28*I28,2) -> 3452.19
A30: 7 | B30: Steel reinforcement
B31: 8 mm ø @ 150 mm c/c bothways | C31: =ROUND((D9-0.6*2)/0.15+1,0) -> 12 | D31: =E9 -> 1.9 | E31: 0.395 | G31: =C31*D31*E31 -> 9.006
C32: =ROUND(E9/0.15+1,0) -> 14 | D32: =D9-0.6*2 -> 1.7 | E32: 0.395 | G32: =C32*D32*E32 -> 9.401
B33: Total reinforcement | G33: =SUM(G31:G32) -> 18.407 | H33: kg | I33: =Rates!$F$39 -> 125.35 | J33: =ROUND(G33*I33,2) -> 2307.32
A35: 8 | B35: 12.5 mm thick 1:4 c-s plaster
B36: floor of CC | C36: 1 | D36: =C3-E22 -> 1.65 | E36: =E3 -> 1 | G36: =ROUND(+C36*D36*E36,2) -> 1.65
B37: Inner sides of Walls of CC | C37: 2 | D37: =D36 -> 1.65 | E37: - | F37: =H3 -> 2.5 | G37: =ROUND(+C37*D37*F37,2) -> 8.25
C38: 2 | D38: =E36 -> 1 | E38: - | F38: =H3 -> 2.5 | G38: =ROUND(+C38*D38*F38,2) -> 5
B39: Side of baffle wall | C39: 2 | D39: =D38 -> 1 | F39: =F22+0.1 -> 0.7 | G39: =ROUND(+C39*D39*F39,2) -> 1.4
B40: top of baffle wall | C40: 1 | D40: =D39 -> 1 | E40: =E22 -> 0.35 | G40: =ROUND(+C40*D40*E40,2) -> 0.35
B41: Outer portion of all walls above GL | C41: 1 | D41: =+(D13+E13)*2 -> 9.6 | E41: - | F41: 0.3 | G41: =ROUND(+C41*D41*F41,2) -> 2.88
B42: Total | G42: =SUM(G35:G41) -> 19.53 | H42: m² | I42: =Rates!$F$60 -> 503.61 | J42: =ROUND(G42*I42,2) -> 9835.5
A43: 9 | B43: 3 mm thick 1:1 c-s punning
C44: as per plaster | G44: =+G42 -> 19.53
B45: Deduct for outer portion | G45: =-G41 -> -2.88
B46: Total | G46: =SUM(G44:G45) -> 16.65 | H46: m² | I46: =Rates!$F$67 -> 346.26 | J46: =ROUND(G46*I46,2) -> 5765.23
A47: 10 | B47: Supply and installation of standard man hole cover - 600×600 mm² | C47: 2 | G47: =C47 -> 2 | H47: set | I47: =MR!$I$41*1.15 -> 2112.2625 | J47: =ROUND(G47*I47,2) -> 4224.53
A49: 11 | B49: Installation of pipes and fittings | G49: 1 | H49: job | I49: 500 | J49: =ROUND(G49*I49,2) -> 500
B50: Subtotal | J50: =SUM(J6:J49) -> 209962.44
B51: Add Value Added Tax | I51: ='Entry for Rates'!$F$114 -> 13 | J51: =I51*J50/100 -> 27295.117
B52: Total Amount | J52: =+J51+J50 -> 237257.56
A55: Distribution Chamber
B57: Inner size of CC portion: | C57: 2 | D57: x | E57: 0.8 | F57: Total height | H57: 1
A59: S.N. | B59: Description | C59: No. | D59: Length | E59: Breadth | F59: Height | G59: Quantity | H59: Unit | I59: Rate | J59: Amount
A61: 1 | B61: Site clearance | D61: 3 | E61: 2 | G61: =D61*E61 -> 6 | H61: m² | I61: =Rates!F7 -> 149.5 | J61: =ROUND(G61*I61,2) -> 897
A62: 2 | B62: Earthwork in excavation for fondation work in hard soil
C63: 1 | D63: =C57+0.45*2 -> 2.9 | E63: =E57+0.45*2 -> 1.7 | F63: =H57 -> 1 | G63: =C63*D63*E63*F63 -> 4.93 | H63: m³ | I63: =Rates!F9 -> 1480.63 | J63: =ROUND(G63*I63,2) -> 7299.51
A64: 3 | B64: Dry stone soling | C64: 1 | D64: =C57+0.45*2 -> 2.9 | E64: =E57+0.45*2 -> 1.7 | F64: 0.15 | G64: =C64*D64*E64*F64 -> 0.7395 | H64: m³ | I64: =Rates!F19 -> 5523.35 | J64: =ROUND(G64*I64,2) -> 4084.52
A65: 4 | B65: Plain Cement Concrete (1:2:4)
B66: in foundation | C66: 1 | D66: =C57+0.45*2 -> 2.9 | E66: =E57+0.45*2 -> 1.7 | F66: 0.1 | G66: =C66*D66*E66*F66 -> 0.493
B67: Pipe embeddment block | C67: 6 | D67: 0.45 | E67: 0.2 | F67: 0.2 | G67: =C67*D67*E67*F67 -> 0.108
B68: Cover slab | C68: 1 | D68: =C57+0.45*2 -> 2.9 | E68: =E57+0.45*2 -> 1.7 | F68: 0.08 | G68: =C68*D68*E68*F68 -> 0.3944
B69: Deduct:
B70: -Manhole cover | C70: 2 | D70: 0.6 | E70: 0.6 | F70: 0.05 | G70: =-2*PI()*D70*E70*F70 -> -0.11309734
B71: Total | G71: =SUM(G65:G70) -> 0.88230266 | H71: m³ | I71: =Rates!F32 -> 16022.87 | J71: =ROUND(G71*I71,2) -> 14137.02
A72: 5 | B72: Stone masonry work in 1:4 c-s mortar
B73: CC portion | C73: 1 | D73: =(C57+0.9+E57)*2 -> 7.4 | E73: 0.45 | F73: =H57 -> 1 | G73: =C73*D73*E73*F73 -> 3.33
B74: Partition wall | C74: 1 | D74: =+E57 -> 0.8 | E74: 0.35 | F74: =+H57 -> 1 | G74: =C74*D74*E74*F74 -> 0.28
B75: Total | G75: =SUM(G72:G74) -> 3.61 | H75: m³ | I75: =Rates!F24 -> 15619.64 | J75: =ROUND(G75*I75,2) -> 56386.9
A76: 6 | B76: Centering & shuttering work for PCC/RCC
B77: Bottom of cover slab - CC portion | C77: 1 | D77: =C57-E74 -> 1.65 | E77: =E57 -> 0.8 | G77: =D77*E77 -> 1.32
B78: -Outer edge of cover slab | C78: 1 | D78: =2*(D63+E63) -> 9.2 | E78: - | F78: =+F68 -> 0.08 | G78: =ROUND(+C78*D78*F78,2) -> 0.74
B79: Total form work | G79: =SUM(G77:G78) -> 2.06 | H79: m² | I79: =Rates!F40 -> 1322.68 | J79: =ROUND(G79*I79,2) -> 2724.72
A81: 7 | B81: Steel reinforcement
B82: 8 mm ø @ 175 mm c/c bothways | C82: =ROUND(D63/0.175+1,0) -> 18 | D82: =E63 -> 1.7 | E82: 0.395 | G82: =C82*D82*E82 -> 12.087
C83: =ROUND(E63/0.15+1,0) -> 12 | D83: =D63 -> 2.9 | E83: 0.395 | G83: =C83*D83*E83 -> 13.746
B84: Deduct for man hole | C84: 16 | D84: 0.6 | E84: 0.395 | G84: =-C84*D84*E84 -> -3.792
B85: Net reinforcement | G85: =SUM(G82:G84) -> 22.041 | H85: kg | I85: =Rates!F39 -> 125.35 | J85: =ROUND(G85*I85,2) -> 2762.84
A87: 8 | B87: 12.5 mm thick 1:4 c-s plaster
B88: floor of CC | C88: 1 | D88: =C57-E74 -> 1.65 | E88: =E57 -> 0.8 | G88: =ROUND(+C88*D88*E88,2) -> 1.32
B89: Inner sides of Walls of CC | C89: 2 | D89: =D88 -> 1.65 | E89: - | F89: =H57 -> 1 | G89: =ROUND(+C89*D89*F89,2) -> 3.3
C90: 2 | D90: =E88 -> 0.8 | E90: - | F90: =H57 -> 1 | G90: =ROUND(+C90*D90*F90,2) -> 1.6
B91: Side of partition wall | C91: 2 | D91: =D90 -> 0.8 | F91: =+H57 -> 1 | G91: =ROUND(+C91*D91*F91,2) -> 1.6
B92: Outer Portion of all walls above GL | C92: 1 | D92: =+(D66+E66)*2 -> 9.2 | E92: - | F92: 0.3 | G92: =ROUND(+C92*D92*F92,2) -> 2.76
B93: Total | G93: =SUM(G87:G92) -> 10.58 | H93: m² | I93: =Rates!F60 -> 503.61 | J93: =ROUND(G93*I93,2) -> 5328.19
A94: 9 | B94: 3 mm thick 1:1 c-s punning
C95: as per plaster | G95: =+G93 -> 10.58
B96: Deduct for outer portion | G96: =-G92 -> -2.76
B97: Total | G97: =SUM(G95:G96) -> 7.82 | H97: m² | I97: =Rates!F67 -> 346.26 | J97: =ROUND(G97*I97,2) -> 2707.75
A98: 10 | B98: Supply and installation of standard man hole cover - 600×600 mm² | C98: 2 | G98: =C98 -> 2 | H98: set | I98: =Rates!F93 -> 2479.6125 | J98: =ROUND(G98*I98,2) -> 4959.23
A100: 11 | B100: Installation of pipes and fittings | G100: 1 | H100: job | I100: =Rates!F103 -> 800 | J100: =ROUND(G100*I100,2) -> 800
B101: Subtotal | J101: =SUM(J61:J100) -> 102087.68
B102: Add Value Added Tax | I102: 13 | J102: =I102*J101/100 -> 13271.398
B103: Total Amount | J103: =+J102+J101 -> 115359.08

Sheet Private_Con
A1: Quantity Estimate
A3: House Connections
A4: Total nos. of connections | C4: 133
A6: S.N. | B6: Description | C6: No. | D6: Length | E6: Breadth | F6: Height | G6: Quantity | H6: Unit | I6: Rates | J6: Amount
A7: A | B7: Earth works for pipe laying
A8: 1 | B8: E/W in excavation in hard soil | C8: =C4 -> 133 | D8: 15 | E8: 0.4 | F8: 0.5 | G8: =F8*E8*D8*C8 -> 399 | H8: m³ | I8: =Rates!F9 -> 1480.63 | J8: =I8*G8 -> 590771.37
A9: 2 | B9: E/W in backfilling in hard soil | C9: =C8 -> 133 | D9: 15 | E9: 0.4 | F9: 0.5 | G9: =C9*D9*E9*F9 -> 399 | H9: m³ | I9: =Rates!F15 -> 746.24 | J9: =I9*G9 -> 297749.76
B10: Sub Total | J10: =SUM(J8:J9) -> 888521.13
B11: Quantity of Pipe and fittings
A13: 1 | B13: GI pipe 1/2" | C13: =$C$4 -> 133 | D13: 10 | G13: =C13*D13 -> 1330 | H13: m | I13: =data!D4 -> 172 | J13: =G13*I13 -> 228760
A14: 2 | B14: Water Meter | C14: =$C$4 -> 133 | D14: 1 | G14: =C14*D14 -> 133 | H14: no | I14: 1500 | J14: =G14*I14 -> 199500
A15: 3 | B15: Elbow 1/2" | C15: =$C$4 -> 133 | D15: 3 | G15: =C15*D15 -> 399 | H15: no | I15: =FittingsSummary!AB17 -> 86 | J15: =G15*I15 -> 34314
A16: 4 | B16: Socket 1/2" | C16: =$C$4 -> 133 | D16: 2 | G16: =C16*D16 -> 266 | H16: no | I16: =FittingsSummary!AB60 -> 30 | J16: =G16*I16 -> 7980
A17: 5 | B17: Nipple 1/2" | C17: =$C$4 -> 133 | D17: 3 | G17: =C17*D17 -> 399 | H17: no | I17: =FittingsSummary!AB32 -> 38 | J17: =G17*I17 -> 15162
A18: 6 | B18: Ferrule 1/2" | C18: =$C$4 -> 133 | D18: 1 | G18: =C18*D18 -> 133 | H18: no | I18: 664 | J18: =G18*I18 -> 88312
A19: 7 | B19: Union 1/2" | C19: =$C$4 -> 133 | D19: 1 | G19: =C19*D19 -> 133 | H19: no | I19: =FittingsSummary!AB79 -> 118 | J19: =G19*I19 -> 15694
A20: 8 | B20: Brass bib cock 1/2" | C20: =$C$4 -> 133 | D20: 1 | G20: =C20*D20 -> 133 | H20: no | I20: =FittingsSummary!AB123 -> 400 | J20: =G20*I20 -> 53200
B21: Sub Total | J21: =SUM(J13:J20) -> 642922
B22: Total | J22: =J21+J10 -> 1531443.1
B23: VAT @ 13% | J23: =J22*0.13 -> 199087.61
B24: Total With Vat | J24: =J23+J22 -> 1730530.7
B25: Rate Per HH Connection | J25: =J24/C4 -> 13011.509

Sheet Qty_in_1
A1: QUANTITY ESTIMATE
A2: TYPE OF WORK : Intake-3 Construction works-Fedi
A3: S.no. | B3: Description of works | C3: Unit | D3: No. | E3: Length,m | F3: Breadth,m | G3: Height,m | H3: Quantity | I3: Remarks
A4: 1 | B4: Site Clearance | C4: sqm | D4: 1 | E4: =7+1 -> 8 | F4: =14+0.3+3+3+1 -> 21.3 | H4: =+ROUND(PRODUCT(D4:G4),2) -> 170.4
A5: 2 | B5: Earthwork Excavation
B6: RCC Weir | C6: Cum | D6: 1 | E6: 5 | F6: 0.3 | G6: 1.525 | H6: =+ROUND(PRODUCT(D6:G6),2) -> 2.29 | L6: =1.5+0.1+0.15 -> 1.75 | M6: =0.31+0.1+0.15 -> 0.56
C7: Cum | D7: 1 | E7: =E6 -> 5 | F7: =2-0.3 -> 1.7 | G7: 0.525 | H7: =+ROUND(PRODUCT(D7:G7),2) -> 4.46
C8: Cum | D8: 1 | E8: =+E7 -> 5 | F8: 0.3 | G8: =+G6 -> 1.525 | H8: =+ROUND(PRODUCT(D8:G8),2) -> 2.29
C9: Cum | D9: 1 | E9: =+E8 -> 5 | F9: 3 | G9: 0.525 | H9: =+ROUND(PRODUCT(D9:G9),2) -> 7.88
B10: Collection and Valve Chamber | C10: Cum | D10: 1 | E10: 2.1 | F10: =2.5+0.3+1+0.25 -> 4.05 | G10: =1.5+0.3 -> 1.8 | H10: =+ROUND(PRODUCT(D10:G10),2) -> 15.31
C11: Cum | G11: Total | H11: =SUM(H6:H10) -> 32.23
A12: 3 | B12: Stone Soling
B13: RCC Weir | C13: Cum | D13: 1 | E13: =E6 -> 5 | F13: =3+0.3+2 -> 5.3 | G13: 0.15 | H13: =+ROUND(PRODUCT(D13:G13),2) -> 3.98
D14: 1 | E14: =4+0.3+3 -> 7.3 | F14: 1.3 | G14: 0.15 | H14: =+ROUND(PRODUCT(D14:G14),2) -> 1.42
B15: Collection and Valve Chamber | C15: Cum | D15: 1 | E15: =+E10 -> 2.1 | F15: 4.85 | G15: =G13 -> 0.15 | H15: =+ROUND(PRODUCT(D15:G15),2) -> 1.53
C16: Cum | G16: Total | H16: =SUM(H13:H15) -> 6.93
A18: 4.1 | B18: PCC M10
B19: RCC Weir | C19: Cum | D19: 1 | E19: =E13 -> 5 | F19: =F13 -> 5.3 | G19: 0.075 | H19: =+ROUND(PRODUCT(D19:G19),2) -> 1.99
C20: Cum | D20: 1 | E20: =E14 -> 7.3 | F20: =F14 -> 1.3 | G20: 0.075 | H20: =+ROUND(PRODUCT(D20:G20),2) -> 0.71
B21: Collection and Valve Chamber | C21: Cum | D21: 1 | E21: =E15 -> 2.1 | F21: =F15 -> 4.85 | G21: 0.075 | H21: =+ROUND(PRODUCT(D21:G21),2) -> 0.76
C22: Cum | G22: Total | H22: =SUM(H19:H21) -> 3.46
A23: 4.2 | B23: RCC works M20
B24: RCC Weir Wall | C24: cum | D24: 1 | E24: =E19 -> 5 | F24: 0.3 | G24: 1.525 | H24: =+ROUND(PRODUCT(D24:G24),2) -> 2.29
C25: cum | D25: 1 | E25: =E24 -> 5 | F25: =2-0.3 -> 1.7 | G25: 0.3 | H25: =+ROUND(PRODUCT(D25:G25),2) -> 2.55
C26: cum | D26: =D25 -> 1 | E26: =E25 -> 5 | F26: 0.3 | G26: =1+0.995+0.3 -> 2.295 | H26: =+ROUND(PRODUCT(D26:G26),2) -> 3.44
C27: cum | D27: =D26 -> 1 | E27: =E26 -> 5 | F27: 3 | G27: 0.3 | H27: =+ROUND(PRODUCT(D27:G27),2) -> 4.5
B28: Collection Chamber | C28: cum | D28: =D21 -> 1 | E28: =E21 -> 2.1 | F28: =F21 -> 4.85 | G28: 0.3 | H28: =+ROUND(PRODUCT(D28:G28),2) -> 3.06
B29: Wall | C29: cum | D29: 1 | E29: 8.3 | F29: 0.3 | G29: 2.15 | H29: =+ROUND(PRODUCT(D29:G29),2) -> 5.35
B30: Cover slab | C30: cum | D30: 1 | E30: 2.1 | F30: =2.5+0.3+0.3 -> 3.1 | G30: 0.15 | H30: =+ROUND(PRODUCT(D30:G30),2) -> 0.98
B31: Valve Chamber
B32: Wall | C32: cum | D32: 1 | E32: =1.25*2+2.1 -> 4.6 | F32: 0.25 | G32: =G29 -> 2.15 | H32: =+ROUND(PRODUCT(D32:G32),2) -> 2.47
B33: Cover slab | C33: cum | D33: 1 | E33: 2.1 | F33: 1.25 | G33: 0.15 | H33: =+ROUND(PRODUCT(D33:G33),2) -> 0.39
B34: Deduction of Manhole Cover | C34: cum | D34: -2 | E34: =3.14*0.6^2/4 -> 0.2826 | G34: 0.15 | H34: =+ROUND(PRODUCT(D34:G34),2) -> -0.08
C35: Cum | G35: Total | H35: =SUM(H24:H34) -> 24.95
A36: 5 | B36: One layer of Water Proofing
B37: Collection Chamber | C37: sqm | D37: =D28 -> 1 | E37: =E28 -> 2.1 | F37: =F28 -> 4.85 | H37: =+ROUND(PRODUCT(D37:G37),2) -> 10.19
B38: Wall | C38: sqm | D38: 1 | E38: =+(E37+F37)*2 -> 13.9 | G38: 2.15 | H38: =+ROUND(PRODUCT(D38:G38),2) -> 29.89
C39: sqm | G39: Total | H39: =SUM(H37:H38) -> 40.08
A40: 6 | B40: Form Works
B41: RCC Weir Base | C41: sqm | D41: 1 | E41: =2*(E19+F19) -> 20.6 | G41: =+G19 -> 0.075 | H41: =+ROUND(PRODUCT(D41:G41),2) -> 1.55
B42: RCC Weir Wall | C42: sqm | D42: 1 | E42: =+(E24+F24)*2 -> 10.6 | G42: =G24 -> 1.525 | H42: =+ROUND(PRODUCT(D42:G42),2) -> 16.17
C43: sqm | D43: 1 | E43: =2*(E25+F25) -> 13.4 | G43: =G25 -> 0.3 | H43: =+ROUND(PRODUCT(D43:G43),2) -> 4.02
C44: sqm | D44: 1 | E44: =2*(E26+F26) -> 10.6 | G44: =G26 -> 2.295 | H44: =+ROUND(PRODUCT(D44:G44),2) -> 24.33
C45: sqm | D45: 1 | E45: =E27+2*F27 -> 11 | G45: =G27 -> 0.3 | H45: =+ROUND(PRODUCT(D45:G45),2) -> 3.3
B46: Collection Chamber | C46: sqm | D46: 2 | E46: =+(E28+F28)*2 -> 13.9 | G46: =+G28 -> 0.3 | H46: =+ROUND(PRODUCT(D46:G46),2) -> 8.34
B47: Wall | C47: sqm | D47: =D28 -> 1 | E47: =+(E29+F29)*2 -> 17.2 | G47: =+G29 -> 2.15 | H47: =+ROUND(PRODUCT(D47:G47),2) -> 36.98
B48: Cover slab | C48: sqm | D48: =D30 -> 1 | E48: =E30+2*G30 -> 2.4 | F48: =F30+2*G30 -> 3.4 | H48: =+ROUND(PRODUCT(D48:G48),2) -> 8.16
B49: Valve Chamber
B50: Wall | C50: sqm | D50: =2*D32 -> 2 | E50: =E32 -> 4.6 | G50: =G32 -> 2.15 | H50: =+ROUND(PRODUCT(D50:G50),2) -> 19.78
B51: Cover slab | C51: sqm | D51: =D33 -> 1 | E51: =E33+2*G33 -> 2.4 | F51: =F33+2*G33 -> 1.55 | H51: =+ROUND(PRODUCT(D51:G51),2) -> 3.72
B52: Deduction of Manhole Cover | C52: sqm | D52: =D34 -> -2 | E52: =E34 -> 0.2826 | H52: =+ROUND(PRODUCT(D52:G52),2) -> -0.57
C53: sqm | G53: Total | H53: =SUM(H41:H52) -> 125.78
A54: 7 | B54: Reinforcement | C54: kg | H54: =+H35*35.32*4.5 -> 3965.553
A56: 9 | B56: 20 to 25mm thick screeding (1:4) on floors
B57: Collection Chamber | C57: sqm | D57: 1 | E57: 2.5 | F57: 1.5 | H57: =+ROUND(PRODUCT(D57:G57),2) -> 3.75
B58: Valve Chamber | C58: sqm | D58: 1 | E58: 1.5 | F58: 1 | H58: =+ROUND(PRODUCT(D58:G58),2) -> 1.5
C59: sqm | G59: Total | H59: =SUM(H57:H58) -> 5.25
A60: 10 | B60: Cement punning
B61: Collection Chamber | C61: sqm | D61: 1 | E61: =E57 -> 2.5 | F61: =F57 -> 1.5 | H61: =+ROUND(PRODUCT(D61:G61),2) -> 3.75
B62: Wall | C62: sqm | D62: 2 | E62: =+(E61+F61)*2 -> 8 | G62: 2.15 | H62: =+ROUND(PRODUCT(D62:G62),2) -> 34.4
B63: Valve Chamber | C63: sqm | D63: 1 | E63: =E58 -> 1.5 | F63: =F58 -> 1 | H63: =+ROUND(PRODUCT(D63:G63),2) -> 1.5
B64: Wall | C64: sqm | D64: 2 | E64: =+(E63+F63)*2 -> 5 | G64: =G50 -> 2.15 | H64: =+ROUND(PRODUCT(D64:G64),2) -> 21.5
C65: sqm | G65: Total | H65: =SUM(H61:H64) -> 61.15
A66: 11 | B66: 12.5 mm thick cement plaster on concrete surface with 1:3 cement sand mortar
B67: Collection Chamber
B68: Wall | C68: sqm | D68: 2 | E68: =E62 -> 8 | G68: =G62 -> 2.15 | H68: =+ROUND(PRODUCT(D68:G68),2) -> 34.4
B69: Cover slab | C69: sqm | D69: 2 | E69: =E48 -> 2.4 | F69: =F48 -> 3.4 | H69: =+ROUND(PRODUCT(D69:G69),2) -> 16.32
B70: Valve Chamber
B71: Wall | C71: sqm | D71: 2 | E71: =E64 -> 5 | G71: =G64 -> 2.15 | H71: =+ROUND(PRODUCT(D71:G71),2) -> 21.5
B72: Cover slab | C72: sqm | D72: 2 | E72: =E51 -> 2.4 | F72: =F51 -> 1.55 | H72: =+ROUND(PRODUCT(D72:G72),2) -> 7.44
B73: Deduction of Manhole Cover | C73: sqm | D73: =D52 -> -2 | E73: =E52 -> 0.2826 | H73: =+ROUND(PRODUCT(D73:G73),2) -> -0.57
C74: sqm | G74: Total | H74: =SUM(H67:H73) -> 79.09
A75: 12 | B75: Gabion Works
B76: Gabion Rip Rap Mesh
B77: 2mx1mx0.3m | C77: Cum | D77: 1 | E77: 14 | F77: 10.6 | G77: 0.3 | H77: =+ROUND(PRODUCT(D77:G77),2) -> 44.52
A78: 13 | B78: 600dia. Manhole Cover | C78: No. | D78: 2 | H78: =+ROUND(PRODUCT(D78:G78),2) -> 2
A79: 15 | B79: Supplying and laying Pipes Fittings
B80: 75∅ Tee | C80: No. | D80: 2 | H80: =+ROUND(PRODUCT(D80:G80),2) -> 2
B81: 75∅ Elbow | C81: No. | D81: 2 | H81: =+ROUND(PRODUCT(D81:G81),2) -> 2
B82: 75∅ Pipe Piece | C82: No. | D82: 10 | H82: =+ROUND(PRODUCT(D82:G82),2) -> 10
B83: 65∅ Gate Valve | C83: No. | D83: 2 | H83: =+ROUND(PRODUCT(D83:G83),2) -> 2
B84: 65∅ Union | C84: No. | D84: 2 | H84: =+ROUND(PRODUCT(D84:G84),2) -> 2
B85: 65∅ Nipple | C85: No. | D85: 2 | H85: =+ROUND(PRODUCT(D85:G85),2) -> 2
B86: 65/75 GI/PE Flanged set | C86: No. | D86: 2 | H86: =+ROUND(PRODUCT(D86:G86),2) -> 2
B87: 75∅ PE Stainer | C87: No. | D87: 1 | H87: =+ROUND(PRODUCT(D87:G87),2) -> 1
A89: TYPE OF WORK : Boulder Pitching in river
A90: S.no. | B90: Description of works | C90: Unit | D90: No. | E90: Length,m | F90: Breadth,m | G90: Height,m | H90: Quantity | I90: Remarks
A91: 1 | B91: Earthwork Excavation
C92: cum | D92: 1 | E92: 50 | F92: =1.68+1 -> 2.68 | G92: 1 | H92: =+ROUND(PRODUCT(D92:G92),2) -> 134
C93: cum | H93: =SUM(H92:H92) -> 134
A94: 2 | B94: Back filling
C95: cum | D95: 1 | E95: =E92*50% -> 25 | F95: 1.2 | G95: =G92 -> 1 | H95: =+ROUND(PRODUCT(D95:G95),2) -> 30
C96: cum | H96: =SUM(H95:H95) -> 30
A98: 4 | B98: Masonary Works
A99: 4.1 | B99: Stone Soling | C99: cum | D99: 1 | E99: =E92 -> 50 | F99: 1.68 | G99: 0.2 | H99: =+ROUND(PRODUCT(D99:G99),2) -> 16.8
C100: cum | H100: =SUM(H99:H99) -> 16.8
A101: 4.3 | B101: Stone Masonary(1:6)
C102: cum | D102: 1 | E102: =E99 -> 50 | F102: 0.35 | G102: 0.32 | H102: =+ROUND(PRODUCT(D102:G102),2) -> 5.6 | L102: =7/3.281 -> 2.1334959 | M102: =1.5*3.281 -> 4.9215
B103: Gate Pillar | C103: cum | D103: 2 | E103: 0.45 | F103: 0.45 | G103: 1.5 | H103: =+ROUND(PRODUCT(D103:G103),2) -> 0.61
C104: cum | H104: =SUM(H102:H103) -> 6.21
...

Sheet int
A1: Stream Intake ( Type II )
A2: (Without valve chamber )
B3: Total length of wing walls | C3: 4 | D3: m | E3: Size of C.C | G3: 1 | H3: x | I3: 1
B4: Height of structure | C4: 1.5 | D4: m
A5: ='Entry for Rates'!F4 -> 0 | J5: Intake: Damai Kholsi
A6: S.N. | B6: Description | C6: No. | D6: Length | E6: Breadth | F6: Height | G6: Quantity | H6: Unit | I6: Rate | J6: Amount
A7: 1 | B7: Site Clearance | D7: 5 | E7: 3 | G7: =D7*E7 -> 15 | H7: m2 | I7: =Rates!F7 -> 149.5 | J7: =ROUND(G7*I7,2) -> 2242.5
A8: 2 | B8: Earthwork in excavation in foundation
B9: wing wall | D9: =C3+0.45 -> 4.45 | E9: 0.45 | F9: 1 | G9: =ROUND(D9*E9*F9,2) -> 2
B10: Catchment portion | D10: =G3+2*0.45 -> 1.9 | E10: =2*0.45+I3 -> 1.9 | F10: 0.8 | G10: =ROUND(D10*E10*F10,2) -> 2.89
B11: Pipe trench for washout | D11: 10 | E11: 0.45 | F11: 1 | G11: =ROUND(D11*E11*F11,2) -> 4.5
B12: water diversion and drainage ditch | D12: 10 | E12: 0.5 | F12: 0.5 | G12: =ROUND(D12*E12*F12,2) -> 2.5
B13: Total earth work | G13: =SUM(G9:G12) -> 11.89 | H13: m³ | I13: =Rates!F9 -> 1480.63 | J13: =ROUND(G13*I13,2) -> 17604.69
A14: 3 | B14: Plain Cement Concrete (1:2:4)
B15: Wing Walls | D15: =C3+0.45 -> 4.45 | E15: 0.45 | F15: 0.1 | G15: =ROUND(D15*E15*F15,3) -> 0.2
B16: Catchment Portion | D16: =G3+0.45*2 -> 1.9 | E16: =I3+0.45*2 -> 1.9 | F16: 0.1 | G16: =ROUND(D16*E16*F16,3) -> 0.361
B17: At the top of Wing Wall | D17: =C3+0.45 -> 4.45 | E17: 0.45 | F17: 0.05 | G17: =ROUND(D17*E17*F17,3) -> 0.1
B18: Lintel over drywall | D18: 0.7 | E18: 0.45 | F18: 0.1 | G18: =ROUND(D18*E18*F18,3) -> 0.032
B19: Pipe Embeddment blocks | C19: 3 | D19: 0.45 | E19: 0.2 | F19: 0.2 | G19: =ROUND(C19*D19*E19*F19,3) -> 0.054
B20: For cover slab | D20: =G3+0.45*2 -> 1.9 | E20: =I3+0.45*2 -> 1.9 | F20: 0.1 | G20: =ROUND(D20*E20*F20,3) -> 0.361
B21: Deduct :
B22: Manhole Cover | C22: 1 | D22: 0.6 | E22: 0.6 | F22: 0.05 | G22: =-ROUND(D22*C22*E22*F22,3) -> -0.018
B23: Total | G23: =SUM(G15:G22) -> 1.09 | H23: m³ | I23: =Rates!F32 -> 16022.87 | J23: =ROUND(G23*I23,2) -> 17464.93
A24: 4 | B24: Stone masonry in 1:4 c-s mortar
B25: Wing Wall | D25: =C3+0.45 -> 4.45 | E25: 0.45 | F25: =C4 -> 1.5 | G25: =ROUND(D25*E25*F25,2) -> 3
B26: Walls of CC | D26: =(G3+0.45*2)*2+I3*2 -> 5.8 | E26: 0.45 | F26: =C4 -> 1.5 | G26: =ROUND(D26*E26*F26,2) -> 3.92
B27: Deduction
B28: for embeddment block | C28: =C19 -> 3 | D28: =D19 -> 0.45 | E28: =E19 -> 0.2 | F28: =F19 -> 0.2 | G28: =-ROUND(D28*C28*E28*F28,2) -> -0.05
B29: for dry wall | D29: 0.5 | E29: 0.45 | F29: 0.3 | G29: =-ROUND(D29*E29*F29,2) -> -0.07
B30: Total masonry work | G30: =SUM(G25:G29) -> 6.8 | H30: m³ | I30: =Rates!F24 -> 15619.64 | J30: =ROUND(G30*I30,2) -> 106213.55
A31: 5 | B31: Dry stone masonry | D31: 0.5 | E31: 0.45 | F31: 0.3 | G31: =ROUND(D31*E31*F31,2) -> 0.07 | H31: m³ | I31: =Rates!F21 -> 7311.32 | J31: =ROUND(G31*I31,2) -> 511.79
A33: 6 | B33: Steel reinforcement
B34: 8mm f bars @ 150c/c both ways
B35: for cover slab | C35: =ROUND((G3+0.45*2)/0.15+1,0) -> 14 | D35: =I3+0.45*2+0.05 -> 1.95 | E35: 0.395 | G35: =ROUND(C35*D35*E35,2) -> 10.78
C36: =ROUND((I3+0.45*2)/0.15+1,0) -> 14 | D36: =G3+0.45*2+0.05 -> 1.95 | E36: 0.395 | G36: =ROUND(C36*D36*E36,2) -> 10.78
B37: Deduction for Manhole Opening | C37: 8 | D37: 0.6 | E37: 0.395 | G37: =-C37*D37*E37 -> -1.896
B38: Total | G38: =SUM(G35:G37) -> 19.664 | H38: kg | I38: =Rates!F39 -> 125.35 | J38: =ROUND(G38*I38,2) -> 2464.88
A39: 7 | B39: Centering & shuttering works for RCC/PCC
B40: edge of slab | C40: 2 | D40: =+G3+0.45*2 -> 1.9 | E40: - | F40: =+F20 -> 0.1 | G40: =ROUND(C40*D40*F40,2) -> 0.38
C41: 2 | D41: 0.64 | E41: - | F41: =+F20 -> 0.1 | G41: =ROUND(C41*D41*F41,2) -> 0.13
B42: Slab Cover - of CC | D42: =G3 -> 1 | E42: =I3 -> 1 | F42: - | G42: =ROUND(D42*E42,2) -> 1
B43: Top of wing wall | C43: 2 | D43: =C3+0.45 -> 4.45 | E43: - | F43: =+F17 -> 0.05 | G43: =ROUND(+C43*D43*F43,2) -> 0.45
B44: Total | G44: =SUM(G40:G43) -> 1.96 | H44: m² | I44: =Rates!F40 -> 1322.68 | J44: =ROUND(G44*I44,2) -> 2592.45
A45: 8 | B45: 12.5 mm thick 1:3 cement sand plaster
B46: inside of wing walls | D46: =C3+I3+2*0.45 -> 5.9 | E46: - | F46: =C4 -> 1.5 | G46: =ROUND(D46*F46,2) -> 8.85 | H46: m²
B47: Inside of CC walls | D47: =2*(G3+I3) -> 4 | F47: =C4 -> 1.5 | G47: =ROUND(D47*F47,2) -> 6
B48: Floor of CC | D48: =G3 -> 1 | E48: =I3 -> 1 | F48: - | G48: =ROUND(D48*E48,2) -> 1
B49: Outside of CC | D49: =2*(G3+0.45*2)+I3+0.45*2 -> 5.7 | F49: =F46+F20 -> 1.6 | G49: =ROUND(D49*F49,2) -> 9.12
B50: Total plastering work | G50: =SUM(G46:G49) -> 24.97 | H50: m² | I50: =Rates!F59 -> 509.41 | J50: =ROUND(G50*I50,2) -> 12719.97
A52: 9 | B52: 3 mm 1:1cement sand punnig | C52: as plastering work | G52: =G50 -> 24.97
B53: Deduct for outside of walls | D53: =D49 -> 5.7 | F53: =F49 -> 1.6 | G53: =-ROUND(D53*F53,2) -> -9.12
B54: Total punning work | G54: =SUM(G52:G53) -> 15.85 | H54: m² | I54: =Rates!F67 -> 346.26 | J54: =ROUND(G54*I54,2) -> 5488.22
A56: 10 | B56: Boulder packing | C56: 1 | D56: 2.76 | E56: 0.6 | F56: 0.5 | G56: =C56*D56*E56*F56 -> 0.828 | H56: m³ | I56: =Rates!F19 -> 5523.35 | J56: =ROUND(G56*I56,2) -> 4573.33
A57: 11 | B57: Standard manhole over 60cm×60cm size | G57: 1 | H57: set | I57: =MR!$I$41*1.15 -> 2112.2625 | J57: =ROUND(G57*I57,2) -> 2112.26
A58: 12 | B58: Barbed wire fencing (Type - B) | G58: 22 | H58: m | I58: ='bar+gate'!J$75 -> 1925.17 | J58: =ROUND(G58*I58,2) -> 42353.74
A59: 13 | B59: Wooden entrance gate (1 m x 1.5 m) | G59: 1 | H59: no | I59: ='bar+gate'!J$98 -> 16574.28 | J59: =ROUND(G59*I59,2) -> 16574.28
A60: 14 | B60: Dewatering | G60: 1 | H60: Job | I60: =Rates!F$111 -> 450 | J60: =ROUND(G60*I60,2) -> 450
A61: 15 | B61: Installation of Pipes & Fittings | G61: 1 | H61: job | I61: =Rates!F$99 -> 600 | J61: =ROUND(G61*I61,2) -> 600
B62: Subtotal | J62: =SUM(J7:J61) -> 233966.59
B63: Add Value Added Tax | I63: ='Entry for Rates'!$F$114 -> 13 | J63: =I63*J62/100 -> 30415.657
B64: Total Amount with VAT | I64: Rs. | J64: =+J63+J62 -> 264382.25

Sheet fe-tank
A1: Ferrocement Storage Tank
A2: ='Entry for Rates'!F4 -> 0 | C2: 10
B3: Diameter, d = | C3: =VLOOKUP(C2,data!F$4:I$18,4,FALSE) -> 3 | D3: m | G3: Tank wall height, h = | H3: =VLOOKUP(C2,data!F$4:H$18,3,FALSE) -> 1.65 | I3: m
B4: Dome height, = | C4: =VLOOKUP(C2,data!F$4:G$18,2,FALSE) -> 0.5 | D4: m | F4: For Scheme # no: | G4: ='Salient feature'!D8 -> 1 | K4: =+K103 -> 360013.89
A5: S.N. | B5: Description | C5: No. | D5: Radius | E5: Length/Radius | F5: Breadth | G5: Height | H5: Qty. | I5: Unit | J5: Rate | K5: Amount
A6: 1 | B6: Site Clearance(L= d+2*2.0m,B=d+1m) | E6: =ROUND(C3+4,0) -> 7 | F6: =ROUND(C3+2,0) -> 5 | H6: =E6*F6 -> 35 | I6: m² | J6: =Rates!$F$7 -> 149.5 | K6: =H6*J6 -> 5232.5
A7: 2 | B7: Earthwork in excavation for foundation in hard soil
B8: Valve Chamber | E8: 1.7 | F8: 1.5 | G8: 1.3 | H8: =E8*F8*G8 -> 3.315
B9: Storage tank | C9: π | D9: =C3/2+0.05+0.75 -> 2.3 | E9: =D9 -> 2.3 | F9: - | G9: =H3+0.3-0.4 -> 1.55 | H9: =IF(C9="π",PI()*D9*E9*G9,IF(C9="2π",2*PI()*D9*E9*G9,"Change")) -> 25.759489
B10: (Q = p x R² x h, R = d/2+0.05+0.75
B11: Total | H11: =SUM(H8:H10) -> 29.074489 | I11: m³ | J11: =Rates!F9 -> 1480.63 | K11: =H11*J11 -> 43048.561
A12: 3 | B12: Earthwork in back filling with
B13: in storage tank : total trench (p*R2*h') | C13: π | D13: =D9 -> 2.3 | E13: =D9 -> 2.3 | F13: - | G13: =G9-0.5 -> 1.05 | H13: =IF(C13="π",PI()*D13*E13*G13,IF(C13="2π",2*PI()*D13*E13*G13,"Change")) -> 17.449976 | I13: m³
B14: Deduct tank portion (p*r2*h'): r=d/2+.05 | C14: π | D14: =C3/2+0.05 -> 1.55 | E14: =D14 -> 1.55 | F14: - | G14: =G13 -> 1.05 | H14: =-PI()*D14*E14*G14 -> -7.9250602 | I14: m³
B15: Net backfilling work | H15: =H13+H14 -> 9.5249162 | I15: =I11 -> m³ | J15: =Rates!$F$15 -> 746.24 | K15: =H15*J15 -> 7107.8735
A16: 4 | B16: Stone soling work
B17: Valve Chamber | E17: 1.7 | F17: 1.5 | G17: 0.15 | H17: =E17*F17*G17 -> 0.3825
B18: Storage tank | C18: π | D18: =C3/2+0.05+0.25 -> 1.8 | E18: =D18 -> 1.8 | F18: - | G18: 0.2 | H18: =IF(C18="π",PI()*D18*E18*G18,IF(C18="2π",2*PI()*D18*E18*G18,"Change")) -> 2.035752
B19: (Q = p x r² x h, r = d/2+0.05+0.25
B20: deduction for overlapping with VC portion | E20: 1.7 | F20: 0.4 | G20: 0.2 | H20: =-E20*F20*G20 -> -0.136
B21: Total | H21: =H17+H18+H20 -> 2.282252 | I21: m³ | J21: =Rates!$F$19 -> 5523.35 | K21: =H21*J21 -> 12605.677
A22: 5 | B22: Stone masonry in 1:6 c-s mortar
B23: Valve Chamber | E23: 5 | F23: 0.35 | G23: 1.15 | H23: =E23*F23*G23 -> 2.0125 | I23: m³ | J23: =Rates!$F$25 -> 14917.39 | K23: =H23*J23 -> 30021.247
A24: 6 | B24: Plain cement concrete (1:2:4)
B25: Cover slab of valve chamber | E25: 1.7 | F25: 1.5 | G25: 0.1 | H25: =E25*F25*G25 -> 0.255
B26: Deduction for manhole opening | C26: π | D26: 0.3 | E26: 0.3 | F26: - | G26: 0.05 | H26: =-IF(C26="π",PI()*D26*E26*G26,IF(C26="2π",2*PI()*D26*E26*G26,"Change")) -> -0.014137167
B27: (Q = p x r² x h, r = 0.30)
B28: Manhole Cover of tank | C28: π | D28: 0.3 | E28: 0.3 | F28: - | G28: 0.05 | H28: =IF(C28="π",PI()*D28*E28*G28,IF(C28="2π",2*PI()*D28*E28*G28,"Change")) -> 0.014137167
B29: Pipe embeddment block | C29: 2 | E29: 1 | F29: 0.35 | G29: 0.2 | H29: =C29*E29*F29*G29 -> 0.14
B30: Total | H30: =SUM(H25:H29) -> 0.395 | I30: m³ | J30: =Rates!$F$32 -> 16022.87 | K30: =H30*J30 -> 6329.0337
A31: 7 | B31: Plain Cement Concrete (1:1.5:3)
B32: for tank base(Q = p x r² x h, r = d/2+0.05+0.10 | C32: π | D32: =C3/2+0.05+0.1 -> 1.65 | E32: =D32 -> 1.65 | F32: - | G32: =(0.1+0.15)/2 -> 0.125 | H32: =PI()*D32*E32*G32 -> 1.0691232 | I32: m³ | J32: =Rates!$F$33 -> 17163.13 | K32: =H32*J32 -> 18349.501
A34: 8 | B34: Steel reinforcement
B35: for VC slab cover 8 mmf bars @ 15 cm c/c both ways
B36: Longer span | C36: 11 | D36: 1.7 | F36: 0.395 | H36: =ROUND(C36*D36*F36,2) -> 7.39
B37: Shorter span | C37: 12 | D37: 1.5 | F37: 0.395 | H37: =ROUND(C37*D37*F37,2) -> 7.11
B38: Deduction for manhole opening | C38: 8 | D38: 0.6 | F38: 0.395 | H38: =-ROUND(C38*D38*F38,2) -> -1.9
B39: Total | H39: =SUM(H36:H38) -> 12.6 | I39: kg | J39: =Rates!$F$39 -> 125.35 | K39: =H39*J39 -> 1579.41
A40: 9 | B40: Shuttering works for RCC
B41: - Cover slab bottom | E41: 1 | F41: 0.8 | H41: =E41*F41 -> 0.8
B42: Side | E42: 6.4 | F42: - | G42: 0.1 | H42: =E42*G42 -> 0.64
B43: Deduction for manhole opening | C43: π | D43: 0.3 | E43: 0.3 | H43: =-IF(C43="π",PI()*D43*E43,IF(C43="2π",2*PI()*D43*E43,"Change")) -> -0.28274334
B44: Total | H44: =SUM(H41:H43) -> 1.1572567 | I44: m² | J44: =Rates!$F$40 -> 1322.68 | K44: =H44*J44 -> 1530.6802
A45: 10 | B45: HDPE formwork for ferrocement
B46: - Wall portion (Q = 2 x p x r x h, r = d/2+.025) | C46: 2π | D46: =C3/2+0.025 -> 1.525 | F46: - | G46: =H3 -> 1.65 | H46: =2*PI()*D46*G46 -> 15.810065
B47: - Roof portion | C47: 2π | D47: =((C3+0.05)^2+4*(C4^2))/8/C4 -> 2.575625 | G47: =C4 -> 0.5 | H47: =2*PI()*D47*G47 -> 8.0915646
B48: Q = 2 x p x R x h, R = ((d+.05)² +4h²)/8h,h=dome height
B49: - Deduction for manhole opening Q=pxr², r=0.30 | C49: π | D49: 0.3 | E49: 0.3 | H49: =-D49*E49*PI() -> -0.28274334
B50: Total form work | H50: =SUM(H46:H49) -> 23.618886 | I50: m² | J50: =Rates!$F$42 -> 490.15 | K50: =H50*J50 -> 11576.797
H55: RT size: | J55: =C2 -> 10 | K55: m³
A56: S.N. | B56: Description | C56: No. | D56: Radius | E56: Length | F56: Breadth | G56: Height | H56: Quantity | I56: Unit | J56: Rate | K56: Amount
A58: 11 | B58: Bar binding work including chicken wire mesh,
B59: MS bar, GI wire, etc. | D59: as per HDPE form work | H59: =H50 -> 23.618886 | I59: m² | J59: =Rates!$F$43 -> 1246.28 | K59: =H59*J59 -> 29435.746
A61: 12 | B61: 12.5 mm thick 1:2 cement-sand plaster
B62: 4 layers for ferrocement
B63: - Wall portion (Q = 4x2 p x r x h, r = d/2+.025) | C63: 4×2π | D63: =D46 -> 1.525 | G63: =G46 -> 1.65 | H63: =D63*G63*4*PI()*2 -> 63.24026
B64: - Roof portion | C64: 4×2π | D64: =D47 -> 2.575625 | G64: =G47 -> 0.5 | H64: =8*PI()*D64*G64 -> 32.366258
B65: Q = 2 x p x R x h, R = ((d+.05)² +4h²)/8h,h=dome height
B66: - Deduction for manhole opening | C66: 4×2π | D66: 0.3 | E66: 0.3 | H66: =-4*PI()*D66*E66 -> -1.1309734
B67: (Q = 4 x p x r², r = 0.60/2 = 0.30)
B68: Total plaster | H68: =SUM(H63:H66) -> 94.475545 | I68: m² | J68: =Rates!$F$58 -> 547.55 | K68: =H68*J68 -> 51730.085
A69: 13 | B69: 12.5 mm thick 1:3 cement-sand plaster
B70: sand mortar for
B71: - Floor portion of storage tank | C71: π | D71: =C3/2 -> 1.5 | E71: =C3/2 -> 1.5 | H71: =PI()*D71*E71 -> 7.0685835 | I71: m² | J71: =Rates!$F$59 -> 509.41 | K71: =H71*J71 -> 3600.8071
B72: (Q = p x r², r = d/2)
A74: 14 | B74: 12.5 mm thick 1:4 cement-sand plaster
B75: - Floor portion of valve chamber | E75: 1 | F75: 0.8 | H75: =E75*F75 -> 0.8
B76: - inner wall of valve chamber | E76: 3.6 | G76: 1.15 | H76: =E76*G76 -> 4.14
B77: Total plaster | H77: =SUM(H75:H76) -> 4.94 | I77: m² | J77: =Rates!$F$60 -> 503.61 | K77: =H77*J77 -> 2487.8334
A79: 15 | B79: 3 mm thick 1:1 cement sand punning
B80: - Floor portion of storage tank(Q = p x r², r = d/2) | C80: π | D80: =C3/2 -> 1.5 | E80: =C3/2 -> 1.5 | H80: =PI()*D80*E80 -> 7.0685835
B81: - Wall portion of storage tank (Q = 2 x p x r x h) | C81: 2π | D81: =C3/2 -> 1.5 | G81: =H3 -> 1.65 | H81: =2*PI()*D81*G81 -> 15.550884
B82: Total punning | H82: =SUM(H80:H81) -> 22.619467 | I82: m² | J82: =Rates!$F$67 -> 346.26 | K82: =H82*J82 -> 7832.2167
A83: 16 | B83: Bitumen paint on the buried surface of storage tank
B84: (Q = 2 x p x r x h, r = d/2+0.05) | C84: 2π | D84: =C3/2+0.05 -> 1.55 | G84: =H3-0.4 -> 1.25 | H84: =2*PI()*D84*G84 -> 12.173672 | I84: m² | J84: =Rates!$F$72 -> 103.35 | K84: =H84*J84 -> 1258.149
A86: 17 | B86: Snowcem paint on exposed surface of storage tank
B87: - Wall portion | C87: 2π | D87: =C3/2+0.05 -> 1.55 | G87: 0.4 | H87: =2*PI()*D87*G87 -> 3.8955749
B88: (Q = 2 x p x r x h, r = d/2+0.05)
B89: - Roof portion | C89: 2π | D89: =((C3+0.1)^2+4*(G89)^2)/(8*(G89)) -> 2.6525 | G89: =C4 -> 0.5 | H89: =D89*G89*2*PI() -> 8.3330745
B90: (Q = 2xpxRxh, R = (D²+4h²)/8h, D = d+0.10, h= dome height)
B91: Total | H91: =SUM(H87:H90) -> 12.228649 | I91: m² | J91: =Rates!$F$71 -> 213.84 | K91: =H91*J91 -> 2614.9744
A93: 18 | B93: 600 mmf circular metal manhole cover for ferrocement | H93: 2 | I93: set | J93: =MR!$I$42*1.15 -> 1465.215 | K93: =H93*J93 -> 2930.43
A95: 19 | B95: Installation of Pipes & fittings | H95: 1 | I95: job | J95: 700 | K95: =H95*J95 -> 700
A97: 20 | B97: Barbed wire fencing (Type-A) | C97: 1 | D97: =VLOOKUP(C2,data!F$4:J$18,5,FALSE) -> 24 | H97: =D97 -> 24 | I97: m | J97: ='bar+gate'!$J$18 -> 2472.44 | K97: =H97*J97 -> 59338.56
A99: 21 | B99: Entrancce gate in barbed wire fencing (Type-A) | C99: 1 | H99: 1 | I99: No | J99: ='bar+gate'!$J$42 -> 19286.28 | K99: =H99*J99 -> 19286.28
B101: Total Amount without VAT | K101: =SUM(K6:K99) -> 318596.36
B102: Add Value Added Tax | J102: ='Entry for Rates'!$F$114 -> 13 | K102: =J102*K101/100 -> 41417.527
B103: Total cost of reservoir tank with fencing and gate | J103: Rs. | K103: =+K102+K101 -> 360013.89
A104: Ferrocement Storage Tank
C105: 20
B106: Diameter, d = | C106: =VLOOKUP(C105,data!F$4:I$18,4,FALSE) -> 4 | D106: m | G106: Tank wall height, h = | H106: =VLOOKUP(C105,data!F$4:H$18,3,FALSE) -> 1.8 | I106: m
B107: Dome height, = | C107: =VLOOKUP(C105,data!F$4:G$18,2,FALSE) -> 0.7 | D107: m | F107: For Scheme # no: | G107: 1 | K107: =+K205 -> 485383
A108: S.N. | B108: Description | C108: No. | D108: Radius | E108: Length/Radius | F108: Breadth | G108: Height | H108: Qty. | I108: Unit | J108: Rate | K108: Amount
A109: 1 | B109: Site Clearance(L= d+2*2.0m,B=d+1m) | E109: =ROUND(C106+4,0) -> 8 | F109: =ROUND(C106+2,0) -> 6 | H109: =E109*F109 -> 48 | I109: m² | J109: =Rates!$F$7 -> 149.5 | K109: =H109*J109 -> 7176
A110: 2 | B110: Earthwork in excavation for foundation in hard soil
B111: Valve Chamber | E111: 1.7 | F111: 1.5 | G111: 1.3 | H111: =E111*F111*G111 -> 3.315
B112: Storage tank | C112: π | D112: =C106/2+0.05+0.75 -> 2.8 | E112: =D112 -> 2.8 | F112: - | G112: =H106+0.3-0.4 -> 1.7 | H112: =IF(C112="π",PI()*D112*E112*G112,IF(C112="2π",2*PI()*D112*E112*G112,"Change")) -> 41.871147
B113: (Q = p x R² x h, R = d/2+0.05+0.75
B114: Total | H114: =SUM(H111:H113) -> 45.186147 | I114: m³ | J114: =Rates!$F$9 -> 1480.63 | K114: =H114*J114 -> 66903.965
A115: 3 | B115: Earthwork in back filling with
...

Sheet vc-bpt
A1: Air Valve Chamber
A3: S.N. | B3: Description | C3: No. | D3: Length | E3: Breadth | F3: Height | G3: Quantity | H3: Unit | I3: Rate | J3: Amount
A4: 1 | B4: Site clearance | D4: 1.5 | E4: 1.5 | G4: =D4*E4 -> 2.25 | I4: =Rates!F7 -> 149.5 | J4: =I4*G4 -> 336.375
A5: 2 | B5: Earthwork in excavation for foundation in BMS
C6: 1 | D6: 1 | E6: 1 | F6: 1.1 | G6: =C6*D6*E6*F6 -> 1.1 | H6: m³ | I6: =Rates!F9 -> 1480.63 | J6: =I6*G6 -> 1628.693
A8: 3 | B8: Dry stone filling | C8: 1 | D8: 1 | E8: 1 | F8: 0.4 | G8: =C8*D8*E8*F8 -> 0.4 | H8: m³ | I8: =Rates!F19 -> 5523.35 | J8: =I8*G8 -> 2209.34
A10: 4 | B10: Stone masonry in 1:6 c-s mortar | C10: 1 | D10: 2.6 | E10: 0.35 | F10: 0.6 | G10: =C10*D10*E10*F10 -> 0.546 | H10: m³ | I10: =Rates!F25 -> 14917.39 | J10: =I10*G10 -> 8144.8949
A11: 5 | B11: Plain Cement Concrete (1:2:4)
B12: Slab cover | C12: 1 | D12: 1 | E12: 1 | F12: 0.08 | G12: =C12*D12*E12*F12 -> 0.08
B13: Deduction for manhole opening | C13: π | D13: 0.23 | E13: 0.23 | F13: 0.08 | G13: =-D13*E13*F13*PI() -> -0.01329522
B14: Manhole cover | C14: π | D14: 0.23 | E14: 0.23 | F14: 0.05 | G14: =D14*E14*F14*PI() -> 0.0083095126
B15: Total | G15: =SUM(G12:G14) -> 0.075014292 | H15: m³ | I15: =Rates!F32 -> 16022.87 | J15: =I15*G15 -> 1201.9443
A16: 6 | B16: Centering & Shuttering Works | C16: 1 | D16: 4 | E16: - | F16: 0.08 | G16: =C16*D16*F16 -> 0.32 | H16: m² | I16: =Rates!F40 -> 1322.68 | J16: =I16*G16 -> 423.2576
A17: 7 | B17: Selected material filling (stone Packing) | C17: 1 | D17: 1 | E17: 1 | F17: 0.25 | G17: =C17*D17*E17*F17 -> 0.25 | H17: m³ | I17: =Rates!F19 -> 5523.35 | J17: =I17*G17 -> 1380.8375
A19: 8 | B19: Standard manhole cover 45×45 cm with metal frame | G19: 1 | H19: no. | I19: =MR!$I$43*1.15 -> 1609.5975 | J19: =I19*G19 -> 1609.5975
A20: 9 | B20: Installation of pipes & fittings | G20: 1 | H20: job | I20: =Rates!F105 -> 600 | J20: =I20 -> 600
B22: Subtotal | J22: =SUM(J4:J20) -> 17534.94
B23: Add Value Added Tax | I23: ='Entry for Rates'!$F$114 -> 13 | J23: =I23*J22/100 -> 2279.5422
B24: Total Amount with VAT | I24: Rs. | J24: =+J23+J22 -> 19814.482
A26: Valve Chamber
A27: ='Entry for Rates'!F4 -> 0
B28: Inner dimension | C28: 1 | D28: m x | E28: 0.6 | F28: m
A30: S.N. | B30: Description | C30: No. | D30: Length | E30: Breadth | F30: Height | G30: Quantity | H30: Unit | I30: Rate | J30: Amount
A31: 1 | B31: Site Clearance | D31: 2 | E31: 2 | G31: =D31*E31 -> 4 | I31: =Rates!F7 -> 149.5 | J31: =I31*G31 -> 598
A33: 2 | B33: Earthwork in excavation for foundation
C34: 1 | D34: =$C$28+0.35*2 -> 1.7 | E34: =$E$28+0.35*2 -> 1.3 | F34: 1.3 | G34: =C34*D34*E34*F34 -> 2.873 | H34: m³ | I34: =Rates!F9 -> 1480.63 | J34: =I34*G34 -> 4253.85
A36: 3 | B36: Boulder soling | C36: 1 | D36: =$C$28+0.35*2 -> 1.7 | E36: =$E$28+0.35*2 -> 1.3 | F36: 0.15 | G36: =C36*D36*E36*F36 -> 0.3315 | H36: m³ | I36: =Rates!F19 -> 5523.35 | J36: =I36*G36 -> 1830.9905
A38: 4 | B38: Stone masonry in 1:6 c-s mortar | D38: =($C$28+2*0.35)*2+$E$28*2 -> 4.6 | E38: 0.35 | F38: 1 | G38: =D38*E38*F38 -> 1.61 | H38: m³ | I38: =Rates!F25 -> 14917.39 | J38: =I38*G38 -> 24016.998
A40: 5 | B40: Plain Cement Concrete (1:2:4)
B41: Cover slab | C41: 1 | D41: =D36 -> 1.7 | E41: =E36 -> 1.3 | F41: 0.1 | G41: =ROUND(C41*D41*E41*F41,2) -> 0.22
B42: Deduction for manhole | D42: 0.6 | E42: 0.6 | F42: =F41 -> 0.1 | G42: =-D42*E42*F42*PI() -> -0.11309734
B43: Manhole cover | D43: 0.6 | E43: 0.6 | F43: 0.05 | G43: =D43*E43*F43*PI() -> 0.056548668
B44: Total | G44: =SUM(G41:G43) -> 0.16345133 | H44: m³ | I44: =Rates!F32 -> 16022.87 | J44: =I44*G44 -> 2618.9594
A45: 6 | B45: Steel reinforcement
B46: 8 mm ø at 150 mm spacing bothways
B47: Longer span | C47: =ROUND(D41/0.15+1,0) -> 12 | D47: =E41 -> 1.3 | E47: 0.395 | G47: =+ROUND(C47*D47*E47,2) -> 6.16
B48: Shorter span | C48: =ROUND(E41/0.15+1,0) -> 10 | D48: =D41 -> 1.7 | E48: 0.395 | G48: =+ROUND(C48*D48*E48,2) -> 6.72
B49: Deduction for manhole opening | C49: 12 | D49: 0.45 | E49: 0.395 | G49: =-ROUND(C49*D49*E49,2) -> -2.13
B50: Total | G50: =SUM(G47:G49) -> 10.75 | H50: kg | I50: =Rates!F39 -> 125.35 | J50: =I50*G50 -> 1347.5125
A51: 7 | B51: Centering & Shuttering work for RCC
B52: Cover slab bottom | C52: 1 | D52: =C28 -> 1 | E52: =E28 -> 0.6 | F52: - | G52: =C52*D52*E52 -> 0.6
B53: Sides | C53: 1 | D53: =2*(D41+E41) -> 6 | E53: - | F53: =F41 -> 0.1 | G53: =C53*D53*F53 -> 0.6
B54: Deduction for manhole opening | C54: 1 | D54: 0.75 | E54: 0.75 | F54: - | G54: =-C54*D54*E54 -> -0.5625
G55: =SUM(G52:G54) -> 0.6375 | H55: m² | I55: =Rates!F40 -> 1322.68 | J55: =I55*G55 -> 843.2085
A57: 8 | B57: Standard manhole cover 60*60 cm with metal frame | G57: 1 | H57: no. | I57: =MR!$I$41*1.15 -> 2112.2625 | J57: =I57*G57 -> 2112.2625
A58: 9 | B58: Installation of pipes & fittings | G58: 1 | H58: job | I58: =Rates!F106 -> 800 | J58: =I58 -> 800
B60: Subtotal | J60: =SUM(J31:J59) -> 38421.781
B61: Add Value Added Tax | I61: ='Entry for Rates'!$F$114 -> 13 | J61: =I61*J60/100 -> 4994.8316
B62: Total Amount with VAT | I62: Rs. | J62: =+J61+J60 -> 43416.613
A66: BREAK PRESSURE CHAMBER
A67: ( Without valve chamber )
B69: Inner size of BPT portion: | C69: 0.8 | D69: x | E69: 0.8 | F69: Total height= | H69: 0.8
A71: S.N. | B71: Description | C71: No. | D71: Length | E71: Breadth | F71: Height | G71: Quantity | H71: Unit | I71: Rate | J71: Amount
A73: 1 | B73: Site clearance | D73: 2.5 | E73: 2.5 | G73: =D73*E73 -> 6.25 | H73: m² | I73: =Rates!F7 -> 149.5 | J73: =ROUND(G73*I73,2) -> 934.38
A74: 2 | B74: Earthwork in excavation
C75: 1 | D75: =+C69+0.45*2 -> 1.7 | E75: =+E69+0.45*2 -> 1.7 | F75: =H69-0.1 -> 0.7 | G75: =C75*D75*E75*F75 -> 2.023 | H75: m³ | I75: =Rates!F9 -> 1480.63 | J75: =ROUND(G75*I75,2) -> 2995.31
A77: 3 | B77: Boulder soling | C77: 1 | D77: =+C69+0.45*2 -> 1.7 | E77: =+E69+0.45*2 -> 1.7 | F77: 0.15 | G77: =C77*D77*E77*F77 -> 0.4335 | H77: m³ | I77: =Rates!F19 -> 5523.35 | J77: =ROUND(G77*I77,2) -> 2394.37
A78: 4 | B78: Plain Cement Concrete (1:2:4)
B79: in foundation | C79: 1 | D79: =+C69+0.45*2 -> 1.7 | E79: =+E69+0.45*2 -> 1.7 | F79: 0.1 | G79: =C79*D79*E79*F79 -> 0.289
B80: Pipe embeddment block | C80: 4 | D80: 0.45 | E80: 0.2 | F80: 0.2 | G80: =C80*D80*E80*F80 -> 0.072
B81: Cover slab | C81: 1 | D81: =+C69+0.45*2 -> 1.7 | E81: =+E69+0.45*2 -> 1.7 | F81: 0.1 | G81: =C81*D81*E81*F81 -> 0.289
B82: Deduct:
B83: -Manhole cover | C83: 1 | D83: 0.6 | E83: 0.6 | F83: 0.05 | G83: =-C83*D83*E83*F83 -> -0.018
B84: Total | G84: =SUM(G78:G83) -> 0.632 | H84: m³ | I84: =Rates!F32 -> 16022.87 | J84: =ROUND(G84*I84,2) -> 10126.45
A85: 5 | B85: Stone masonry work in 1:4 c-s mortar
C86: 1 | D86: =2*(C69+0.45*2+E69) -> 5 | E86: 0.45 | F86: =H69 -> 0.8 | G86: =C86*D86*E86*F86 -> 1.8
B87: Deduct for pipe embeddment block | C87: 4 | D87: 0.45 | E87: 0.2 | F87: 0.2 | G87: =-C87*D87*E87*F87 -> -0.072
B88: Total | G88: =SUM(G86:G87) -> 1.728 | H88: m³ | I88: =Rates!F24 -> 15619.64 | J88: =ROUND(G88*I88,2) -> 26990.74
A89: 6 | B89: Centering & shuttering works
B90: Bottom of cover slab | C90: 1 | D90: =C69 -> 0.8 | E90: =E69 -> 0.8 | G90: =D90*E90 -> 0.64
B91: -Outer edge of cover slab | C91: 1 | D91: =2*(E81+D81) -> 6.8 | F91: 0.1 | G91: =+D91*F91 -> 0.68
B92: Total | G92: =SUM(G90:G91) -> 1.32 | H92: m² | I92: =Rates!F40 -> 1322.68 | J92: =ROUND(G92*I92,2) -> 1745.94
A94: 7 | B94: Steel reinforcement (for cover slab)
B95: 8 mm ø @ 150 mm c/c bothways | C95: =ROUND(D81/0.15+1,0) -> 12 | D95: =E81 -> 1.7 | E95: 0.395 | G95: =C95*D95*E95 -> 8.058
C96: =ROUND(E81/0.15+1,0) -> 12 | D96: =D81 -> 1.7 | E96: 0.395 | G96: =C96*D96*E96 -> 8.058
B97: Deduct for man hole | C97: 8 | D97: 0.6 | E97: 0.395 | G97: =-C97*D97*E97 -> -1.896
B98: Total | G98: =SUM(G95:G97) -> 14.22 | H98: kg | I98: =Rates!F39 -> 125.35 | J98: =ROUND(G98*I98,2) -> 1782.48
A100: 8 | B100: 12.5 mm thick 1:4 c-s plaster
B101: floor | C101: 1 | D101: =C69 -> 0.8 | E101: =E69 -> 0.8 | G101: =ROUND(+C101*D101*E101,2) -> 0.64
B102: Inner sides of Walls | C102: 2 | D102: =D101 -> 0.8 | E102: - | F102: =H69 -> 0.8 | G102: =ROUND(+C102*D102*F102,2) -> 1.28
C103: 2 | D103: =E101 -> 0.8 | E103: - | F103: =H69 -> 0.8 | G103: =ROUND(+C103*D103*F103,2) -> 1.28
B104: Outer Portion of all walls above GL | C104: 1 | D104: =+D91 -> 6.8 | E104: - | F104: 0.35 | G104: =ROUND(+C104*D104*F104,2) -> 2.38
B105: Total | G105: =SUM(G100:G104) -> 5.58 | H105: m² | I105: =Rates!F60 -> 503.61 | J105: =ROUND(G105*I105,2) -> 2810.14
A106: 9 | B106: 3 mm 1:1 c-s punning
B107: -Inner side of BPT | G107: =G101+G102+G103 -> 3.2 | H107: m² | I107: =Rates!F67 -> 346.26 | J107: =ROUND(G107*I107,2) -> 1108.03
A109: 10 | B109: Standard manhole cover 60x60 cm ø with metal frame | G109: 1 | H109: set | I109: =MR!$I$41*1.15 -> 2112.2625 | J109: =ROUND(G109*I109,2) -> 2112.26
A111: 11 | B111: Installation of pipes and fittings | G111: 1 | H111: job | I111: =Rates!F104 -> 800 | J111: =ROUND(G111*I111,2) -> 800
B112: Subtotal | J112: =SUM(J72:J111) -> 53800.1
B113: Add Value Added Tax | I113: ='Entry for Rates'!$F$114 -> 13 | J113: =I113*J112/100 -> 6994.013
B114: Total Amount with VAT | I114: Rs. | J114: =+J113+J112 -> 60794.113

Sheet tools
A1: Procurement of Tools & Plants
F4: Total | G4: Unit Price | H4: Amount
A5: Sn | B5: Type of Tools | C5: Unit | D5: Qty | E5: Wt/Unit | F5: Wt | G5: 2072/73
E6: kg | F6: kg | G6: (Rs) | H6: (Rs)
A7: 1 | B7: Shovel | C7: Pc | D7: 10 | E7: 2.4 | F7: =D7*E7 -> 24 | G7: 535 | H7: =D7*G7 -> 5350
A8: =A7+1 -> 2 | B8: Pick Axe | C8: Pc | D8: 10 | E8: 5 | F8: =D8*E8 -> 50 | G8: 523 | H8: =D8*G8 -> 5230
A9: =A8+1 -> 3 | B9: Hoe | C9: Pc | D9: 10 | E9: 2 | F9: =D9*E9 -> 20 | G9: 330 | H9: =D9*G9 -> 3300
A10: 2 | B10: Crowbar 1" x 5" | C10: Pc | D10: 6 | E10: 3.5 | F10: =D10*E10 -> 21 | G10: 1660 | H10: =D10*G10 -> 9960
A11: =A10+1 -> 3 | B11: Sledge Hammer 10 lbs | C11: Pc | D11: 4 | E11: 4.55 | F11: =D11*E11 -> 18.2 | G11: 1160 | H11: =D11*G11 -> 4640
A12: =A11+1 -> 4 | B12: Stone Chisel 1" x 6" | C12: Pc | D12: 4 | E12: 1 | F12: =D12*E12 -> 4 | G12: 357 | H12: =D12*G12 -> 1428
A13: 3 | B13: Stone Chisel 1" x 12" | C13: Pc | D13: 4 | E13: 2 | F13: =D13*E13 -> 8 | G13: 620 | H13: =D13*G13 -> 2480
A14: =A13+1 -> 4 | B14: Tools Box with locking set | C14: Pc | D14: 4 | E14: 10 | F14: =D14*E14 -> 40 | G14: 1593 | H14: =D14*G14 -> 6372
A15: =A14+1 -> 5 | B15: Heating Plate (100 mm dia.) | C15: Pc | D15: 4 | E15: 2.5 | F15: =D15*E15 -> 10 | G15: 655.2 | H15: =D15*G15 -> 2620.8
A16: 4 | B16: Heating Plate (150 mm dia.) | C16: Pc | D16: 4 | E16: 3.5 | F16: =D16*E16 -> 14 | G16: 1542 | H16: =D16*G16 -> 6168
A17: =A16+1 -> 5 | B17: Teflon Cover (18cm x 18cm - bag size) | C17: Rm | D17: 1 | E17: 0.01 | F17: =D17*E17 -> 0.01 | G17: 450 | H17: =D17*G17 -> 450
A18: =A17+1 -> 6 | B18: Thermocrome Crayon | C18: Pc | D18: 1 | F18: =D18*E18 -> 0 | G18: 4338 | H18: =D18*G18 -> 4338
A19: 5 | B19: Blow Torch | C19: Pc | D19: 4 | E19: 1 | F19: =D19*E19 -> 4 | G19: 960 | H19: =D19*G19 -> 3840
A20: =A19+1 -> 6 | B20: Thread seal tape | C20: Pc | D20: 30 | F20: =D20*E20 -> 0 | G20: 15 | H20: =D20*G20 -> 450
A21: =A20+1 -> 7 | B21: Pipe Wrench 36" | C21: Pc | D21: 4 | E21: 3 | F21: =D21*E21 -> 12 | G21: 2956.8 | H21: =D21*G21 -> 11827.2
A22: 6 | B22: Pipe Wrench 24" | C22: Pc | D22: 4 | E22: 2.5 | F22: =D22*E22 -> 10 | G22: 1575 | H22: =D22*G22 -> 6300
A23: =A22+1 -> 7 | B23: Pipe Wrench 14" | C23: Pc | D23: 4 | E23: 1.5 | F23: =D23*E23 -> 6 | G23: 739.2 | H23: =D23*G23 -> 2956.8
A24: =A23+1 -> 8 | B24: Pipe Wrench 18" | C24: Pc | D24: 4 | E24: 2.4 | F24: =D24*E24 -> 9.6 | G24: 1050 | H24: =D24*G24 -> 4200
A25: 7 | B25: Pipe Wrench 12" | C25: Pc | D25: 4 | E25: 2.4 | F25: =D25*E25 -> 9.6 | G25: 513.6 | H25: =D25*G25 -> 2054.4
A26: =A25+1 -> 8 | B26: Hacksaw Frame | C26: Pc | D26: 4 | E26: 0.6 | F26: =D26*E26 -> 2.4 | G26: 175 | H26: =D26*G26 -> 700
A27: =A26+1 -> 9 | B27: Hacksaw Blade | C27: dz. | D27: 4 | E27: 0.5 | F27: =D27*E27 -> 2 | G27: 72 | H27: =D27*G27 -> 288
A28: 8 | B28: Adjustable Spanner 18" | C28: Pc | D28: 4 | E28: 0.4 | F28: =D28*E28 -> 1.6 | G28: 365 | H28: =D28*G28 -> 1460
A29: =A28+1 -> 9 | B29: Iron Pan (medium size) | C29: Pc | D29: 4 | E29: 1 | F29: =D29*E29 -> 4 | G29: 300 | H29: =D29*G29 -> 1200
A30: =A29+1 -> 10 | B30: Building Trowel | C30: Pc | D30: 4 | E30: 0.25 | F30: =D30*E30 -> 1 | G30: 90 | H30: =D30*G30 -> 360
A31: 9 | B31: Pointing Trowel | C31: Pc | D31: 4 | E31: 0.1 | F31: =D31*E31 -> 0.4 | G31: 75 | H31: =D31*G31 -> 300
A32: =A31+1 -> 10 | B32: Iron Brush | C32: Pc | D32: 4 | E32: 0.5 | F32: =D32*E32 -> 2 | G32: 84 | H32: =D32*G32 -> 336
A33: =A32+1 -> 11 | B33: Die Set ½"-1" with teeth | C33: Set | D33: 2 | E33: 0.8 | F33: =D33*E33 -> 1.6 | G33: 4113.6 | H33: =D33*G33 -> 8227.2
A34: 10 | B34: Die Set 1½"-2½" with teeth | C34: Set | D34: 2 | E34: 1 | F34: =D34*E34 -> 2 | G34: 8740.8 | H34: =D34*G34 -> 17481.6
A35: =A34+1 -> 11 | B35: Spare Die Teeth (½"-2½") | C35: Set | D35: 2 | E35: 0.5 | F35: =D35*E35 -> 1 | G35: 2887.2 | H35: =D35*G35 -> 5774.4
A36: =A35+1 -> 12 | B36: Spare Die Teeth (3"-4") | C36: Set | D36: 2 | E36: 0.5 | F36: =D36*E36 -> 1 | G36: 1645.2 | H36: =D36*G36 -> 3290.4
A37: 11 | B37: Die Teeth Oil with cane | C37: Lt. | D37: 2 | E37: 1.5 | F37: =D37*E37 -> 3 | G37: 164.4 | H37: =D37*G37 -> 328.8
A38: =A37+1 -> 12 | B38: Measuring Tape(fibre glass) 30 m. | C38: Pc | D38: 2 | E38: 0.75 | F38: =D38*E38 -> 1.5 | G38: 800 | H38: =D38*G38 -> 1600
E39: Sub-Total | F39: =SUM(F7:F38) -> 283.91 | H39: =SUM(H7:H38) -> 125311.6
B40: Add Value Added Tax | G40: 13 | H40: =H39*G40/100 -> 16290.508
B41: Total | G41: Rs. | H41: =H40+H39 -> 141602.11

Sheet FittingsSummary
A1: Scheme No: | C1: ='Salient feature'!D8 -> 1
A2: Scheme Name : | C2: Scheme 1
A3: Summary of structurewise fittings
A5: SN | B5: Description | C5: ItemCode | D5: Units | E5: BPT-01 | F5: IC-01 | G5: CoC-01 | H5: CoC-02 | I5: CoC-03 | J5: DiC-01 | K5: DiC-02 | L5: ='sum cost_All'!#REF! -> #REF! | M5: ='sum cost_All'!#REF! -> #REF! | N5: ='sum cost_All'!#REF! -> #REF! | O5: ='sum cost_All'!#REF! -> #REF! | P5: SINT-01 | Q5: SINT-02 | R5: SINT-03 | S5: S-VaC-J1 | T5: W-VaC-J5 | U5: A-VaC-J40 | V5: VaC-J50 | W5: VaC-J51 | X5: VaC-J57 | Y5: TotalQty | Z5: UnitWt(kg) | AA5: TotalWt(Kg) | AB5: Rate(Rs) | AC5: TotalAmount(Rs)
D6: Nos | E6: 6 | F6: 0 | G6: 2 | H6: 0 | I6: 0 | J6: 1 | K6: 0 | L6: 0 | M6: 0 | N6: 0 | O6: 2 | P6: 1 | Q6: 0 | R6: 0 | S6: 6 | T6: 6 | U6: 5 | V6: 0 | W6: 0 | X6: 0
A7: 1 | B7: Brass Union (15x20 mmØ) | C7: BU-15 | D7: no | P7: 2 | Y7: =SUMPRODUCT(E7:X7,$E$6:$X$6) -> 2 | Z7: 0.13 | AA7: =Y7*Z7 -> 0.26 | AB7: 455 | AC7: =Y7*AB7 -> 910
A8: 2 | B8: Brass Union (20x25 mmØ) | C8: BU-20 | D8: no | S8: 4 | T8: 4 | Y8: =SUMPRODUCT(E8:X8,$E$6:$X$6) -> 48 | Z8: 0.18 | AA8: =Y8*Z8 -> 8.64 | AB8: 484 | AC8: =Y8*AB8 -> 23232
A9: 3 | B9: Brass Union (25x32 mmØ) | C9: BU-25 | D9: no | E9: 5 | G9: 2 | T9: 4 | U9: 4 | Y9: =SUMPRODUCT(E9:X9,$E$6:$X$6) -> 78 | Z9: 0.25 | AA9: =Y9*Z9 -> 19.5 | AB9: 717 | AC9: =Y9*AB9 -> 55926
A10: 4 | B10: Brass Union (32x40 mmØ) | C10: BU-32 | D10: no | E10: 3 | S10: 6 | U10: 4 | Y10: =SUMPRODUCT(E10:X10,$E$6:$X$6) -> 74 | Z10: 0.37 | AA10: =Y10*Z10 -> 27.38 | AB10: 979 | AC10: =Y10*AB10 -> 72446
A11: 5 | B11: Brass Union (40x50 mmØ) | C11: BU-40 | D11: no | G11: 1 | S11: 2 | Y11: =SUMPRODUCT(E11:X11,$E$6:$X$6) -> 14 | Z11: 0.5 | AA11: =Y11*Z11 -> 7 | AB11: 1469 | AC11: =Y11*AB11 -> 20566
A12: 6 | B12: GI Blind flange set (100 mmØ) | C12: GBF-100 | D12: set | Y12: =SUMPRODUCT(E12:X12,$E$6:$X$6) -> 0 | Z12: 6 | AA12: =Y12*Z12 -> 0 | AB12: 2121 | AC12: =Y12*AB12 -> 0
A13: 7 | B13: GI Blind flange set (65 mmØ) | C13: GBF-65 | D13: set | Y13: =SUMPRODUCT(E13:X13,$E$6:$X$6) -> 0 | Z13: 3.75 | AA13: =Y13*Z13 -> 0 | AB13: 1532 | AC13: =Y13*AB13 -> 0
A14: 8 | B14: GI Elbow (100 mmØ) | C14: GEL-100 | D14: no | Y14: =SUMPRODUCT(E14:X14,$E$6:$X$6) -> 0 | Z14: 1.97 | AA14: =Y14*Z14 -> 0 | AB14: 1320 | AC14: =Y14*AB14 -> 0
A15: 9 | B15: GI Elbow (15 mmØ) | C15: GEL-15 | D15: no | O15: 4 | P15: 1 | Y15: =SUMPRODUCT(E15:X15,$E$6:$X$6) -> 9 | Z15: 0.1 | AA15: =Y15*Z15 -> 0.9 | AB15: 34 | AC15: =Y15*AB15 -> 306
A16: 10 | B16: GI Elbow (20 mmØ) | C16: GEL-20 | D16: no | Y16: =SUMPRODUCT(E16:X16,$E$6:$X$6) -> 0 | Z16: 0.2 | AA16: =Y16*Z16 -> 0 | AB16: 86 | AC16: =Y16*AB16 -> 0
A17: 11 | B17: GI Elbow (25 mmØ) | C17: GEL-25 | D17: no | E17: 6 | G17: 6 | Y17: =SUMPRODUCT(E17:X17,$E$6:$X$6) -> 48 | Z17: 0.2 | AA17: =Y17*Z17 -> 9.6 | AB17: 86 | AC17: =Y17*AB17 -> 4128
A18: 12 | B18: GI Elbow (32 mmØ) | C18: GEL-32 | D18: no | E18: 3 | Y18: =SUMPRODUCT(E18:X18,$E$6:$X$6) -> 18 | Z18: 0.3 | AA18: =Y18*Z18 -> 5.4 | AB18: 133 | AC18: =Y18*AB18 -> 2394
A19: 13 | B19: GI Elbow (40 mmØ) | C19: GEL-40 | D19: no | E19: 6 | O19: 3 | Y19: =SUMPRODUCT(E19:X19,$E$6:$X$6) -> 42 | Z19: 0.4 | AA19: =Y19*Z19 -> 16.8 | AB19: 184 | AC19: =Y19*AB19 -> 7728
A20: 14 | B20: GI Elbow (50 mmØ) | C20: GEL-50 | D20: no | E20: 3 | O20: 8 | Y20: =SUMPRODUCT(E20:X20,$E$6:$X$6) -> 34 | Z20: 0.68 | AA20: =Y20*Z20 -> 23.12 | AB20: 284 | AC20: =Y20*AB20 -> 9656
A21: 15 | B21: GI Elbow (63 mmØ) | C21: GEL-65 | D21: no | G21: 3 | J21: 3 | Y21: =SUMPRODUCT(E21:X21,$E$6:$X$6) -> 9 | Z21: 1.07 | AA21: =Y21*Z21 -> 9.63 | AB21: 539 | AC21: =Y21*AB21 -> 4851
A22: 16 | B22: GI Elbow (75 mmØ) | C22: GEL-80 | D22: no | G22: 2 | J22: 2 | Y22: =SUMPRODUCT(E22:X22,$E$6:$X$6) -> 6 | Z22: 1.46 | AA22: =Y22*Z22 -> 8.76 | AB22: 730 | AC22: =Y22*AB22 -> 4380
A23: 17 | B23: GI Equal Tee (100 mmØ) | C23: GET-100 | D23: no | Y23: =SUMPRODUCT(E23:X23,$E$6:$X$6) -> 0 | Z23: 2.25 | AA23: =Y23*Z23 -> 0 | AB23: 1528 | AC23: =Y23*AB23 -> 0
A24: 18 | B24: GI Equal Tee (15 mmØ) | C24: GET-15 | D24: no | E24: 6 | G24: 2 | J24: 1 | Y24: =SUMPRODUCT(E24:X24,$E$6:$X$6) -> 41 | Z24: 0.13 | AA24: =Y24*Z24 -> 5.33 | AB24: 54 | AC24: =Y24*AB24 -> 2214
A25: 19 | B25: GI Equal Tee (20 mmØ) | C25: GET-20 | D25: no | Y25: =SUMPRODUCT(E25:X25,$E$6:$X$6) -> 0 | Z25: 1.75 | AA25: =Y25*Z25 -> 0 | AB25: 78 | AC25: =Y25*AB25 -> 0
A26: 20 | B26: GI Equal Tee (25 mmØ) | C26: GET-25 | D26: no | G26: 2 | P26: 2 | Y26: =SUMPRODUCT(E26:X26,$E$6:$X$6) -> 6 | Z26: 1.75 | AA26: =Y26*Z26 -> 10.5 | AB26: 226 | AC26: =Y26*AB26 -> 1356
A27: 21 | B27: GI Equal Tee (32 mmØ) | C27: GET-32 | D27: no | Y27: =SUMPRODUCT(E27:X27,$E$6:$X$6) -> 0 | Z27: 1.75 | AA27: =Y27*Z27 -> 0 | AB27: 275 | AC27: =Y27*AB27 -> 0
A28: 22 | B28: GI Equal Tee (40 mmØ) | C28: GET-40 | D28: no | Y28: =SUMPRODUCT(E28:X28,$E$6:$X$6) -> 0 | Z28: 1.75 | AA28: =Y28*Z28 -> 0 | AB28: 431 | AC28: =Y28*AB28 -> 0
A29: 23 | B29: GI Equal Tee (80 mmØ) | C29: GET-80 | D29: no | Y29: =SUMPRODUCT(E29:X29,$E$6:$X$6) -> 0 | Z29: 1.75 | AA29: =Y29*Z29 -> 0 | AB29: 678 | AC29: =Y29*AB29 -> 0
A30: 24 | B30: GI Equal Tee(40 mmØ) | C30: GET-40 | D30: no | Y30: =SUMPRODUCT(E30:X30,$E$6:$X$6) -> 0 | Z30: 0.5 | AA30: =Y30*Z30 -> 0 | AB30: 220 | AC30: =Y30*AB30 -> 0
A31: 25 | B31: GI Nipple (100 mmØ) | C31: GNI-100 | D31: no | Y31: =SUMPRODUCT(E31:X31,$E$6:$X$6) -> 0 | Z31: 2.45 | AA31: =Y31*Z31 -> 0 | AB31: 697 | AC31: =Y31*AB31 -> 0
A32: 26 | B32: GI Nipple (15 mmØ) | C32: GNI-15 | D32: no | O32: 2 | P32: 2 | T32: 4 | Y32: =SUMPRODUCT(E32:X32,$E$6:$X$6) -> 30 | Z32: 0.13 | AA32: =Y32*Z32 -> 3.9 | AB32: 38 | AC32: =Y32*AB32 -> 1140
A33: 27 | B33: GI Nipple (20 mmØ) | C33: GNI-20 | D33: no | Y33: =SUMPRODUCT(E33:X33,$E$6:$X$6) -> 0 | Z33: 0.2 | AA33: =Y33*Z33 -> 0 | AB33: 62 | AC33: =Y33*AB33 -> 0
A34: 28 | B34: GI Nipple (25 mmØ) | C34: GNI-25 | D34: no | E34: 3 | G34: 4 | T34: 4 | U34: 4 | Y34: =SUMPRODUCT(E34:X34,$E$6:$X$6) -> 70 | Z34: 0.25 | AA34: =Y34*Z34 -> 17.5 | AB34: 82 | AC34: =Y34*AB34 -> 5740
A35: 29 | B35: GI Nipple (32 mmØ) | C35: GNI-32 | D35: no | E35: 2 | Y35: =SUMPRODUCT(E35:X35,$E$6:$X$6) -> 12 | Z35: 0.28 | AA35: =Y35*Z35 -> 3.36 | AB35: 117 | AC35: =Y35*AB35 -> 1404
A36: 30 | B36: GI Nipple (40 mmØ) | C36: GNI-40 | D36: no | E36: 1 | T36: 2 | U36: 4 | Y36: =SUMPRODUCT(E36:X36,$E$6:$X$6) -> 38 | Z36: 0.3 | AA36: =Y36*Z36 -> 11.4 | AB36: 182 | AC36: =Y36*AB36 -> 6916
A37: 31 | B37: GI Nipple (50 mmØ) | C37: GNI-50 | D37: no | E37: 1 | O37: 8 | T37: 2 | Y37: =SUMPRODUCT(E37:X37,$E$6:$X$6) -> 34 | Z37: 0.4 | AA37: =Y37*Z37 -> 13.6 | AB37: 241 | AC37: =Y37*AB37 -> 8194
A38: 32 | B38: GI Nipple (65 mmØ) | C38: GNI-63 | D38: no | U38: 2 | Y38: =SUMPRODUCT(E38:X38,$E$6:$X$6) -> 10 | Z38: 0.7 | AA38: =Y38*Z38 -> 7 | AB38: 315 | AC38: =Y38*AB38 -> 3150
A39: 33 | B39: GI Nipple (80 mmØ) | C39: GNI-80 | D39: no | J39: 1 | Y39: =SUMPRODUCT(E39:X39,$E$6:$X$6) -> 1 | Z39: 1.75 | AA39: =Y39*Z39 -> 1.75 | AB39: 525 | AC39: =Y39*AB39 -> 525
A40: 34 | B40: GI Pipe (100mm)-MC | C40: GPM-100 | D40: m | Y40: =SUMPRODUCT(E40:X40,$E$6:$X$6) -> 0 | Z40: 12.99 | AA40: =Y40*Z40 -> 0 | AB40: 1265 | AC40: =Y40*AB40 -> 0
A41: 35 | B41: GI Pipe (15mm)-MC | C41: GPM-15 | D41: m | E41: 8.7 | G41: 2.9 | J41: 1.45 | O41: 5.3 | Y41: =SUMPRODUCT(E41:X41,$E$6:$X$6) -> 70.05 | Z41: 1.28 | AA41: =Y41*Z41 -> 89.664 | AB41: 134 | AC41: =Y41*AB41 -> 9386.7
A42: 36 | B42: GI Pipe (20mm)-MC | C42: GPM-20 | D42: m | Y42: =SUMPRODUCT(E42:X42,$E$6:$X$6) -> 0 | Z42: 1.66 | AA42: =Y42*Z42 -> 0 | AB42: 170 | AC42: =Y42*AB42 -> 0
A43: 37 | B43: GI Pipe (25mm)-MC | C43: GPM-25 | D43: m | E43: 9.18 | G43: 3.85 | Y43: =SUMPRODUCT(E43:X43,$E$6:$X$6) -> 62.78 | Z43: 2.53 | AA43: =Y43*Z43 -> 158.8334 | AB43: 259 | AC43: =Y43*AB43 -> 16260.02
A44: 38 | B44: GI Pipe (32mm)-MC | C44: GPM-32 | D44: m | E44: 5.59 | Y44: =SUMPRODUCT(E44:X44,$E$6:$X$6) -> 33.54 | Z44: 3.28 | AA44: =Y44*Z44 -> 110.0112 | AB44: 337 | AC44: =Y44*AB44 -> 11302.98
A45: 39 | B45: GI Pipe (40mm)-MC | C45: GPM-40 | D45: m | E45: 5.18 | G45: 2 | J45: 2 | O45: 3.2 | Y45: =SUMPRODUCT(E45:X45,$E$6:$X$6) -> 43.48 | Z45: 3.79 | AA45: =Y45*Z45 -> 164.7892 | AB45: 387 | AC45: =Y45*AB45 -> 16826.76
A46: 40 | B46: GI Pipe (50mm)-MC | C46: GPM-50 | D46: m | E46: 6.89 | G46: 1.1 | O46: 16.7 | Y46: =SUMPRODUCT(E46:X46,$E$6:$X$6) -> 76.94 | Z46: 5.32 | AA46: =Y46*Z46 -> 409.3208 | AB46: 532 | AC46: =Y46*AB46 -> 40932.08
A47: 41 | B47: GI Pipe (63mm)-MC | C47: GPM-65 | D47: m | J47: 7.34 | Y47: =SUMPRODUCT(E47:X47,$E$6:$X$6) -> 7.34 | Z47: 6.35 | AA47: =Y47*Z47 -> 46.609 | AB47: 679 | AC47: =Y47*AB47 -> 4983.86
A48: 42 | B48: GI Pipe (75mm)-MC | C48: GPM-80 | D48: m | J48: 12.65 | Y48: =SUMPRODUCT(E48:X48,$E$6:$X$6) -> 12.65 | Z48: 8.85 | AA48: =Y48*Z48 -> 111.9525 | AB48: 845 | AC48: =Y48*AB48 -> 10689.25
A49: 43 | B49: GI Plug (40 mmØ) | C49: GIP-40 | D49: no | Y49: =SUMPRODUCT(E49:X49,$E$6:$X$6) -> 0 | Z49: 1 | AA49: =Y49*Z49 -> 0 | AB49: 66 | AC49: =Y49*AB49 -> 0
A50: 44 | B50: GI Plug (50 mmØ) | C50: GIP-50 | D50: no | Y50: =SUMPRODUCT(E50:X50,$E$6:$X$6) -> 0 | Z50: 1 | AA50: =Y50*Z50 -> 0 | AB50: 101 | AC50: =Y50*AB50 -> 0
A51: 45 | B51: GI Reducer Socket (100x40 mmØ) | C51: GRS-100x40 | D51: no | Y51: =SUMPRODUCT(E51:X51,$E$6:$X$6) -> 0 | Z51: 0.65 | AA51: =Y51*Z51 -> 0 | AB51: 895 | AC51: =Y51*AB51 -> 0
A52: 46 | B52: GI Reducer Socket (100x80 mmØ) | C52: GRS-100x80 | D52: no | Y52: =SUMPRODUCT(E52:X52,$E$6:$X$6) -> 0 | Z52: 0.95 | AA52: =Y52*Z52 -> 0 | AB52: 895 | AC52: =Y52*AB52 -> 0
A53: 47 | B53: GI Reducer Socket (125x100 mmØ) | C53: GRS-125x100 | D53: no | Y53: =SUMPRODUCT(E53:X53,$E$6:$X$6) -> 0 | Z53: 1 | AA53: =Y53*Z53 -> 0 | AB53: 895 | AC53: =Y53*AB53 -> 0
A54: 48 | B54: GI Reducer Socket (32x25 mmØ) | C54: GRS-32x25 | D54: no | Y54: =SUMPRODUCT(E54:X54,$E$6:$X$6) -> 0 | Z54: 0.65 | AA54: =Y54*Z54 -> 0 | AB54: 108 | AC54: =Y54*AB54 -> 0
A55: 49 | B55: GI Reducer Socket (40x32 mmØ) | C55: GRS-40x32 | D55: no | Y55: =SUMPRODUCT(E55:X55,$E$6:$X$6) -> 0 | Z55: 0.65 | AA55: =Y55*Z55 -> 0 | AB55: 134 | AC55: =Y55*AB55 -> 0
A56: 50 | B56: GI Reducer Socket (50x40 mmØ) | C56: GRS-50x40 | D56: no | Y56: =SUMPRODUCT(E56:X56,$E$6:$X$6) -> 0 | Z56: 0.65 | AA56: =Y56*Z56 -> 0 | AB56: 224 | AC56: =Y56*AB56 -> 0
A57: 51 | B57: GI Reducer Socket (65x50 mmØ) | C57: GRS-65x50 | D57: no | Y57: =SUMPRODUCT(E57:X57,$E$6:$X$6) -> 0 | Z57: 0.65 | AA57: =Y57*Z57 -> 0 | AB57: 366 | AC57: =Y57*AB57 -> 0
A58: 52 | B58: GI Reducer Socket (80x40 mmØ) | C58: GRS-80x40 | D58: no | Y58: =SUMPRODUCT(E58:X58,$E$6:$X$6) -> 0 | Z58: 0.65 | AA58: =Y58*Z58 -> 0 | AB58: 895 | AC58: =Y58*AB58 -> 0
A59: 53 | B59: GI Socket 100 mmØ | C59: GS-100 | D59: no | Y59: =SUMPRODUCT(E59:X59,$E$6:$X$6) -> 0 | Z59: 1.5 | AA59: =Y59*Z59 -> 0 | AB59: 782 | AC59: =Y59*AB59 -> 0
A60: 54 | B60: GI Socket 15 mmØ | C60: GS-15 | D60: no | P60: 1 | Y60: =SUMPRODUCT(E60:X60,$E$6:$X$6) -> 1 | Z60: 0.08 | AA60: =Y60*Z60 -> 0.08 | AB60: 30 | AC60: =Y60*AB60 -> 30
A61: 55 | B61: GI Socket 25 mmØ | C61: GS-25 | D61: no | Y61: =SUMPRODUCT(E61:X61,$E$6:$X$6) -> 0 | Z61: 0.15 | AA61: =Y61*Z61 -> 0 | AB61: 62 | AC61: =Y61*AB61 -> 0
A62: 56 | B62: GI Socket 40 mmØ | C62: GS-40 | D62: no | Y62: =SUMPRODUCT(E62:X62,$E$6:$X$6) -> 0 | Z62: 0.25 | AA62: =Y62*Z62 -> 0 | AB62: 118 | AC62: =Y62*AB62 -> 0
A63: 57 | B63: GI Socket 50 mmØ | C63: GS-50 | D63: no | Y63: =SUMPRODUCT(E63:X63,$E$6:$X$6) -> 0 | Z63: 0.5 | AA63: =Y63*Z63 -> 0 | AB63: 197 | AC63: =Y63*AB63 -> 0
A64: 58 | B64: GI Socket 75 mmØ | C64: GS-80 | D64: no | J64: 1 | Y64: =SUMPRODUCT(E64:X64,$E$6:$X$6) -> 1 | Z64: 1.13 | AA64: =Y64*Z64 -> 1.13 | AB64: 483 | AC64: =Y64*AB64 -> 483
A65: 59 | B65: GI Unequal Tee (100x15 mmØ) | C65: GUT-100x15 | D65: no | Y65: =SUMPRODUCT(E65:X65,$E$6:$X$6) -> 0 | Z65: 1.5 | AA65: =Y65*Z65 -> 0 | AB65: 1500 | AC65: =Y65*AB65 -> 0
A66: 60 | B66: GI Unequal Tee (100x25 mmØ) | C66: GUT-100x25 | D66: no | Y66: =SUMPRODUCT(E66:X66,$E$6:$X$6) -> 0 | Z66: 1.6 | AA66: =Y66*Z66 -> 0 | AB66: 1500 | AC66: =Y66*AB66 -> 0
A67: 61 | B67: GI Unequal Tee (100x40 mmØ) | C67: GUT-100x40 | D67: no | Y67: =SUMPRODUCT(E67:X67,$E$6:$X$6) -> 0 | Z67: 1.7 | AA67: =Y67*Z67 -> 0 | AB67: 1500 | AC67: =Y67*AB67 -> 0
A68: 62 | B68: GI Unequal Tee (100x50 mmØ) | C68: GUT-100x50 | D68: no | Y68: =SUMPRODUCT(E68:X68,$E$6:$X$6) -> 0 | Z68: 1.75 | AA68: =Y68*Z68 -> 0 | AB68: 1500 | AC68: =Y68*AB68 -> 0
A69: 63 | B69: GI Unequal Tee (100x80 mmØ) | C69: GUT-100x80 | D69: no | Y69: =SUMPRODUCT(E69:X69,$E$6:$X$6) -> 0 | Z69: 1.95 | AA69: =Y69*Z69 -> 0 | AB69: 1500 | AC69: =Y69*AB69 -> 0
A70: 64 | B70: GI Unequal Tee (25x15 mmØ) | C70: GUT-25x15 | D70: no | E70: 3 | U70: 2 | Y70: =SUMPRODUCT(E70:X70,$E$6:$X$6) -> 28 | Z70: 0.23 | AA70: =Y70*Z70 -> 6.44 | AB70: 140 | AC70: =Y70*AB70 -> 3920
A71: 65 | B71: GI Unequal Tee (32x15 mmØ) | C71: GUT-32x15 | D71: no | E71: 2 | Y71: =SUMPRODUCT(E71:X71,$E$6:$X$6) -> 12 | Z71: 0.23 | AA71: =Y71*Z71 -> 2.76 | AB71: 209 | AC71: =Y71*AB71 -> 2508
A72: 66 | B72: GI Unequal Tee (40x15 mmØ) | C72: GUT-40x15 | D72: no | E72: 1 | G72: 1 | U72: 2 | Y72: =SUMPRODUCT(E72:X72,$E$6:$X$6) -> 18 | Z72: 0.4 | AA72: =Y72*Z72 -> 7.2 | AB72: 278 | AC72: =Y72*AB72 -> 5004
A73: 67 | B73: GI Unequal Tee (50x15 mmØ) | C73: GUT-50x15 | D73: no | E73: 1 | O73: 2 | Y73: =SUMPRODUCT(E73:X73,$E$6:$X$6) -> 10 | Z73: 0.5 | AA73: =Y73*Z73 -> 5 | AB73: 439 | AC73: =Y73*AB73 -> 4390
A74: 68 | B74: GI Unequal Tee (80x15 mmØ) | C74: GUT-80x15 | D74: no | G74: 1 | Y74: =SUMPRODUCT(E74:X74,$E$6:$X$6) -> 2 | Z74: 0.85 | AA74: =Y74*Z74 -> 1.7 | AB74: 1216 | AC74: =Y74*AB74 -> 2432
A75: 69 | B75: GI Unequal Tee (80x20 mmØ) | C75: GUT-80x20 | D75: no | U75: 1 | Y75: =SUMPRODUCT(E75:X75,$E$6:$X$6) -> 5 | Z75: 0.9 | AA75: =Y75*Z75 -> 4.5 | AB75: 1216 | AC75: =Y75*AB75 -> 6080
A76: 70 | B76: GI Unequal Tee (80x40 mmØ) | C76: GUT-80x40 | D76: no | Y76: =SUMPRODUCT(E76:X76,$E$6:$X$6) -> 0 | Z76: 1.05 | AA76: =Y76*Z76 -> 0 | AB76: 1216 | AC76: =Y76*AB76 -> 0
A77: 71 | B77: GI Unequal Tee (80x50 mmØ) | C77: GUT-80x50 | D77: no | Y77: =SUMPRODUCT(E77:X77,$E$6:$X$6) -> 0 | Z77: 1.1 | AA77: =Y77*Z77 -> 0 | AB77: 1216 | AC77: =Y77*AB77 -> 0
A78: 72 | B78: GI Union (15 mmØ) | C78: GUN-15 | D78: no | O78: 2 | Y78: =SUMPRODUCT(E78:X78,$E$6:$X$6) -> 4 | Z78: 0.22 | AA78: =Y78*Z78 -> 0.88 | AB78: 92 | AC78: =Y78*AB78 -> 368
A79: 73 | B79: GI Union (20 mmØ) | C79: GUN-20 | D79: no | Y79: =SUMPRODUCT(E79:X79,$E$6:$X$6) -> 0 | Z79: 0.26 | AA79: =Y79*Z79 -> 0 | AB79: 118 | AC79: =Y79*AB79 -> 0
A80: 74 | B80: GI Union (25 mmØ) | C80: GUN-25 | D80: no | E80: 3 | Y80: =SUMPRODUCT(E80:X80,$E$6:$X$6) -> 18 | Z80: 0.3 | AA80: =Y80*Z80 -> 5.4 | AB80: 170 | AC80: =Y80*AB80 -> 3060
A81: 75 | B81: GI Union (32 mmØ) | C81: GUN-32 | D81: no | E81: 2 | Y81: =SUMPRODUCT(E81:X81,$E$6:$X$6) -> 12 | Z81: 0.5 | AA81: =Y81*Z81 -> 6 | AB81: 270 | AC81: =Y81*AB81 -> 3240
A82: 76 | B82: GI Union (40 mmØ) | C82: GUN-40 | D82: no | E82: 1 | Y82: =SUMPRODUCT(E82:X82,$E$6:$X$6) -> 6 | Z82: 0.65 | AA82: =Y82*Z82 -> 3.9 | AB82: 328 | AC82: =Y82*AB82 -> 1968
A83: 77 | B83: GI Union (50 mmØ) | C83: GUN-50 | D83: no | E83: 1 | O83: 2 | Y83: =SUMPRODUCT(E83:X83,$E$6:$X$6) -> 10 | Z83: 1.13 | AA83: =Y83*Z83 -> 11.3 | AB83: 501 | AC83: =Y83*AB83 -> 5010
A84: 78 | B84: GI Union (80 mmØ) | C84: GUN-80 | D84: no | J84: 1 | Y84: =SUMPRODUCT(E84:X84,$E$6:$X$6) -> 1 | Z84: 2.38 | AA84: =Y84*Z84 -> 2.38 | AB84: 1309 | AC84: =Y84*AB84 -> 1309
A85: 79 | B85: GI-GI flange set (100 mmØ) | C85: GFL-100 | D85: set | Y85: =SUMPRODUCT(E85:X85,$E$6:$X$6) -> 0 | Z85: 3.75 | AA85: =Y85*Z85 -> 0 | AB85: 2121 | AC85: =Y85*AB85 -> 0
A86: 80 | B86: GI-HDP flange set (100x125 mmØ) | C86: GHF-100 | D86: set | Y86: =SUMPRODUCT(E86:X86,$E$6:$X$6) -> 0 | Z86: 3.75 | AA86: =Y86*Z86 -> 0 | AB86: 1768 | AC86: =Y86*AB86 -> 0
A87: 81 | B87: GI-HDP flange set (40x50 mmØ) | C87: GHF-50 | D87: set | E87: 3 | O87: 1 | T87: 2 | U87: 2 | Y87: =SUMPRODUCT(E87:X87,$E$6:$X$6) -> 42 | Z87: 2.4 | AA87: =Y87*Z87 -> 100.8 | AB87: 1196 | AC87: =Y87*AB87 -> 50232
A88: 82 | B88: GI-HDP flange set (50x63 mmØ) | C88: GHF-63 | D88: set | E88: 2 | J88: 1 | O88: 2 | T88: 2 | Y88: =SUMPRODUCT(E88:X88,$E$6:$X$6) -> 29 | Z88: 2.4 | AA88: =Y88*Z88 -> 69.6 | AB88: 1800 | AC88: =Y88*AB88 -> 52200
A89: 83 | B89: GI-HDP flange set (80x90 mmØ) | C89: GHF-80 | D89: set | J89: 1 | Y89: =SUMPRODUCT(E89:X89,$E$6:$X$6) -> 1 | Z89: 3.25 | AA89: =Y89*Z89 -> 3.25 | AB89: 1795 | AC89: =Y89*AB89 -> 1795
A90: 84 | B90: GI-HDP flange set (75x63 mmØ) | C90: GHF-75 | D90: no | U90: 2 | Y90: =SUMPRODUCT(E90:X90,$E$6:$X$6) -> 10 | Z90: 2.7 | AA90: =Y90*Z90 -> 27 | AB90: 2050 | AC90: =Y90*AB90 -> 20500
A91: 85 | B91: GM Gate Valve (100 mmØ) | C91: GMGAV-100 | D91: no | Y91: =SUMPRODUCT(E91:X91,$E$6:$X$6) -> 0 | Z91: 5.44 | AA91: =Y91*Z91 -> 0 | AB91: 28000 | AC91: =Y91*AB91 -> 0
A92: 86 | B92: GM Gate Valve (15 mmØ) | C92: GMGAV-15 | D92: no | Y92: =SUMPRODUCT(E92:X92,$E$6:$X$6) -> 0 | Z92: 0.65 | AA92: =Y92*Z92 -> 0 | AB92: 832 | AC92: =Y92*AB92 -> 0
A93: 87 | B93: GM Gate Valve (20 mmØ) | C93: GMGAV-20 | D93: no | S93: 2 | T93: 2 | Y93: =SUMPRODUCT(E93:X93,$E$6:$X$6) -> 24 | Z93: 1.2 | AA93: =Y93*Z93 -> 28.8 | AB93: 1143 | AC93: =Y93*AB93 -> 27432
A94: 88 | B94: GM Gate Valve (25 mmØ) | C94: GMGAV-25 | D94: no | G94: 2 | S94: 3 | T94: 2 | Y94: =SUMPRODUCT(E94:X94,$E$6:$X$6) -> 34 | Z94: 1.67 | AA94: =Y94*Z94 -> 56.78 | AB94: 1744 | AC94: =Y94*AB94 -> 59296
A95: 89 | B95: GM Gate Valve (32 mmØ) | C95: GMGAV-32 | D95: no | S95: 1 | Y95: =SUMPRODUCT(E95:X95,$E$6:$X$6) -> 6 | Z95: 1.8 | AA95: =Y95*Z95 -> 10.8 | AB95: 2624 | AC95: =Y95*AB95 -> 15744
A96: 90 | B96: GM Gate Valve (40 mmØ) | C96: GMGAV-40 | D96: no | T96: 1 | Y96: =SUMPRODUCT(E96:X96,$E$6:$X$6) -> 6 | Z96: 1.9 | AA96: =Y96*Z96 -> 11.4 | AB96: 3537 | AC96: =Y96*AB96 -> 21222
A97: 91 | B97: GM Gate Valve (50 mmØ) | C97: GMGAV-50 | D97: no | O97: 4 | T97: 1 | Y97: =SUMPRODUCT(E97:X97,$E$6:$X$6) -> 14 | Z97: 2.7 | AA97: =Y97*Z97 -> 37.8 | AB97: 5500 | AC97: =Y97*AB97 -> 77000
A98: 92 | B98: GM Gate Valve (65 mmØ) | C98: BGAV-65 | J98: `1 | Y98: =SUMPRODUCT(E98:X98,$E$6:$X$6) -> 0 | Z98: 3.1 | AA98: =Y98*Z98 -> 0 | AB98: 7299 | AC98: =Y98*AB98 -> 0
A99: 93 | B99: GM Gate Valve (80 mmØ) | C99: GMGAV-80 | D99: no | Y99: =SUMPRODUCT(E99:X99,$E$6:$X$6) -> 0 | Z99: 4.25 | AA99: =Y99*Z99 -> 0 | AB99: 16000 | AC99: =Y99*AB99 -> 0
A100: 94 | B100: GM Globe Valve (100 mmØ) | C100: GMGLV-100 | D100: no | Y100: =SUMPRODUCT(E100:X100,$E$6:$X$6) -> 0 | Z100: 1 | AA100: =Y100*Z100 -> 0 | AB100: 28293 | AC100: =Y100*AB100 -> 0
A101: 95 | B101: GM Globe Valve (15 mmØ) | C101: GMGLV-15 | D101: no | Y101: =SUMPRODUCT(E101:X101,$E$6:$X$6) -> 0 | Z101: 0.88 | AA101: =Y101*Z101 -> 0 | AB101: 761 | AC101: =Y101*AB101 -> 0
...

Sheet conp
A1: Shankharapur Municipality
A2: Office of Municipal Executive
A3: Sankhu, Kathmandu
A4: Detail Estimated Sheet
A5: Project:- Sankhu Khanepaani
A6: Location:- Shankharapur Municipality-06,07
A8: S.N. | B8: Description of work | C8: Quantity | D8: Unit | E8: Rate | F8: Amount | G8: Quantity | H8: Amount | I8: Difference | J8: Remarks
A9: 1 | B9: Earthworks in excavation in hard soil as per standard specification | C9: 164.48 | D9: m3 | E9: 300 | F9: =E9*C9 -> 49344 | G9: ='Detail Measurement'!G24 -> 80.463825 | H9: =G9*E9 -> 24139.148 | I9: =H9-F9 -> -25204.852
A10: 2 | B10: Backfilling with Hard Soil as per standard specifications all complete | C10: 63.95 | D10: m3 | E10: 80 | F10: =E10*C10 -> 5116 | G10: ='Detail Measurement'!G28 -> 0 | H10: =G10*E10 -> 0 | I10: =H10-F10 -> -5116
A11: 3 | B11: Dry Stone Soling in foundation in perfect line and level all complete | C11: 45.68 | D11: m3 | E11: 4000 | F11: =E11*C11 -> 182720 | G11: ='Detail Measurement'!G39 -> 27.00825 | H11: =G11*E11 -> 108033 | I11: =H11-F11 -> -74687
A12: 4 | B12: Providing and laying of 1:2:4 PCC as per drawing and Standard specifications all complete | C12: 25.69 | D12: m3 | E12: 9000 | F12: =E12*C12 -> 231210 | G12: ='Detail Measurement'!G52 -> 15.56925 | H12: =G12*E12 -> 140123.25 | I12: =H12-F12 -> -91086.75
A13: 5 | B13: Providing Plaster works 1:4 , 12.5mm with 3mm punning all complete as per standard specifications | C13: 416.71 | D13: m2 | E13: 400 | F13: =E13*C13 -> 166684 | G13: ='Detail Measurement'!G59 -> 22.2065 | H13: =G13*E13 -> 8882.6 | I13: =H13-F13 -> -157801.4
A14: 6 | B14: Providing of Form work for concrete work in shear wall,etc as per standard norms and specifications all complete | C14: 326.86 | D14: m2 | E14: 750 | F14: =E14*C14 -> 245145 | G14: ='Detail Measurement'!G67 -> 323.2655 | H14: =G14*E14 -> 242449.13 | I14: =H14-F14 -> -2695.875
A15: 7 | B15: PCC for RCC works in CSA 1:1.5:3 (ढलानको कार्य) with water proofing chemical all complete in water tank and slab cover | C15: 212.13 | D15: m3 | E15: 12000 | F15: =E15*C15 -> 2545560 | G15: ='Detail Measurement'!G96 -> 52.91553 | H15: =G15*E15 -> 634986.36 | I15: =H15-F15 -> -1910573.6
A16: 8 | B16: Cutting , bending and laying of Reinforcement works FE-500 as per given drawing and standard specifications all complete | C16: 9324.57 | D16: kg | E16: 105 | F16: =E16*C16 -> 979079.85 | G16: ='Detail Measurement'!G108 -> 3508.7322 | H16: =G16*E16 -> 368416.88 | I16: =H16-F16 -> -610662.97
A17: 9 | B17: Random Rubble Stone Masonry in C/S 1:4 including weep holes in perfect line and level with proper curing all complete. | C17: 259.1 | D17: m3 | E17: 5000 | F17: =E17*C17 -> 1295500 | G17: ='Detail Measurement'!G118 -> 97.89435 | H17: =G17*E17 -> 489471.75 | I17: =H17-F17 -> -806028.25
A18: 11 | B18: Supply and fitting of Rectangular 24"x24" (50 kg) C.I. tank manhole Cover locking types for burkamala Intake | C18: 2 | D18: Nos | E18: 5000 | F18: =E18*C18 -> 10000 | G18: ='Detail Measurement'!G121 -> 2 | H18: =G18*E18 -> 10000 | I18: =H18-F18 -> 0
A19: 12 | B19: Gabion Works: Gabion Preparation, mesh forming etc. (size 2mx1mx1m) | C19: 48 | D19: m3 | E19: 2500 | F19: =E19*C19 -> 120000 | G19: ='Detail Measurement'!G123 -> 38 | H19: =G19*E19 -> 95000 | I19: =H19-F19 -> -25000
A20: 13 | B20: Gabion Works: Filling of gabion box with stones | C20: 48 | D20: m3 | E20: 2500 | F20: =E20*C20 -> 120000 | G20: ='Detail Measurement'!G125 -> 38 | H20: =G20*E20 -> 95000 | I20: =H20-F20 -> -25000
F21: =SUM(F9:F20) -> 5950358.8 | H21: =SUM(H9:H20) -> 2216502.1 | I21: =H21-F21 -> -3733856.7
F22: =F21*0.13 -> 773546.65 | H22: =H21*0.13 -> 288145.28
F23: =SUM(F21:F22) -> 6723905.5 | H23: =SUM(H21:H22) -> 2504647.4
A24: 14 | B24: Project Information Board | C24: 1 | D24: ps | E24: =ABSTRACT!E24 -> 5000 | F24: =E24*C24 -> 5000 | G24: ='Estimate '!G94 -> 1 | H24: =E24 -> 5000
A25: 15 | B25: Lab Test Report | C25: 1 | D25: ps | E25: =ABSTRACT!E25 -> 20000 | F25: =E25*C25 -> 20000 | G25: ='Estimate '!G96 -> 1 | H25: =E25 -> 20000
A26: 16 | B26: Insurance | C26: 1 | D26: ps | E26: =ABSTRACT!E26 -> 20000 | F26: =E26*C26 -> 20000 | G26: ='Estimate '!G98 -> 1 | H26: =E26 -> 20000
A27: 17 | B27: Other necessary fittings as required on site | C27: 1 | D27: ps | E27: =ABSTRACT!E27 -> 100000 | F27: =E27*C27 -> 100000 | G27: ='Estimate '!G100 -> 1 | H27: =E27 -> 100000
B28: Total with VAT and PS | F28: =SUM(F23:F27) -> 6868905.5 | H28: =SUM(H23:H27) -> 2649647.4
B29: Contingencies 3% | F29: =F21*0.03 -> 178510.77 | H29: =H21*0.03 -> 66495.063
B30: Grand Total | F30: =SUM(F28:F29) -> 7047416.3 | H30: =SUM(H23:H29) -> 5365789.8

Sheet Sheet5
A1: Shankharapur Municipality
A2: Office of Municipal Executive
A3: Sankhu, Kathmandu
A4: First Running Bill
B6: योजनाको नामः | C6: Sankhu Khanepani | J6: बिलको क्रम सङ्ख्याः | L6: 1
B7: योजना कार्यान्वयन हुने स्थानः | C7: shankharapur-6,7,4 | J7: कार्य आदेश मितिः | L7: 65356
B8: ठेकदारको नामः | C8: Consolidated Builders and Engineers Pvt. Ltd., lalitpur | J8: काम सम्पन्न गर्नु पर्ने मितिः | L8: 65449
B9: ठेक्का पट्टाको सङ्केतः | C9: SMO/078/79/56 | J9: म्याद थप/भेरिएसन मितिः
B10: नापी किताब नं | J10: काम सम्पन्न भएको मितिः | L10: June 20 2022
A12: Item.No | B12: Description of work | C12: Unit | D12: सम्झौता बमोजिम | G12: हाल भएको काम | I12: अगिल्लो बिलमा भएको काम | K12: हाल सम्म भएको काम | M12: बाकि काम
D13: परिमाण | E13: दर | F13: रकम | G13: =D13 -> परिमाण | H13: =F13 -> रकम | I13: =G13 -> परिमाण | J13: =H13 -> रकम | K13: परिमाण | L13: रकम
A14: 1 | B14: Earthworks in excavation in hard soil as per standard specification | C14: =conp!D9 -> m3 | D14: =conp!C9 -> 164.48 | E14: =conp!E9 -> 300 | F14: =E14*D14 -> 49344 | G14: =conp!G9 -> 80.463825 | H14: =G14*E14 -> 24139.148 | K14: =I14+G14 -> 80.463825 | L14: =H14+J14 -> 24139.148 | M14: =K14-D14 -> -84.016175
A15: 2 | B15: Backfilling with Hard Soil as per standard specifications all complete | C15: =conp!D10 -> m3 | D15: =conp!C10 -> 63.95 | E15: =conp!E10 -> 80 | F15: =E15*D15 -> 5116 | G15: =conp!G10 -> 0 | H15: =G15*E15 -> 0 | K15: =I15+G15 -> 0 | L15: =H15+J15 -> 0 | M15: =K15-D15 -> -63.95
A16: 3 | B16: Dry Stone Soling in foundation in perfect line and level all complete | C16: =conp!D11 -> m3 | D16: =conp!C11 -> 45.68 | E16: =conp!E11 -> 4000 | F16: =E16*D16 -> 182720 | G16: =conp!G11 -> 27.00825 | H16: =G16*E16 -> 108033 | K16: =I16+G16 -> 27.00825 | L16: =H16+J16 -> 108033 | M16: =K16-D16 -> -18.67175
A17: 4 | B17: Providing and laying of 1:2:4 PCC as per drawing and Standard specifications all complete | C17: =conp!D12 -> m3 | D17: =conp!C12 -> 25.69 | E17: =conp!E12 -> 9000 | F17: =E17*D17 -> 231210 | G17: =conp!G12 -> 15.56925 | H17: =G17*E17 -> 140123.25 | K17: =I17+G17 -> 15.56925 | L17: =H17+J17 -> 140123.25 | M17: =K17-D17 -> -10.12075
A18: 5 | B18: Providing Plaster works 1:4 , 12.5mm with 3mm punning all complete as per standard specifications | C18: =conp!D13 -> m2 | D18: =conp!C13 -> 416.71 | E18: =conp!E13 -> 400 | F18: =E18*D18 -> 166684 | G18: =conp!G13 -> 22.2065 | H18: =G18*E18 -> 8882.6 | K18: =I18+G18 -> 22.2065 | L18: =H18+J18 -> 8882.6 | M18: =K18-D18 -> -394.5035
A19: 6 | B19: Providing of Form work for concrete work in shear wall,etc as per standard norms and specifications all complete | C19: =conp!D14 -> m2 | D19: =conp!C14 -> 326.86 | E19: =conp!E14 -> 750 | F19: =E19*D19 -> 245145 | G19: =conp!G14 -> 323.2655 | H19: =G19*E19 -> 242449.13 | K19: =I19+G19 -> 323.2655 | L19: =H19+J19 -> 242449.13 | M19: =K19-D19 -> -3.5945
A20: 7 | B20: PCC for RCC works in CSA 1:1.5:3 (ढलानको कार्य) with water proofing chemical all complete in water tank and slab cover | C20: =conp!D15 -> m3 | D20: =conp!C15 -> 212.13 | E20: =conp!E15 -> 12000 | F20: =E20*D20 -> 2545560 | G20: =conp!G15 -> 52.91553 | H20: =G20*E20 -> 634986.36 | K20: =I20+G20 -> 52.91553 | L20: =H20+J20 -> 634986.36 | M20: =K20-D20 -> -159.21447
A21: 8 | B21: Cutting , bending and laying of Reinforcement works FE-500 as per given drawing and standard specifications all complete | C21: =conp!D16 -> kg | D21: =conp!C16 -> 9324.57 | E21: =conp!E16 -> 105 | F21: =E21*D21 -> 979079.85 | G21: =conp!G16 -> 3508.7322 | H21: =G21*E21 -> 368416.88 | K21: =I21+G21 -> 3508.7322 | L21: =H21+J21 -> 368416.88 | M21: =K21-D21 -> -5815.8378
A22: 9 | B22: Random Rubble Stone Masonry in C/S 1:4 including weep holes in perfect line and level with proper curing all complete. | C22: =conp!D17 -> m3 | D22: =conp!C17 -> 259.1 | E22: =conp!E17 -> 5000 | F22: =E22*D22 -> 1295500 | G22: =conp!G17 -> 97.89435 | H22: =G22*E22 -> 489471.75 | K22: =I22+G22 -> 97.89435 | L22: =H22+J22 -> 489471.75 | M22: =K22-D22 -> -161.20565
A23: 11 | B23: Supply and fitting of Rectangular 24"x24" (50 kg) C.I. tank manhole Cover locking types for burkamala Intake | C23: =conp!D18 -> Nos | D23: =conp!C18 -> 2 | E23: =conp!E18 -> 5000 | F23: =E23*D23 -> 10000 | G23: =conp!G18 -> 2 | H23: =G23*E23 -> 10000 | K23: =I23+G23 -> 2 | L23: =H23+J23 -> 10000 | M23: =K23-D23 -> 0
A24: 12 | B24: Gabion Works: Gabion Preparation, mesh forming etc. (size 2mx1mx1m) | C24: =conp!D19 -> m3 | D24: =conp!C19 -> 48 | E24: =conp!E19 -> 2500 | F24: =E24*D24 -> 120000 | G24: =conp!G19 -> 38 | H24: =G24*E24 -> 95000 | K24: =I24+G24 -> 38 | L24: =H24+J24 -> 95000 | M24: =K24-D24 -> -10
A25: 13 | B25: Gabion Works: Filling of gabion box with stones | C25: =conp!D20 -> m3 | D25: =conp!C20 -> 48 | E25: =conp!E20 -> 2500 | F25: =E25*D25 -> 120000 | G25: =conp!G20 -> 38 | H25: =G25*E25 -> 95000 | K25: =I25+G25 -> 38 | L25: =H25+J25 -> 95000 | M25: =K25-D25 -> -10
B26: Total | F26: =ROUND(SUM(F14:F25),0) -> 5950359 | H26: =SUM(H14:H25) -> 2216502.1 | L26: =SUM(L14:L25) -> 2216502.1 | M26: =K26-D26 -> 0
B27: 13 % VAT | F27: =F26*13% -> 773546.67 | H27: =H26*13% -> 288145.28 | L27: =L26*13% -> 288145.28 | M27: =K27-D27 -> 0
C28: Total with VAT | F28: =SUM(F26:F27) -> 6723905.7 | H28: =SUM(H26:H27) -> 2504647.4 | L28: =SUM(L26:L27) -> 2504647.4 | M28: =K28-D28 -> 0
B29: Provisional sum
A30: 14 | B30: Project Information Board | C30: ='[64]abstract contract'!D88 -> ps | D30: ='[64]abstract contract'!C88 -> 1 | E30: 5000 | F30: =D30*E30 -> 5000 | G30: ='[64]abstract contract'!G88 -> 1 | H30: ='Valuated abstract'!E27 -> 5000 | K30: =G30+I30 -> 1 | L30: =H30+J30 -> 5000
A31: 15 | B31: Lab Test Report | C31: ='[64]abstract contract'!D89 -> ps | D31: ='[64]abstract contract'!C89 -> 1 | E31: 20000 | F31: =D31*E31 -> 20000 | G31: ='[64]abstract contract'!G89 -> 1 | H31: 0 | K31: =G31+I31 -> 1 | L31: =H31+J31 -> 0
A32: 16 | B32: Insurance | C32: ='[64]abstract contract'!D90 -> ps | D32: ='[64]abstract contract'!C90 -> 1 | E32: 20000 | F32: =D32*E32 -> 20000 | G32: ='[64]abstract contract'!G90 -> 1 | H32: 0 | K32: =G32+I32 -> 1 | L32: =H32+J32 -> 0
A33: 17 | B33: Other necessary fittings as required on site | C33: ='[64]abstract contract'!D91 -> ps | D33: ='[64]abstract contract'!C91 -> 1 | E33: 100000 | F33: =D33*E33 -> 100000 | G33: ='[64]abstract contract'!G91 -> 1 | H33: 0 | K33: =G33+I33 -> 1 | L33: =H33+J33 -> 0
B35: Grand total Rs. | F35: =SUM(F28:F34) -> 6868905.7 | H35: =SUM(H28:H34) -> 2509647.4 | L35: =SUM(L28:L34) -> 2509647.4
B36: उपर्युक्त बमोजिम ठीक छ भनी प्रमाणित गर्नेको सही ः–
B37: यो बमोजिमको जम्मा रु. | D37: =L35 -> 2509647.4 | G37: भ्याट सहित | J37: ङ) धरौटी @5% का दरले | L37: =H26*5% -> 110825.11
B38: अघिल्लो बिलबाट भुक्तानी भएको रु. | D38: =J35 -> 0 | G38: भ्याट सहित | J38: च) अग्रीम आयकरः – 1.5% का दरले जम्मा रु.
B39: बाँकी दिनु पर्ने रु. | D39: =D37-D38 -> 2509647.4 | G39: भ्याट सहित | J39: ठेकेदारको सही ः–
B40: कट्टा गर्नू पर्ने रु | J40: खुद दिनु पर्ने रु.
B41: क) पेश्की | J41: जम्मा रु: …………………..……...अक्षेरेपी...............को चेक नं
B43: नाप जाँच गर्नेको सही | E43: चेक गर्नेको सही | L43: स्वीकृत गर्नेको सही

Sheet Valuated abstract
A1: Shankharapur Municipality
A2: Office of Municipal Executive
A3: Sankhu, Kathmandu
A4: Abstract of Valuated Cost
A5: Bill No.: First Running Bill
A6: Contractors Name: Consolidated Builders and Engineers Pvt. Ltd., lalitpur
A7: Contract No.: SMO/078/79/51
A8: Project:- Sankhu Khanepaani | G8: Date: 2079/03/09
A9: Location:- Shankharapur Municipality-06,07
D10: FY :78/79
A11: S.N. | B11: Description of work | C11: Quantity | D11: Unit | E11: Rate | F11: Amount | G11: Remarks | H11: ‍
A12: 1 | B12: Earthworks in excavation in hard soil as per standard specification | C12: ='Detail Measurement'!G24 -> 80.463825 | D12: m3 | E12: 300 | F12: =C12*E12 -> 24139.148
A13: 2 | B13: Backfilling with Hard Soil as per standard specifications all complete | C13: ='Detail Measurement'!G28 -> 0 | D13: m3 | E13: 80 | F13: =C13*E13 -> 0
A14: 3 | B14: Dry Stone Soling in foundation in perfect line and level all complete | C14: ='Detail Measurement'!G39 -> 27.00825 | D14: m3 | E14: 4000 | F14: =C14*E14 -> 108033
A15: 4 | B15: Providing and laying of 1:2:4 PCC as per drawing and Standard specifications all complete | C15: ='Detail Measurement'!G52 -> 15.56925 | D15: m3 | E15: 9000 | F15: =C15*E15 -> 140123.25
A16: 5 | B16: Providing Plaster works 1:4 , 12.5mm with 3mm punning all complete as per standard specifications | C16: ='Detail Measurement'!G59 -> 22.2065 | D16: m2 | E16: 400 | F16: =C16*E16 -> 8882.6
A17: 6 | B17: Providing of Form work for concrete work in shear wall,etc as per standard norms and specifications all complete | C17: ='Detail Measurement'!G67 -> 323.2655 | D17: m2 | E17: 750 | F17: =C17*E17 -> 242449.13
A18: 7 | B18: PCC for RCC works in CSA 1:1.5:3 (ढलानको कार्य) with water proofing chemical all complete in water tank and slab cover | C18: ='Detail Measurement'!G96 -> 52.91553 | D18: m3 | E18: 12000 | F18: =C18*E18 -> 634986.36
A19: 8 | B19: Cutting , bending and laying of Reinforcement works FE-500 as per given drawing and standard specifications all complete | C19: ='Detail Measurement'!G108 -> 3508.7322 | D19: kg | E19: 105 | F19: =C19*E19 -> 368416.88
A20: 9 | B20: Random Rubble Stone Masonry in C/S 1:4 including weep holes in perfect line and level with proper curing all complete. | C20: ='Detail Measurement'!G118 -> 97.89435 | D20: m3 | E20: 5000 | F20: =C20*E20 -> 489471.75
A21: 11 | B21: Supply and fitting of Rectangular 24"x24" (50 kg) C.I. tank manhole Cover locking types for burkamala Intake | C21: ='Detail Measurement'!G121 -> 2 | D21: Nos | E21: 5000 | F21: =C21*E21 -> 10000
A22: 12 | B22: Gabion Works: Gabion Preparation, mesh forming etc. (size 2mx1mx1m) | C22: ='Detail Measurement'!G123 -> 38 | D22: m3 | E22: 2500 | F22: =C22*E22 -> 95000
A23: 13 | B23: Gabion Works: Filling of gabion box with stones | C23: ='Detail Measurement'!G125 -> 38 | D23: m3 | E23: 2500 | F23: =C23*E23 -> 95000
E24: Sub Total | F24: =SUM(F12:F23) -> 2216502.1
E25: VAT 13% | F25: =F24*0.13 -> 288145.28
E26: Total | F26: =SUM(F24:F25) -> 2504647.4
A27: 14 | B27: Project Information Board | C27: ='Estimate '!G94 -> 1 | D27: ps | E27: 5000 | F27: =C27*E27 -> 5000
A28: 15 | B28: Lab Test Report | C28: ='Estimate '!G96 -> 1 | D28: ps | F28: =C28*E28 -> 0
A29: 16 | B29: Insurance | C29: ='Estimate '!G98 -> 1 | D29: ps | F29: 0
A30: 17 | B30: Other necessary fittings as required on site | C30: ='Estimate '!G100 -> 1 | D30: ps | F30: =C30*E30 -> 0
E31: Total With VAT and PS | F31: =SUM(F26:F30) -> 2509647.4
E32: Contingencies 3% | F32: =F24*0.03 -> 66495.063
E33: Grand Total | F33: =SUM(F31:F32) -> 2576142.5 | H33: =F33*0.026 -> 66979.704

Sheet Detail Measurement
A1: Shankharapur Municipality
A2: Office of Municipal Executive
A3: Sankhu, Kathmandu
A4: Detail Measurement Sheet
A5: Bill No.: First Running Bill
A6: Contractors Name: Consolidated Builders and Engineers Pvt. Ltd., lalitpur
A7: Contract No.: SMO/078/79/51
A8: Project:- Sankhu Khanepaani | K8: Date: 2079/03/09
A9: Location:- Shankharapur Municipality-06,07
H10: FY :78/79
A11: S.N. | B11: Description of work | C11: No. | D11: Length | E11: Breadth | F11: Height | G11: Quantity | H11: Unit | I11: Rate | J11: Amount | K11: Remarks | L11: ‍
A12: 1 | B12: Earthworks in excavation in hard soil
B13: RCC drain | C13: 1 | D13: =D95 -> 61.05 | E13: 1.5 | F13: 0.3 | G13: =PRODUCT(C13:F13) -> 27.4725
B15: Retaining wall at boundary | C15: 1 | D15: =9.1+6.9+7.1+2.6 -> 25.7 | E15: 1.1 | F15: 0.6 | G15: =PRODUCT(C15:F15) -> 16.962
B17: Retaining wall near roughing filter | C17: 1 | D17: =14.8*2 -> 29.6 | E17: 0.75 | F17: 0.6 | G17: =PRODUCT(C17:F17) -> 13.32 | K17: two step
C18: 1 | D18: 4.35 | E18: 0.75 | F18: 0.3
B20: Retaining wall near the old intake | C20: 1 | D20: 2.8 | E20: 0.7 | F20: 0.6 | G20: =PRODUCT(C20:F20) -> 1.176
C21: 1 | D21: 1.4 | E21: 0.6 | F21: 0.6 | G21: =PRODUCT(C21:F21) -> 0.504
C22: 1 | D22: 1.5 | E22: 0.7 | F22: 0.6 | G22: =PRODUCT(C22:F22) -> 0.63
B23: Burkamala intake | G23: ='Intake (v)'!H9 -> 20.399325
G24: =SUM(G13:G23) -> 80.463825 | H24: m3 | I24: =Analysis!R24 -> 1480.63 | J24: =G24*I24 -> 119137.15
A26: 2 | B26: Backfilling with Hard Soil
B27: Behind retaining wall
G28: =SUM(G27:G27) -> 0 | H28: m3 | I28: =Analysis!R30 -> 746.24 | J28: =G28*I28 -> 0
